Workbook

Sheet Sheet
N1: BASE INSS | P1: BASE GERAL FOLHA | R1: VALOR SALARIO FAMILIA | S1: 20% PATRONAL | T1: 5,8% TERCEIROS | U1: RAT AJUSTADO 3x FAP 1,0312 | W1: VALOR GUIA LANÇAMENTO INSS | X1: IRRF FOLHA
N2: PROLABORE | O2: 8475.55 | P2: =P4+O2 -> 339404.33 | Q2: =eSocial!XEI17 -> 339404.33 | R2: 87.8 | T2: =eSocial!XEK29 -> 19193.84 | U2: 3 | V2: 1.0312 | W2: =S6+T3+V4+P10-R2 -> 126592.04 | X2: 4632.58
P3: BASE TOTAL FOLHA | T3: =P4*0.058 -> 19193.869 | V3: =U2*V2 -> 3.0936
N4: =N11 -> 320213.14 | O4: 10715.64 | P4: =O4+N4 -> 330928.78 | S4: =O2*0.2 -> 1695.11 | T4: =eSocial!XEI28 -> 1695.11 | V4: =P4*(V3/100) -> 10237.613 | W4: =eSocial!XEI34 -> 10237.61 | X4: VALOR GUIA eCAC | Y4: =W2+X2 -> 131224.62
S5: =P4*0.2 -> 66185.756 | T5: =eSocial!XEI27 -> 66185.75
P6: 27471.49 | S6: =SUM(S4:S5) -> 67880.866
P7: 160.11
P8: 932.31 | Q8: =P6+P8 -> 28403.8 | S8: 5069.08 | T8: 124896.91 | U8: =T8+S4 -> 126592.02
P9: 803.58 | S9: 1695.13
P10: =SUM(P6:P9) -> 29367.49 | Q10: =eSocial!XEJ19 -> 29367.49
N11: =N150 -> 320213.14 | O11: =O150 -> 10715.64 | P11: =P150 -> 28403.8 | Q11: =Q150 -> 803.58 | R11: =R150 -> 160.11 | S11: =S151 -> 66185.756 | T11: =T151 -> 9927.8634 | U11: =U151 -> 19193.869 | V11: =V151 -> 124587.18 | W11: =W151 -> 326639.36 | X11: =X151 -> 2049.33 | Y11: =Y151 -> 4632.58 | Z11: =Z151 -> 0 | AA11: =AA151 -> 0
A12: NOME | B12: CCUSTO | C12: CODSITUACAO | D12: CODTIPO | E12: BASEFGTS | F12: BASEFGTSAVPREVIO | H12: BASEFGTS13AVPREVIO | I12: BASEFGTS13 | J12: FGTS | K12: FGTS_AVISO | L12: FGTS13_AVISO | M12: FGTS13 | N12: BASEINSS | O12: BASEINSS13 | P12: INSS | Q12: INSS13 | R12: INSSFERIAS | S12: INSS EMPRESA | T12: INSS RAT AJUSTADO | U12: INSS TERCEIROS | V12: TOTAL GUA | W12: BASEIRRF | X12: BASEIRRFFERIAS | Y12: IRRF | Z12: IRRF13 | AA12: IRRFFERIAS | AD12: Nome | AE12: Governo - Base INSS | AF12: Governo - Base INSS - 13° Salário | AG12: Governo - Valor INSS | AH12: Governo - Valor INSS - 13° Salário | AI12: CONFERE BASE FGTS | AJ12: CONFERE VALOR FGTS | AK12: Nome Trabalhador | AL12: Base Remuneracao Total | AM12: Valor FGTS na Guia
A13: ADNNY DA SILVA PITANGA | B13: BR - 060/GO - Rio Verde GO | C13: D | D13: N | E13: 1467.94 | F13: 613.89 | H13: 0 | I13: 602.59 | J13: 117.4352 | K13: 49.1112 | L13: 0 | M13: 48.2072 | N13: 1467.94 | O13: 602.59 | P13: 110.09 | Q13: 45.19 | R13: 0 | S13: 414.106 | T13: 62.1159 | U13: 120.09074 | V13: 751.59264 | W13: 1467.94 | X13: 0 | Y13: 0 | Z13: 0 | AA13: 0 | AB13: =(N13+O13)-(AE13+AF13) -> 0 | AC13: =(P13+Q13)-(AG13+AH13) -> 0 | AD13: ADNNY DA SILVA PITANGA | AE13: 1467.94 | AF13: 602.59 | AG13: 110.09 | AH13: 45.19 | AI13: =(E13+F13+H13+I13)-AL13 -> 2684.42 | AJ13: =(J13+K13+L13+M13)-AM13 -> 214.7536
A14: ADRYAN ANDRADE ESPIRITO SANTO | B14: BR - 060/GO - Rio Verde GO | C14: D | D14: N | E14: 1429.82 | F14: 612.64 | H14: 0 | I14: 601.71 | J14: 114.3856 | K14: 49.0112 | L14: 0 | M14: 48.1368 | N14: 1429.82 | O14: 601.71 | P14: 107.23 | Q14: 45.12 | R14: 0 | S14: 406.306 | T14: 60.9459 | U14: 117.82874 | V14: 737.43064 | W14: 1429.82 | X14: 0 | Y14: 0 | Z14: 0 | AA14: 0 | AB14: =(N14+O14)-(AE14+AF14) -> 0 | AC14: =(P14+Q14)-(AG14+AH14) -> 0 | AD14: ADRYAN ANDRADE ESPIRITO SANTO | AE14: 1429.82 | AF14: 601.71 | AG14: 107.23 | AH14: 45.12 | AI14: =(E14+F14+H14+I14)-AL14 -> 2644.17 | AJ14: =(J14+K14+L14+M14)-AM14 -> 211.5336
A15: ALDECIR DA SILVA | B15: BR-463/MS - Dourados | C15: A | D15: N | E15: 1981.3 | F15: 0 | H15: 0 | I15: 0 | J15: 158.504 | K15: 0 | L15: 0 | M15: 0 | N15: 1981.3 | O15: 0 | P15: 153.99 | Q15: 0 | R15: 0 | S15: 396.26 | T15: 59.439 | U15: 114.9154 | V15: 724.6044 | W15: 1981.3 | X15: 0 | Y15: 0 | Z15: 0 | AA15: 0 | AB15: =(N15+O15)-(AE15+AF15) -> 0 | AC15: =(P15+Q15)-(AG15+AH15) -> 0 | AD15: ALDECIR DA SILVA | AE15: 1981.3 | AF15: 0 | AG15: 153.99 | AH15: 0 | AI15: =(E15+F15+H15+I15)-AL15 -> 0 | AJ15: =(J15+K15+L15+M15)-AM15 -> 0.004 | AK15: ALDECIR DA SILVA | AL15: 1981.3 | AM15: 158.5
A16: ALDO PLACIDO DE ESPIRITO SANTO | B16: Oficina | C16: A | D16: N | E16: 3353.75 | F16: 0 | H16: 0 | I16: 0 | J16: 268.3 | K16: 0 | L16: 0 | M16: 0 | N16: 3353.75 | O16: 0 | P16: 291.03 | Q16: 0 | R16: 0 | S16: 670.75 | T16: 100.6125 | U16: 194.5175 | V16: 1256.91 | W16: 3353.75 | X16: 0 | Y16: 0 | Z16: 0 | AA16: 0 | AB16: =(N16+O16)-(AE16+AF16) -> 0 | AC16: =(P16+Q16)-(AG16+AH16) -> 0 | AD16: ALDO PLACIDO DE ESPIRITO SANTO | AE16: 3353.75 | AF16: 0 | AG16: 291.03 | AH16: 0 | AI16: =(E16+F16+H16+I16)-AL16 -> 0 | AJ16: =(J16+K16+L16+M16)-AM16 -> 0 | AK16: ALDO PLACIDO DE ESPIRITO SANTO | AL16: 3353.75 | AM16: 268.3
A17: ALESSANDRO OMIDO DA SILVA | B17: Oficina | C17: A | D17: N | E17: 4571.03 | F17: 0 | H17: 0 | I17: 0 | J17: 365.6824 | K17: 0 | L17: 0 | M17: 0 | N17: 4571.03 | O17: 0 | P17: 441.44 | Q17: 0 | R17: 0 | S17: 914.206 | T17: 137.1309 | U17: 265.11974 | V17: 1757.8966 | W17: 4571.03 | X17: 0 | Y17: 0 | Z17: 0 | AA17: 0 | AB17: =(N17+O17)-(AE17+AF17) -> 0 | AC17: =(P17+Q17)-(AG17+AH17) -> 0 | AD17: ALESSANDRO OMIDO DA SILVA | AE17: 4571.03 | AF17: 0 | AG17: 441.44 | AH17: 0 | AI17: =(E17+F17+H17+I17)-AL17 -> 0 | AJ17: =(J17+K17+L17+M17)-AM17 -> 0.0024 | AK17: ALESSANDRO OMIDO DA SILVA | AL17: 4571.03 | AM17: 365.68
A18: ALISSON ALVES DA CRUZ | B18: BR-376/MS - Nova Andradina / Ivinhema | C18: A | D18: N | E18: 1947.01 | F18: 0 | H18: 0 | I18: 0 | J18: 155.7608 | K18: 0 | L18: 0 | M18: 0 | N18: 1947.01 | O18: 0 | P18: 150.91 | Q18: 0 | R18: 0 | S18: 389.402 | T18: 58.4103 | U18: 112.92658 | V18: 711.64888 | W18: 1947.01 | X18: 0 | Y18: 0 | Z18: 0 | AA18: 0 | AB18: =(N18+O18)-(AE18+AF18) -> 0 | AC18: =(P18+Q18)-(AG18+AH18) -> 0 | AD18: ALISSON ALVES DA CRUZ | AE18: 1947.01 | AF18: 0 | AG18: 150.91 | AH18: 0 | AI18: =(E18+F18+H18+I18)-AL18 -> 0 | AJ18: =(J18+K18+L18+M18)-AM18 -> 0.0008 | AK18: ALISSON ALVES DA CRUZ | AL18: 1947.01 | AM18: 155.76
A19: ALOIR DE SOUZA VIANA | B19: BR - 262/MS - Miranda - Guaicurus MS | C19: D | D19: N | E19: 987.59 | F19: 2511.45 | H19: 184.63 | I19: 553.87 | J19: 79.0072 | K19: 200.916 | L19: 14.7704 | M19: 44.3096 | N19: 987.59 | O19: 738.5 | P19: 74.06 | Q19: 55.38 | R19: 0 | S19: 345.218 | T19: 51.7827 | U19: 100.11322 | V19: 626.55392 | W19: 987.59 | X19: 0 | Y19: 0 | Z19: 0 | AA19: 0 | AB19: =(N19+O19)-(AE19+AF19) -> 0 | AC19: =(P19+Q19)-(AG19+AH19) -> 0 | AD19: ALOIR DE SOUZA VIANA | AE19: 987.59 | AF19: 738.5 | AG19: 74.06 | AH19: 55.38 | AI19: =(E19+F19+H19+I19)-AL19 -> 4237.54 | AJ19: =(J19+K19+L19+M19)-AM19 -> 339.0032
A20: ANDERSEN GUASSACE RODRIGUES | B20: BR-262 e 359/MS - Corumbá - 2º Contrato | C20: D | D20: N | E20: 196.14 | F20: 0 | H20: 0 | I20: 0 | J20: 15.6912 | K20: 0 | L20: 0 | M20: 0 | N20: 196.14 | O20: 0 | P20: 14.71 | Q20: 0 | R20: 0 | S20: 39.228 | T20: 5.8842 | U20: 11.37612 | V20: 71.19832 | W20: 196.14 | X20: 0 | Y20: 0 | Z20: 0 | AA20: 0 | AB20: =(N20+O20)-(AE20+AF20) -> 0 | AC20: =(P20+Q20)-(AG20+AH20) -> 0 | AD20: ANDERSEN GUASSACE RODRIGUES | AE20: 196.14 | AF20: 0 | AG20: 14.71 | AH20: 0 | AI20: =(E20+F20+H20+I20)-AL20 -> 0 | AJ20: =(J20+K20+L20+M20)-AM20 -> 0.0012 | AK20: ANDERSEN GUASSACE RODRIGUES | AL20: 196.14 | AM20: 15.69
A21: ANDRE AUGUSTO CAVALHEIRO DA SILVA | B21: BR - 267/MS - Nova Alvorada MS - 2º Contrato | C21: A | D21: N | E21: 2012.88 | F21: 0 | H21: 0 | I21: 0 | J21: 161.0304 | K21: 0 | L21: 0 | M21: 0 | N21: 2012.88 | O21: 0 | P21: 156.83 | Q21: 0 | R21: 0 | S21: 402.576 | T21: 60.3864 | U21: 116.74704 | V21: 736.53944 | W21: 2012.88 | X21: 0 | Y21: 0 | Z21: 0 | AA21: 0 | AB21: =(N21+O21)-(AE21+AF21) -> 0 | AC21: =(P21+Q21)-(AG21+AH21) -> 0 | AD21: ANDRE AUGUSTO CAVALHEIRO DA SILVA | AE21: 2012.88 | AF21: 0 | AG21: 156.83 | AH21: 0 | AI21: =(E21+F21+H21+I21)-AL21 -> 0 | AJ21: =(J21+K21+L21+M21)-AM21 -> 0.0004 | AK21: ANDRE AUGUSTO CAVALHEIRO DA SILVA | AL21: 2012.88 | AM21: 161.03
A22: ANDREIA PERPETUA MORENO | B22: Oficina | C22: A | D22: N | E22: 2700 | F22: 0 | H22: 0 | I22: 0 | J22: 216 | K22: 0 | L22: 0 | M22: 0 | N22: 2700 | O22: 0 | P22: 218.68 | Q22: 0 | R22: 0 | S22: 540 | T22: 81 | U22: 156.6 | V22: 996.28 | W22: 2700 | X22: 0 | Y22: 0 | Z22: 0 | AA22: 0 | AB22: =(N22+O22)-(AE22+AF22) -> 0 | AC22: =(P22+Q22)-(AG22+AH22) -> 0 | AD22: ANDREIA PERPETUA MORENO | AE22: 2700 | AF22: 0 | AG22: 218.68 | AH22: 0 | AI22: =(E22+F22+H22+I22)-AL22 -> 0 | AJ22: =(J22+K22+L22+M22)-AM22 -> 0 | AK22: ANDREIA PERPETUA MORENO | AL22: 2700 | AM22: 216
A23: ANTONIO MARCOS DE LIMA | B23: Oficina | C23: A | D23: N | E23: 3798.32 | F23: 0 | H23: 0 | I23: 0 | J23: 303.8656 | K23: 0 | L23: 0 | M23: 0 | N23: 3798.32 | O23: 0 | P23: 344.38 | Q23: 0 | R23: 0 | S23: 759.664 | T23: 113.9496 | U23: 220.30256 | V23: 1438.2962 | W23: 3798.32 | X23: 0 | Y23: 0 | Z23: 0 | AA23: 0 | AB23: =(N23+O23)-(AE23+AF23) -> 0 | AC23: =(P23+Q23)-(AG23+AH23) -> 0 | AD23: ANTONIO MARCOS DE LIMA | AE23: 3798.32 | AF23: 0 | AG23: 344.38 | AH23: 0 | AI23: =(E23+F23+H23+I23)-AL23 -> 0 | AJ23: =(J23+K23+L23+M23)-AM23 -> 0.0056 | AK23: ANTONIO MARCOS DE LIMA | AL23: 3798.32 | AM23: 303.86
A24: ANTONIO MARCOS DOS SANTOS MOREIRA | B24: Restaura MS180 - Juti MS | C24: A | D24: N | E24: 2161.49 | F24: 0 | H24: 0 | I24: 0 | J24: 172.9192 | K24: 0 | L24: 0 | M24: 0 | N24: 2161.49 | O24: 0 | P24: 170.21 | Q24: 0 | R24: 0 | S24: 432.298 | T24: 64.8447 | U24: 125.36642 | V24: 792.71912 | W24: 2161.49 | X24: 0 | Y24: 0 | Z24: 0 | AA24: 0 | AB24: =(N24+O24)-(AE24+AF24) -> 0 | AC24: =(P24+Q24)-(AG24+AH24) -> 0 | AD24: ANTONIO MARCOS DOS SANTOS MOREIRA | AE24: 2161.49 | AF24: 0 | AG24: 170.21 | AH24: 0 | AI24: =(E24+F24+H24+I24)-AL24 -> 0 | AJ24: =(J24+K24+L24+M24)-AM24 -> 0.0092 | AK24: ANTONIO MARCOS DOS SANTOS MOREIRA | AL24: 2161.49 | AM24: 172.91
A25: ARNALDO SALLES GUIMARAES | B25: BR-060/MS - Jardim - 2º Contrato | C25: A | D25: N | E25: 3560.44 | F25: 0 | H25: 0 | I25: 0 | J25: 284.8352 | K25: 0 | L25: 0 | M25: 0 | N25: 3560.44 | O25: 0 | P25: 315.84 | Q25: 0 | R25: 0 | S25: 712.088 | T25: 106.8132 | U25: 206.50552 | V25: 1341.2467 | W25: 3560.44 | X25: 0 | Y25: 0 | Z25: 0 | AA25: 0 | AB25: =(N25+O25)-(AE25+AF25) -> 0 | AC25: =(P25+Q25)-(AG25+AH25) -> 0 | AD25: ARNALDO SALLES GUIMARAES | AE25: 3560.44 | AF25: 0 | AG25: 315.84 | AH25: 0 | AI25: =(E25+F25+H25+I25)-AL25 -> 0 | AJ25: =(J25+K25+L25+M25)-AM25 -> 0.0052 | AK25: ARNALDO SALLES GUIMARAES | AL25: 3560.44 | AM25: 284.83
A26: CANDELARIO GARCIA MELGAR | B26: BR-262 e 359/MS - Corumbá - 2º Contrato | C26: A | D26: N | E26: 1606.37 | F26: 0 | H26: 0 | I26: 0 | J26: 128.5096 | K26: 0 | L26: 0 | M26: 0 | N26: 1606.37 | O26: 0 | P26: 120.47 | Q26: 0 | R26: 0 | S26: 321.274 | T26: 48.1911 | U26: 93.16946 | V26: 583.10456 | W26: 1606.37 | X26: 0 | Y26: 0 | Z26: 0 | AA26: 0 | AB26: =(N26+O26)-(AE26+AF26) -> 0 | AC26: =(P26+Q26)-(AG26+AH26) -> 0 | AD26: CANDELARIO GARCIA MELGAR | AE26: 1606.37 | AF26: 0 | AG26: 120.47 | AH26: 0 | AI26: =(E26+F26+H26+I26)-AL26 -> 0 | AJ26: =(J26+K26+L26+M26)-AM26 -> 0.0096 | AK26: CANDELARIO GARCIA MELGAR | AL26: 1606.37 | AM26: 128.5
A27: CARLA CRISTINA GAMBATTI | B27: Financeiro | C27: A | D27: N | E27: 2500 | F27: 0 | H27: 0 | I27: 0 | J27: 200 | K27: 0 | L27: 0 | M27: 0 | N27: 2500 | O27: 0 | P27: 200.68 | Q27: 0 | R27: 0 | S27: 500 | T27: 75 | U27: 145 | V27: 920.68 | W27: 2500 | X27: 0 | Y27: 0 | Z27: 0 | AA27: 0 | AB27: =(N27+O27)-(AE27+AF27) -> 0 | AC27: =(P27+Q27)-(AG27+AH27) -> 0 | AD27: CARLA CRISTINA GAMBATTI | AE27: 2500 | AF27: 0 | AG27: 200.68 | AH27: 0 | AI27: =(E27+F27+H27+I27)-AL27 -> 0 | AJ27: =(J27+K27+L27+M27)-AM27 -> 0 | AK27: CARLA CRISTINA GAMBATTI | AL27: 2500 | AM27: 200
A28: CARLOS DONIZETI BOTARO | B28: BR - 060/MS Contorno Campo Grande 2º Contrato | C28: A | D28: N | E28: 7907.32 | F28: 0 | H28: 0 | I28: 0 | J28: 632.5856 | K28: 0 | L28: 0 | M28: 0 | N28: 7907.32 | O28: 0 | P28: 908.52 | Q28: 0 | R28: 0 | S28: 1581.464 | T28: 237.2196 | U28: 458.62456 | V28: 3185.8282 | W28: 7907.32 | X28: 0 | Y28: 963.8 | Z28: 0 | AA28: 0 | AB28: =(N28+O28)-(AE28+AF28) -> 0 | AC28: =(P28+Q28)-(AG28+AH28) -> 0 | AD28: CARLOS DONIZETI BOTARO | AE28: 7907.32 | AF28: 0 | AG28: 908.52 | AH28: 0 | AI28: =(E28+F28+H28+I28)-AL28 -> 0 | AJ28: =(J28+K28+L28+M28)-AM28 -> 0.0056 | AK28: CARLOS DONIZETI BOTARO | AL28: 7907.32 | AM28: 632.58
A29: CARLOS HENRIQUE TREVISAN BARBOSA | B29: BR - 359/MS - Coxim MS | C29: D | D29: N | E29: 142.71 | F29: 0 | H29: 0 | I29: 0 | J29: 11.4168 | K29: 0 | L29: 0 | M29: 0 | N29: 142.71 | O29: 0 | P29: 10.7 | Q29: 0 | R29: 0 | S29: 28.542 | T29: 4.2813 | U29: 8.27718 | V29: 51.80048 | W29: 142.71 | X29: 0 | Y29: 0 | Z29: 0 | AA29: 0 | AB29: =(N29+O29)-(AE29+AF29) -> 0 | AC29: =(P29+Q29)-(AG29+AH29) -> 0 | AD29: CARLOS HENRIQUE TREVISAN BARBOSA | AE29: 142.71 | AF29: 0 | AG29: 10.7 | AH29: 0 | AI29: =(E29+F29+H29+I29)-AL29 -> 0 | AJ29: =(J29+K29+L29+M29)-AM29 -> 0.0068 | AK29: CARLOS HENRIQUE TREVISAN BARBOSA | AL29: 142.71 | AM29: 11.41
A30: CARLOS MORAES | B30: BR-060/MS - Jardim - 2º Contrato | C30: A | D30: N | E30: 1990.05 | F30: 0 | H30: 0 | I30: 0 | J30: 159.204 | K30: 0 | L30: 0 | M30: 0 | N30: 1990.05 | O30: 0 | P30: 154.78 | Q30: 0 | R30: 0 | S30: 398.01 | T30: 59.7015 | U30: 115.4229 | V30: 727.9144 | W30: 1990.05 | X30: 0 | Y30: 0 | Z30: 0 | AA30: 0 | AB30: =(N30+O30)-(AE30+AF30) -> 0 | AC30: =(P30+Q30)-(AG30+AH30) -> 0 | AD30: CARLOS MORAES | AE30: 1990.05 | AF30: 0 | AG30: 154.78 | AH30: 0 | AI30: =(E30+F30+H30+I30)-AL30 -> 0 | AJ30: =(J30+K30+L30+M30)-AM30 -> 0.004 | AK30: CARLOS MORAES | AL30: 1990.05 | AM30: 159.2
A31: CHARLES FRANCO RODRIGUES | B31: Restaura MS180 - Juti MS | C31: A | D31: N | E31: 2068.35 | F31: 0 | H31: 0 | I31: 0 | J31: 165.468 | K31: 0 | L31: 0 | M31: 0 | N31: 2068.35 | O31: 0 | P31: 161.83 | Q31: 0 | R31: 0 | S31: 413.67 | T31: 62.0505 | U31: 119.9643 | V31: 757.5148 | W31: 2068.35 | X31: 0 | Y31: 0 | Z31: 0 | AA31: 0 | AB31: =(N31+O31)-(AE31+AF31) -> 0 | AC31: =(P31+Q31)-(AG31+AH31) -> 0 | AD31: CHARLES FRANCO RODRIGUES | AE31: 2068.35 | AF31: 0 | AG31: 161.83 | AH31: 0 | AI31: =(E31+F31+H31+I31)-AL31 -> 0 | AJ31: =(J31+K31+L31+M31)-AM31 -> 0.008 | AK31: CHARLES FRANCO RODRIGUES | AL31: 2068.35 | AM31: 165.46
... A41: EDER AUGUSTO TREVISAN BARBOSA | B41: BR - 060/MS - Sidrolândia MS | C41: A | D41: N | E41: 3013.01 | F41: 0 | H41: 0 | I41: 0 | J41: 241.0408 | K41: 0 | L41: 0 | M41: 0 | N41: 3013.01 | O41: 0 | P41: 250.15 | Q41: 0 | R41: 0 | S41: 602.602 | T41: 90.3903 | U41: 174.75458 | V41: 1117.8969 | W41: 3013.01 | X41: 0 | Y41: 0 | Z41: 0 | AA41: 0 | AB41: =(N41+O41)-(AE41+AF41) -> 0 | AC41: =(P41+Q41)-(AG41+AH41) -> 0 | AD41: EDER AUGUSTO TREVISAN BARBOSA | AE41: 3013.01 | AF41: 0 | AG41: 250.15 | AH41: 0 | AI41: =(E41+F41+H41+I41)-AL41 -> 0 | AJ41: =(J41+K41+L41+M41)-AM41 -> 0.0008 | AK41: EDER AUGUSTO TREVISAN BARBOSA | AL41: 3013.01 | AM41: 241.04
A42: EDIVANIO RODRIGUES DA SILVA | B42: BR - 060/GO - Rio Verde GO | C42: D | D42: N | E42: 2706.69 | F42: 0 | H42: 0 | I42: 610.23 | J42: 216.5352 | K42: 0 | L42: 0 | M42: 48.8184 | N42: 2706.69 | O42: 610.23 | P42: 219.28 | Q42: 45.76 | R42: 0 | S42: 663.384 | T42: 99.5076 | U42: 192.38136 | V42: 1220.313 | W42: 2706.69 | X42: 0 | Y42: 0 | Z42: 0 | AA42: 0 | AB42: =(N42+O42)-(AE42+AF42) -> 0 | AC42: =(P42+Q42)-(AG42+AH42) -> 0 | AD42: EDIVANIO RODRIGUES DA SILVA | AE42: 2706.69 | AF42: 610.23 | AG42: 219.28 | AH42: 45.76 | AI42: =(E42+F42+H42+I42)-AL42 -> 3316.92 | AJ42: =(J42+K42+L42+M42)-AM42 -> 265.3536
A43: EDUARDO BATISTA MOREIRA | B43: Restaura MS180 - Juti MS | C43: A | D43: N | E43: 644.03 | F43: 0 | H43: 0 | I43: 0 | J43: 51.5224 | K43: 0 | L43: 0 | M43: 0 | N43: 644.03 | O43: 0 | P43: 48.3 | Q43: 0 | R43: 0 | S43: 128.806 | T43: 19.3209 | U43: 37.35374 | V43: 233.78064 | W43: 644.03 | X43: 0 | Y43: 0 | Z43: 0 | AA43: 0 | AB43: =(N43+O43)-(AE43+AF43) -> 0 | AC43: =(P43+Q43)-(AG43+AH43) -> 0 | AD43: EDUARDO BATISTA MOREIRA | AE43: 644.03 | AF43: 0 | AG43: 48.3 | AH43: 0 | AI43: =(E43+F43+H43+I43)-AL43 -> 0 | AJ43: =(J43+K43+L43+M43)-AM43 -> 0.0024 | AK43: EDUARDO BATISTA MOREIRA | AL43: 644.03 | AM43: 51.52
A44: ELERRANDRO DUTRA SOUSA | B44: BR - 060/GO - Rio Verde GO | C44: D | D44: N | E44: 1551.26 | F44: 908.66 | H44: 0 | I44: 611.41 | J44: 124.1008 | K44: 72.6928 | L44: 0 | M44: 48.9128 | N44: 1551.26 | O44: 611.41 | P44: 116.34 | Q44: 45.85 | R44: 0 | S44: 432.534 | T44: 64.8801 | U44: 125.43486 | V44: 785.03896 | W44: 1551.26 | X44: 0 | Y44: 0 | Z44: 0 | AA44: 0 | AB44: =(N44+O44)-(AE44+AF44) -> 0 | AC44: =(P44+Q44)-(AG44+AH44) -> 0 | AD44: ELERRANDRO DUTRA SOUSA | AE44: 1551.26 | AF44: 611.41 | AG44: 116.34 | AH44: 45.85 | AI44: =(E44+F44+H44+I44)-AL44 -> 3071.33 | AJ44: =(J44+K44+L44+M44)-AM44 -> 245.7064
A45: ELIAQUIM SANTOS MACHADO | B45: BR - 060/GO - Rio Verde GO | C45: D | D45: N | E45: 1539.48 | F45: 618.45 | H45: 0 | I45: 606.71 | J45: 123.1584 | K45: 49.476 | L45: 0 | M45: 48.5368 | N45: 1539.48 | O45: 606.71 | P45: 115.46 | Q45: 45.5 | R45: 0 | S45: 429.238 | T45: 64.3857 | U45: 124.47902 | V45: 779.06272 | W45: 1539.48 | X45: 0 | Y45: 0 | Z45: 0 | AA45: 0 | AB45: =(N45+O45)-(AE45+AF45) -> 0 | AC45: =(P45+Q45)-(AG45+AH45) -> 0 | AD45: ELIAQUIM SANTOS MACHADO | AE45: 1539.48 | AF45: 606.71 | AG45: 115.46 | AH45: 45.5 | AI45: =(E45+F45+H45+I45)-AL45 -> 2764.64 | AJ45: =(J45+K45+L45+M45)-AM45 -> 221.1712
A46: ELIAS FREITAS DE MIRANDA | B46: BR - 359/MS - Coxim MS | C46: A | D46: N | E46: 2024.69 | F46: 0 | H46: 0 | I46: 0 | J46: 161.9752 | K46: 0 | L46: 0 | M46: 0 | N46: 2024.69 | O46: 0 | P46: 157.9 | Q46: 0 | R46: 0 | S46: 404.938 | T46: 60.7407 | U46: 117.43202 | V46: 741.01072 | W46: 2024.69 | X46: 0 | Y46: 0 | Z46: 0 | AA46: 0 | AB46: =(N46+O46)-(AE46+AF46) -> 0 | AC46: =(P46+Q46)-(AG46+AH46) -> 0 | AD46: ELIAS FREITAS DE MIRANDA | AE46: 2024.69 | AF46: 0 | AG46: 157.9 | AH46: 0 | AI46: =(E46+F46+H46+I46)-AL46 -> 0 | AJ46: =(J46+K46+L46+M46)-AM46 -> 0.0052 | AK46: ELIAS FREITAS DE MIRANDA | AL46: 2024.69 | AM46: 161.97
A47: ELIUDI DANIEL | B47: BR-463/MS - Dourados | C47: A | D47: N | E47: 1987.4 | F47: 0 | H47: 0 | I47: 0 | J47: 158.992 | K47: 0 | L47: 0 | M47: 0 | N47: 1987.4 | O47: 0 | P47: 154.54 | Q47: 0 | R47: 0 | S47: 397.48 | T47: 59.622 | U47: 115.2692 | V47: 726.9112 | W47: 1987.4 | X47: 0 | Y47: 0 | Z47: 0 | AA47: 0 | AB47: =(N47+O47)-(AE47+AF47) -> 0 | AC47: =(P47+Q47)-(AG47+AH47) -> 0 | AD47: ELIUDI DANIEL | AE47: 1987.4 | AF47: 0 | AG47: 154.54 | AH47: 0 | AI47: =(E47+F47+H47+I47)-AL47 -> 0 | AJ47: =(J47+K47+L47+M47)-AM47 -> 0.002 | AK47: ELIUDI DANIEL | AL47: 1987.4 | AM47: 158.99
A48: ELIZABETE DUARTE DA SILVA | B48: Restaura MS180 - Juti MS | C48: A | D48: N | E48: 1067.17 | F48: 0 | H48: 0 | I48: 0 | J48: 85.3736 | K48: 0 | L48: 0 | M48: 0 | N48: 1067.17 | O48: 0 | P48: 80.03 | Q48: 0 | R48: 0 | S48: 213.434 | T48: 32.0151 | U48: 61.89586 | V48: 319.83496 | W48: 1067.17 | X48: 0 | Y48: 0 | Z48: 0 | AA48: 0 | AB48: =(N48+O48)-(AE48+AF48) -> 0 | AC48: =(P48+Q48)-(AG48+AH48) -> 0 | AD48: ELIZABETE DUARTE DA SILVA | AE48: 1067.17 | AF48: 0 | AG48: 80.03 | AH48: 0 | AI48: =(E48+F48+H48+I48)-AL48 -> 0 | AJ48: =(J48+K48+L48+M48)-AM48 -> 0.0036 | AK48: ELIZABETE DUARTE DA SILVA | AL48: 1067.17 | AM48: 85.37
A49: ELTON DA SILVA FONSECA | B49: Restaura MS180 - Juti MS | C49: A | D49: N | E49: 5600.47 | F49: 0 | H49: 0 | I49: 0 | J49: 448.0376 | K49: 0 | L49: 0 | M49: 0 | N49: 5600.47 | O49: 0 | P49: 585.56 | Q49: 0 | R49: 0 | S49: 1120.094 | T49: 168.0141 | U49: 324.82726 | V49: 2198.4954 | W49: 5600.47 | X49: 0 | Y49: 134.6 | Z49: 0 | AA49: 0 | AB49: =(N49+O49)-(AE49+AF49) -> 0 | AC49: =(P49+Q49)-(AG49+AH49) -> 0 | AD49: ELTON DA SILVA FONSECA | AE49: 5600.47 | AF49: 0 | AG49: 585.56 | AH49: 0 | AI49: =(E49+F49+H49+I49)-AL49 -> 0 | AJ49: =(J49+K49+L49+M49)-AM49 -> 0.0076 | AK49: ELTON DA SILVA FONSECA | AL49: 5600.47 | AM49: 448.03
A50: ELTON DA SILVA SOARES | B50: BR - 060/MS - Sidrolândia MS | C50: A | D50: N | E50: 1972.81 | F50: 0 | H50: 0 | I50: 0 | J50: 157.8248 | K50: 0 | L50: 0 | M50: 0 | N50: 1972.81 | O50: 0 | P50: 153.23 | Q50: 0 | R50: 0 | S50: 394.562 | T50: 59.1843 | U50: 114.42298 | V50: 721.39928 | W50: 1972.81 | X50: 0 | Y50: 0 | Z50: 0 | AA50: 0 | AB50: =(N50+O50)-(AE50+AF50) -> 0 | AC50: =(P50+Q50)-(AG50+AH50) -> 0 | AD50: ELTON DA SILVA SOARES | AE50: 1972.81 | AF50: 0 | AG50: 153.23 | AH50: 0 | AI50: =(E50+F50+H50+I50)-AL50 -> 0 | AJ50: =(J50+K50+L50+M50)-AM50 -> 0.0048 | AK50: ELTON DA SILVA SOARES | AL50: 1972.81 | AM50: 157.82
A51: ERLON BRUNO DA CONCEICAO ALVES | B51: BR-262 e 359/MS - Corumbá - 2º Contrato | C51: A | D51: N | E51: 2024.56 | F51: 0 | H51: 0 | I51: 0 | J51: 161.9648 | K51: 0 | L51: 0 | M51: 0 | N51: 2024.56 | O51: 0 | P51: 157.89 | Q51: 0 | R51: 0 | S51: 404.912 | T51: 60.7368 | U51: 117.42448 | V51: 740.96328 | W51: 2024.56 | X51: 0 | Y51: 0 | Z51: 0 | AA51: 0 | AB51: =(N51+O51)-(AE51+AF51) -> 0 | AC51: =(P51+Q51)-(AG51+AH51) -> 0 | AD51: ERLON BRUNO DA ONCEICAO ALVES | AE51: 2024.56 | AF51: 0 | AG51: 157.89 | AH51: 0 | AI51: =(E51+F51+H51+I51)-AL51 -> 0 | AJ51: =(J51+K51+L51+M51)-AM51 -> 0.0048 | AK51: ERLON BRUNO DA CONCEICAO ALVES | AL51: 2024.56 | AM51: 161.96
A52: EVALDO BENEDITO CONSTANTINO | B52: BR - 359/MS - Coxim MS | C52: A | D52: N | E52: 6853.09 | F52: 0 | H52: 0 | I52: 0 | J52: 548.2472 | K52: 0 | L52: 0 | M52: 0 | N52: 6853.09 | O52: 0 | P52: 760.93 | Q52: 0 | R52: 0 | S52: 1370.618 | T52: 205.5927 | U52: 397.47922 | V52: 2734.6199 | W52: 6853.09 | X52: 0 | Y52: 700.44 | Z52: 0 | AA52: 0 | AB52: =(N52+O52)-(AE52+AF52) -> 0 | AC52: =(P52+Q52)-(AG52+AH52) -> 0 | AD52: EVALDO BENEDITO CONSTANTINO | AE52: 6853.09 | AF52: 0 | AG52: 760.93 | AH52: 0 | AI52: =(E52+F52+H52+I52)-AL52 -> 0 | AJ52: =(J52+K52+L52+M52)-AM52 -> 0.0072 | AK52: EVALDO BENEDITO CONSTANTINO | AL52: 6853.09 | AM52: 548.24
A53: EVANDRO ANTONIO JOAQUIM | B53: BR - 262/MS - Miranda - Guaicurus MS | C53: A | D53: N | E53: 1969.63 | F53: 0 | H53: 0 | I53: 0 | J53: 157.5704 | K53: 0 | L53: 0 | M53: 0 | N53: 1969.63 | O53: 0 | P53: 152.94 | Q53: 0 | R53: 0 | S53: 393.926 | T53: 59.0889 | U53: 114.23854 | V53: 720.19344 | W53: 1969.63 | X53: 0 | Y53: 0 | Z53: 0 | AA53: 0 | AB53: =(N53+O53)-(AE53+AF53) -> 0 | AC53: =(P53+Q53)-(AG53+AH53) -> 0 | AD53: EVANDRO ANTONIO JOAQUIM | AE53: 1969.63 | AF53: 0 | AG53: 152.94 | AH53: 0 | AI53: =(E53+F53+H53+I53)-AL53 -> 0 | AJ53: =(J53+K53+L53+M53)-AM53 -> 0.0004 | AK53: EVANDRO ANTONIO JOAQUIM | AL53: 1969.63 | AM53: 157.57
A54: FABIO VELASQUEZ GALEANO | B54: BR - 060/MS Contorno Campo Grande 2º Contrato | C54: A | D54: N | E54: 1499.86 | F54: 0 | H54: 0 | I54: 0 | J54: 119.9888 | K54: 0 | L54: 0 | M54: 0 | N54: 1499.86 | O54: 0 | P54: 112.48 | Q54: 0 | R54: 0 | S54: 299.972 | T54: 44.9958 | U54: 86.99188 | V54: 544.43968 | W54: 1499.86 | X54: 0 | Y54: 0 | Z54: 0 | AA54: 0 | AB54: =(N54+O54)-(AE54+AF54) -> 0 | AC54: =(P54+Q54)-(AG54+AH54) -> 0 | AD54: FABIO VELASQUEZ GALEANO | AE54: 1499.86 | AF54: 0 | AG54: 112.48 | AH54: 0 | AI54: =(E54+F54+H54+I54)-AL54 -> 0 | AJ54: =(J54+K54+L54+M54)-AM54 -> 0.0088 | AK54: FABIO VELASQUEZ GALEANO | AL54: 1499.86 | AM54: 119.98
A55: FELIPE DISTACIO LOPES | B55: Oficina | C55: A | D55: Z | E55: 1190 | F55: 0 | H55: 0 | I55: 0 | J55: =E55*0.02 -> 23.8 | K55: 0 | L55: 0 | M55: 0 | N55: 1190 | O55: 0 | P55: 89.25 | Q55: 0 | R55: 0 | S55: 238 | T55: 35.7 | U55: 69.02 | V55: 431.97 | W55: 1190 | X55: 0 | Y55: 0 | Z55: 0 | AA55: 0 | AB55: =(N55+O55)-(AE55+AF55) -> 0 | AC55: =(P55+Q55)-(AG55+AH55) -> 0 | AD55: FELIPE DISTACIO LOPES | AE55: 1190 | AF55: 0 | AG55: 89.25 | AH55: 0 | AI55: =(E55+F55+H55+I55)-AL55 -> 0 | AJ55: =(J55+K55+L55+M55)-AM55 -> 0 | AK55: FELIPE DISTACIO LOPES | AL55: 1190 | AM55: 23.8
A56: FELIPE GONZALES LIMA | B56: BR - 359/MS - Coxim MS | C56: A | D56: N | E56: 3444.95 | F56: 0 | H56: 0 | I56: 0 | J56: 275.596 | K56: 0 | L56: 0 | M56: 0 | N56: 3444.95 | O56: 0 | P56: 301.98 | Q56: 0 | R56: 0 | S56: 688.99 | T56: 103.3485 | U56: 199.8071 | V56: 1294.1256 | W56: 3444.95 | X56: 0 | Y56: 0 | Z56: 0 | AA56: 0 | AB56: =(N56+O56)-(AE56+AF56) -> 0 | AC56: =(P56+Q56)-(AG56+AH56) -> 0 | AD56: FELIPE GONZALES LIMA | AE56: 3444.95 | AF56: 0 | AG56: 301.98 | AH56: 0 | AI56: =(E56+F56+H56+I56)-AL56 -> 0 | AJ56: =(J56+K56+L56+M56)-AM56 -> 0.006 | AK56: FELIPE GONZALES LIMA | AL56: 3444.95 | AM56: 275.59
A57: FILIPE DOS SANTOS | B57: BR - 060/GO - Rio Verde GO | C57: D | D57: N | E57: 1313.69 | F57: 617.05 | H57: 0 | I57: 598.37 | J57: 105.0952 | K57: 49.364 | L57: 0 | M57: 47.8696 | N57: 1313.69 | O57: 598.37 | P57: 98.52 | Q57: 44.87 | R57: 0 | S57: 382.412 | T57: 57.3618 | U57: 110.89948 | V57: 694.06328 | W57: 1313.69 | X57: 0 | Y57: 0 | Z57: 0 | AA57: 0 | AB57: =(N57+O57)-(AE57+AF57) -> 0 | AC57: =(P57+Q57)-(AG57+AH57) -> 0 | AD57: FILIPE DOS SANTOS | AE57: 1313.69 | AF57: 598.37 | AG57: 98.52 | AH57: 44.87 | AI57: =(E57+F57+H57+I57)-AL57 -> 2529.11 | AJ57: =(J57+K57+L57+M57)-AM57 -> 202.3288
A58: FLAVIO CARLOS DE SOUZA ORTEGA | B58: BR-060/MS - Pedra / Nioaque | C58: V | D58: N | E58: 2108.48 | F58: 0 | H58: 0 | I58: 0 | J58: 168.6784 | K58: 0 | L58: 0 | M58: 0 | N58: 2108.48 | O58: 0 | P58: 165.44 | Q58: 0 | R58: 0 | S58: 421.696 | T58: 63.2544 | U58: 122.29184 | V58: 772.68224 | W58: 2108.48 | X58: 0 | Y58: 0 | Z58: 0 | AA58: 0 | AB58: =(N58+O58)-(AE58+AF58) -> 0 | AC58: =(P58+Q58)-(AG58+AH58) -> 0 | AD58: FLAVIO CARLOS DE SOUZA ORTEGA | AE58: 2108.48 | AF58: 0 | AG58: 165.44 | AH58: 0 | AI58: =(E58+F58+H58+I58)-AL58 -> 0 | AJ58: =(J58+K58+L58+M58)-AM58 -> 0.0084 | AK58: FLAVIO CARLOS DE SOUZA ORTEGA | AL58: 2108.48 | AM58: 168.67
A59: FRANCISCO DE ASSIS ANDRADE NETO | B59: BR - 060/GO - Rio Verde GO | C59: D | D59: N | E59: 2633.82 | F59: 866.93 | H59: 0 | I59: 933.7 | J59: 210.7056 | K59: 69.3544 | L59: 0 | M59: 74.696 | N59: 2633.82 | O59: 933.7 | P59: 212.72 | Q59: 70.02 | R59: 0 | S59: 713.504 | T59: 107.0256 | U59: 206.91616 | V59: 1310.1858 | W59: 2633.82 | X59: 0 | Y59: 0 | Z59: 0 | AA59: 0 | AB59: =(N59+O59)-(AE59+AF59) -> 0 | AC59: =(P59+Q59)-(AG59+AH59) -> 0 | AD59: FRANCISCO DE ASSIS ANDRADE NETO | AE59: 2633.82 | AF59: 933.7 | AG59: 212.72 | AH59: 70.02 | AI59: =(E59+F59+H59+I59)-AL59 -> 4434.45 | AJ59: =(J59+K59+L59+M59)-AM59 -> 354.756
A60: FRANCISCO PEREIRA CRUZ | B60: Oficina | C60: A | D60: N | E60: 4172.31 | F60: 0 | H60: 0 | I60: 0 | J60: 333.7848 | K60: 0 | L60: 0 | M60: 0 | N60: 4172.31 | O60: 0 | P60: 389.26 | Q60: 0 | R60: 0 | S60: 834.462 | T60: 125.1693 | U60: 241.99398 | V60: 1590.8853 | W60: 4172.31 | X60: 0 | Y60: 0 | Z60: 0 | AA60: 0 | AB60: =(N60+O60)-(AE60+AF60) -> 0 | AC60: =(P60+Q60)-(AG60+AH60) -> 0 | AD60: FRANCISCO PEREIRA CRUZ | AE60: 4172.31 | AF60: 0 | AG60: 389.26 | AH60: 0 | AI60: =(E60+F60+H60+I60)-AL60 -> 0 | AJ60: =(J60+K60+L60+M60)-AM60 -> 0.0048 | AK60: FRANCISCO PEREIRA CRUZ | AL60: 4172.31 | AM60: 333.78
A61: GABRIEL CAMPOS TELES | B61: Oficina | C61: A | D61: Z | E61: 1190 | F61: 0 | H61: 0 | I61: 0 | J61: =E61*0.02 -> 23.8 | K61: 0 | L61: 0 | M61: 0 | N61: 1190 | O61: 0 | P61: 89.25 | Q61: 0 | R61: 0 | S61: 238 | T61: 35.7 | U61: 69.02 | V61: 431.97 | W61: 1190 | X61: 0 | Y61: 0 | Z61: 0 | AA61: 0 | AB61: =(N61+O61)-(AE61+AF61) -> 0 | AC61: =(P61+Q61)-(AG61+AH61) -> 0 | AD61: GABRIEL CAMPOS TELES | AE61: 1190 | AF61: 0 | AG61: 89.25 | AH61: 0 | AI61: =(E61+F61+H61+I61)-AL61 -> 0 | AJ61: =(J61+K61+L61+M61)-AM61 -> 0 | AK61: GABRIEL CAMPOS TELES | AL61: 1190 | AM61: 23.8
A62: GEFERSON ESCOT ATAIDE THOMAZ | B62: BR-376/MS - Nova Andradina / Ivinhema | C62: A | D62: N | E62: 3117.76 | F62: 0 | H62: 0 | I62: 0 | J62: 249.4208 | K62: 0 | L62: 0 | M62: 0 | N62: 3117.76 | O62: 0 | P62: 262.72 | Q62: 0 | R62: 0 | S62: 623.552 | T62: 93.5328 | U62: 180.83008 | V62: 1160.6349 | W62: 3117.76 | X62: 0 | Y62: 0 | Z62: 0 | AA62: 0 | AB62: =(N62+O62)-(AE62+AF62) -> 0 | AC62: =(P62+Q62)-(AG62+AH62) -> 0 | AD62: GEFERSON ESCOT ATAIDE THOMAZ | AE62: 3117.76 | AF62: 0 | AG62: 262.72 | AH62: 0 | AI62: =(E62+F62+H62+I62)-AL62 -> 0 | AJ62: =(J62+K62+L62+M62)-AM62 -> 0.0008 | AK62: GEFERSON ESCOT ATAIDE THOMAZ | AL62: 3117.76 | AM62: 249.42
A63: GUILHERME GUIMARAES XAVIER | B63: BR - 262/MS - Miranda - Guaicurus MS | C63: D | D63: N | E63: 1262.1 | F63: 0 | H63: 0 | I63: 556.3 | J63: 100.968 | K63: 0 | L63: 0 | M63: 44.504 | N63: 1262.1 | O63: 556.3 | P63: 94.65 | Q63: 41.72 | R63: 0 | S63: 363.68 | T63: 54.552 | U63: 105.4672 | V63: 660.0692 | W63: 1262.1 | X63: 0 | Y63: 0 | Z63: 0 | AA63: 0 | AB63: =(N63+O63)-(AE63+AF63) -> 0 | AC63: =(P63+Q63)-(AG63+AH63) -> 0 | AD63: GUILHERME GUIMARAES XAVIER | AE63: 1262.1 | AF63: 556.3 | AG63: 94.65 | AH63: 41.72 | AI63: =(E63+F63+H63+I63)-AL63 -> 0 | AJ63: =(J63+K63+L63+M63)-AM63 -> 0.012 | AK63: GUILHERME GUIMARAES XAVIER | AL63: 1818.4 | AM63: 145.46
A64: GUILHERME MARTINS LOURENCO | B64: Financeiro | C64: A | D64: Z | E64: 610 | F64: 0 | H64: 0 | I64: 0 | J64: =E64*0.02 -> 12.2 | K64: 0 | L64: 0 | M64: 0 | N64: 610 | O64: 0 | P64: 45.75 | Q64: 0 | R64: 0 | S64: 122 | T64: 18.3 | U64: 35.38 | V64: 221.43 | W64: 610 | X64: 0 | Y64: 0 | Z64: 0 | AA64: 0 | AB64: =(N64+O64)-(AE64+AF64) -> 0 | AC64: =(P64+Q64)-(AG64+AH64) -> 0 | AD64: GUILHERME MARTINS LOURENCO | AE64: 610 | AF64: 0 | AG64: 45.75 | AH64: 0 | AI64: =(E64+F64+H64+I64)-AL64 -> 0 | AJ64: =(J64+K64+L64+M64)-AM64 -> 0 | AK64: GUILHERME MARTINS LOURENCO | AL64: 610 | AM64: 12.2
A65: GUSTAVO DUARTE DA SILVA | B65: BR - 060/MS Contorno Campo Grande 2º Contrato | C65: A | D65: N | E65: 2020.29 | F65: 0 | H65: 0 | I65: 0 | J65: 161.6232 | K65: 0 | L65: 0 | M65: 0 | N65: 2020.29 | O65: 0 | P65: 157.5 | Q65: 0 | R65: 0 | S65: 404.058 | T65: 60.6087 | U65: 117.17682 | V65: 739.34352 | W65: 2020.29 | X65: 0 | Y65: 0 | Z65: 0 | AA65: 0 | AB65: =(N65+O65)-(AE65+AF65) -> 0 | AC65: =(P65+Q65)-(AG65+AH65) -> 0 | AD65: GUSTAVO DUARTE DA SILVA | AE65: 2020.29 | AF65: 0 | AG65: 157.5 | AH65: 0 | AI65: =(E65+F65+H65+I65)-AL65 -> 0 | AJ65: =(J65+K65+L65+M65)-AM65 -> 0.0032 | AK65: GUSTAVO DUARTE DA SILVA | AL65: 2020.29 | AM65: 161.62
A66: HEITOR XAVIER FIDELIS | B66: Financeiro | C66: A | D66: Z | E66: 610 | F66: 0 | H66: 0 | I66: 0 | J66: =E66*0.02 -> 12.2 | K66: 0 | L66: 0 | M66: 0 | N66: 610 | O66: 0 | P66: 45.75 | Q66: 0 | R66: 0 | S66: 122 | T66: 18.3 | U66: 35.38 | V66: 221.43 | W66: 610 | X66: 0 | Y66: 0 | Z66: 0 | AA66: 0 | AB66: =(N66+O66)-(AE66+AF66) -> 0 | AC66: =(P66+Q66)-(AG66+AH66) -> 0 | AD66: HEITOR XAVIER FIDELIS | AE66: 610 | AF66: 0 | AG66: 45.75 | AH66: 0 | AI66: =(E66+F66+H66+I66)-AL66 -> 0 | AJ66: =(J66+K66+L66+M66)-AM66 -> 0 | AK66: HEITOR XAVIER FIDELIS | AL66: 610 | AM66: 12.2
A67: JACIR DE ARAUJO LELLES | B67: BR - 262/MS - Miranda - Guaicurus MS | C67: A | D67: N | E67: 3247.4 | F67: 0 | H67: 0 | I67: 0 | J67: 259.792 | K67: 0 | L67: 0 | M67: 0 | N67: 3247.4 | O67: 0 | P67: 278.27 | Q67: 0 | R67: 0 | S67: 649.48 | T67: 97.422 | U67: 188.3492 | V67: 1213.5212 | W67: 3247.4 | X67: 0 | Y67: 0 | Z67: 0 | AA67: 0 | AB67: =(N67+O67)-(AE67+AF67) -> 0 | AC67: =(P67+Q67)-(AG67+AH67) -> 0 | AD67: JACIR DE ARAUJO LELLES | AE67: 3247.4 | AF67: 0 | AG67: 278.27 | AH67: 0 | AI67: =(E67+F67+H67+I67)-AL67 -> 0 | AJ67: =(J67+K67+L67+M67)-AM67 -> 0.002 | AK67: JACIR DE ARAUJO LELLES | AL67: 3247.4 | AM67: 259.79
A68: JADSON DA COSTA GOMES | B68: Oficina | C68: A | D68: N | E68: 5433.91 | F68: 0 | H68: 0 | I68: 0 | J68: 434.7128 | K68: 0 | L68: 0 | M68: 0 | N68: 5433.91 | O68: 0 | P68: 562.24 | Q68: 0 | R68: 0 | S68: 1086.782 | T68: 163.0173 | U68: 315.16678 | V68: 2127.2061 | W68: 5433.91 | X68: 0 | Y68: 163.49 | Z68: 0 | AA68: 0 | AB68: =(N68+O68)-(AE68+AF68) -> 0 | AC68: =(P68+Q68)-(AG68+AH68) -> 0 | AD68: JADSON DA COSTA GOMES | AE68: 5433.91 | AF68: 0 | AG68: 562.24 | AH68: 0 | AI68: =(E68+F68+H68+I68)-AL68 -> 0 | AJ68: =(J68+K68+L68+M68)-AM68 -> 0.0028 | AK68: JADSON DA COSTA GOMES | AL68: 5433.91 | AM68: 434.71
A69: JAIRO IBANES | B69: BR-060/MS - Jardim - 2º Contrato | C69: A | D69: N | E69: 2127.56 | F69: 0 | H69: 0 | I69: 0 | J69: 170.2048 | K69: 0 | L69: 0 | M69: 0 | N69: 2127.56 | O69: 0 | P69: 167.16 | Q69: 0 | R69: 0 | S69: 425.512 | T69: 63.8268 | U69: 123.39848 | V69: 779.89728 | W69: 2127.56 | X69: 0 | Y69: 0 | Z69: 0 | AA69: 0 | AB69: =(N69+O69)-(AE69+AF69) -> 0 | AC69: =(P69+Q69)-(AG69+AH69) -> 0 | AD69: JAIRO IBANES | AE69: 2127.56 | AF69: 0 | AG69: 167.16 | AH69: 0 | AI69: =(E69+F69+H69+I69)-AL69 -> 0 | AJ69: =(J69+K69+L69+M69)-AM69 -> 0.0048 | AK69: JAIRO IBANES | AL69: 2127.56 | AM69: 170.2
A70: JOAO BATISTA CARDOSO DE BARROS | B70: BR-060/MS - Pedra / Nioaque | C70: A | D70: N | E70: 2085.07 | F70: 0 | H70: 0 | I70: 0 | J70: 166.8056 | K70: 0 | L70: 0 | M70: 0 | N70: 2085.07 | O70: 0 | P70: 163.33 | Q70: 0 | R70: 0 | S70: 417.014 | T70: 62.5521 | U70: 120.93406 | V70: 763.83016 | W70: 2085.07 | X70: 0 | Y70: 0 | Z70: 0 | AA70: 0 | AB70: =(N70+O70)-(AE70+AF70) -> 0 | AC70: =(P70+Q70)-(AG70+AH70) -> 0 | AD70: JOAO BATISTA CARDOSO DE BARROS | AE70: 2085.07 | AF70: 0 | AG70: 163.33 | AH70: 0 | AI70: =(E70+F70+H70+I70)-AL70 -> 0 | AJ70: =(J70+K70+L70+M70)-AM70 -> 0.0056 | AK70: JOAO BATISTA CARDOSO DE BARROS | AL70: 2085.07 | AM70: 166.8
A71: JOAO IBANHES JUNIOR | B71: BR-060/MS - Jardim - 2º Contrato | C71: P | D71: N | E71: 1634.54 | F71: 0 | H71: 0 | I71: 0 | J71: 130.7632 | K71: 0 | L71: 0 | M71: 0 | N71: 0 | O71: 0 | P71: 0 | Q71: 0 | R71: 0 | S71: 0 | T71: 0 | U71: 0 | V71: 0 | W71: 0 | X71: 0 | Y71: 0 | Z71: 0 | AA71: 0 | AB71: =(N71+O71)-(AE71+AF71) -> 0 | AC71: =(P71+Q71)-(AG71+AH71) -> 0 | AI71: =(E71+F71+H71+I71)-AL71 -> 0 | AJ71: =(J71+K71+L71+M71)-AM71 -> 0.0032 | AK71: JOAO IBANHES JUNIOR | AL71: 1634.54 | AM71: 130.76
A72: JOAO LUCAS DA SILVA FIRMO | B72: BR - 262/MS - Miranda - Guaicurus MS | C72: A | D72: N | E72: 2079.2 | F72: 0 | H72: 0 | I72: 0 | J72: 166.336 | K72: 0 | L72: 0 | M72: 0 | N72: 2079.2 | O72: 0 | P72: 162.8 | Q72: 0 | R72: 0 | S72: 415.84 | T72: 62.376 | U72: 120.5936 | V72: 761.6096 | W72: 2079.2 | X72: 0 | Y72: 0 | Z72: 0 | AA72: 0 | AB72: =(N72+O72)-(AE72+AF72) -> 0 | AC72: =(P72+Q72)-(AG72+AH72) -> 0 | AD72: JOAO LUCAS DA SILVA FIRMO | AE72: 2079.2 | AF72: 0 | AG72: 162.8 | AH72: 0 | AI72: =(E72+F72+H72+I72)-AL72 -> 0 | AJ72: =(J72+K72+L72+M72)-AM72 -> 0.006 | AK72: JOAO LUCAS DA SILVA FIRMO | AL72: 2079.2 | AM72: 166.33
A73: JOAO PAULO LUCARELO GOMES | B73: Financeiro | C73: A | D73: D | E73: 0 | F73: 0 | H73: 0 | I73: 0 | J73: 0 | K73: 0 | L73: 0 | M73: 0 | N73: 0 | O73: 0 | P73: 932.31 | Q73: 0 | R73: 0 | S73: 0 | T73: 0 | U73: 0 | V73: 932.31 | W73: 8475.55 | X73: 0 | Y73: 1113.52 | Z73: 0 | AA73: 0 | AB73: =(N73+O73)-(AE73+AF73) -> -8475.55 | AC73: =(P73+Q73)-(AG73+AH73) -> 0 | AD73: JOAO PAULO LUCARELO GOMES | AE73: 8475.55 | AF73: 0 | AG73: 932.31 | AH73: 0 | AI73: =(E73+F73+H73+I73)-AL73 -> 0 | AJ73: =(J73+K73+L73+M73)-AM73 -> 0
A74: JOAO VITOR DA SILVA SOUZA | B74: BR - 359/MS - Coxim MS | C74: A | D74: N | E74: 2070.8 | F74: 0 | H74: 0 | I74: 0 | J74: 165.664 | K74: 0 | L74: 0 | M74: 0 | N74: 2070.8 | O74: 0 | P74: 162.05 | Q74: 0 | R74: 0 | S74: 414.16 | T74: 62.124 | U74: 120.1064 | V74: 758.4404 | W74: 2070.8 | X74: 0 | Y74: 0 | Z74: 0 | AA74: 0 | AB74: =(N74+O74)-(AE74+AF74) -> 0 | AC74: =(P74+Q74)-(AG74+AH74) -> 0 | AD74: JOAO VITOR DA SILVA SOUZA | AE74: 2070.8 | AF74: 0 | AG74: 162.05 | AH74: 0 | AI74: =(E74+F74+H74+I74)-AL74 -> 0 | AJ74: =(J74+K74+L74+M74)-AM74 -> 0.004 | AK74: JOAO VITOR DA SILVA SOUZA | AL74: 2070.8 | AM74: 165.66
A75: JOAO VITOR DE ARRUDA DOS SANTOS | B75: BR-262 e 359/MS - Corumbá - 2º Contrato | C75: A | D75: N | E75: 2029.34 | F75: 0 | H75: 0 | I75: 0 | J75: 162.3472 | K75: 0 | L75: 0 | M75: 0 | N75: 2029.34 | O75: 0 | P75: 158.32 | Q75: 0 | R75: 0 | S75: 405.868 | T75: 60.8802 | U75: 117.70172 | V75: 742.76992 | W75: 2029.34 | X75: 0 | Y75: 0 | Z75: 0 | AA75: 0 | AB75: =(N75+O75)-(AE75+AF75) -> 0 | AC75: =(P75+Q75)-(AG75+AH75) -> 0 | AD75: JOAO VITOR DE ARRUDA DOS SANTOS | AE75: 2029.34 | AF75: 0 | AG75: 158.32 | AH75: 0 | AI75: =(E75+F75+H75+I75)-AL75 -> 0 | AJ75: =(J75+K75+L75+M75)-AM75 -> 0.0072 | AK75: JOAO VITOR DE ARRUDA DOS SANTOS | AL75: 2029.34 | AM75: 162.34
A76: JOEL DA SILVA | B76: BR - 060/MS Contorno Campo Grande 2º Contrato | C76: A | D76: N | E76: 2015.27 | F76: 0 | H76: 0 | I76: 0 | J76: 161.2216 | K76: 0 | L76: 0 | M76: 0 | N76: 2015.27 | O76: 0 | P76: 157.05 | Q76: 0 | R76: 0 | S76: 403.054 | T76: 60.4581 | U76: 116.88566 | V76: 737.44776 | W76: 2015.27 | X76: 0 | Y76: 0 | Z76: 0 | AA76: 0 | AB76: =(N76+O76)-(AE76+AF76) -> 0 | AC76: =(P76+Q76)-(AG76+AH76) -> 0 | AD76: JOEL DA SILVA | AE76: 2015.27 | AF76: 0 | AG76: 157.05 | AH76: 0 | AI76: =(E76+F76+H76+I76)-AL76 -> 0 | AJ76: =(J76+K76+L76+M76)-AM76 -> 0.0016 | AK76: JOEL DA SILVA | AL76: 2015.27 | AM76: 161.22
A77: JONAS CARDOSO DE ALMEIDA | B77: BR - 262/MS - Miranda - Guaicurus MS | C77: A | D77: N | E77: 2079.2 | F77: 0 | H77: 0 | I77: 0 | J77: 166.336 | K77: 0 | L77: 0 | M77: 0 | N77: 2079.2 | O77: 0 | P77: 162.8 | Q77: 0 | R77: 0 | S77: 415.84 | T77: 62.376 | U77: 120.5936 | V77: 761.6096 | W77: 2079.2 | X77: 0 | Y77: 0 | Z77: 0 | AA77: 0 | AB77: =(N77+O77)-(AE77+AF77) -> 0 | AC77: =(P77+Q77)-(AG77+AH77) -> 0 | AD77: JONAS CARDOSO DE ALMEIDA | AE77: 2079.2 | AF77: 0 | AG77: 162.8 | AH77: 0 | AI77: =(E77+F77+H77+I77)-AL77 -> 0 | AJ77: =(J77+K77+L77+M77)-AM77 -> 0.006 | AK77: JONAS CARDOSO DE ALMEIDA | AL77: 2079.2 | AM77: 166.33
A78: JORGE JEFERSON SILVA CHAVES | B78: BR-262 e 359/MS - Corumbá - 2º Contrato | C78: A | D78: N | E78: 2521.69 | F78: 0 | H78: 0 | I78: 0 | J78: 201.7352 | K78: 0 | L78: 0 | M78: 0 | N78: 2521.69 | O78: 0 | P78: 202.63 | Q78: 0 | R78: 0 | S78: 504.338 | T78: 75.6507 | U78: 146.25802 | V78: 928.87672 | W78: 2521.69 | X78: 0 | Y78: 0 | Z78: 0 | AA78: 0 | AB78: =(N78+O78)-(AE78+AF78) -> 0 | AC78: =(P78+Q78)-(AG78+AH78) -> 0 | AD78: JORGE JEFERSON SILVA CHAVES | AE78: 2521.69 | AF78: 0 | AG78: 202.63 | AH78: 0 | AI78: =(E78+F78+H78+I78)-AL78 -> 0 | AJ78: =(J78+K78+L78+M78)-AM78 -> 0.0052 | AK78: JORGE JEFERSON SILVA CHAVES | AL78: 2521.69 | AM78: 201.73
A79: JOSE ANTUNES DE ABREU NETO | B79: BR-376/MS - Nova Andradina / Ivinhema | C79: A | D79: N | E79: 2115.92 | F79: 0 | H79: 0 | I79: 0 | J79: 169.2736 | K79: 0 | L79: 0 | M79: 0 | N79: 2115.92 | O79: 0 | P79: 166.11 | Q79: 0 | R79: 0 | S79: 423.184 | T79: 63.4776 | U79: 122.72336 | V79: 775.49496 | W79: 2115.92 | X79: 0 | Y79: 0 | Z79: 0 | AA79: 0 | AB79: =(N79+O79)-(AE79+AF79) -> 0 | AC79: =(P79+Q79)-(AG79+AH79) -> 0 | AD79: JOSE ANTUNES DE ABREU NETO | AE79: 2115.92 | AF79: 0 | AG79: 166.11 | AH79: 0 | AI79: =(E79+F79+H79+I79)-AL79 -> 0 | AJ79: =(J79+K79+L79+M79)-AM79 -> 0.0036 | AK79: JOSE ANTUNES DE ABREU NETO | AL79: 2115.92 | AM79: 169.27
A80: JOSE CARLOS GIMENEZ AQUINO | B80: Oficina | C80: A | D80: N | E80: 3750.55 | F80: 0 | H80: 0 | I80: 0 | J80: 300.044 | K80: 0 | L80: 0 | M80: 0 | N80: 3750.55 | O80: 0 | P80: 338.65 | Q80: 0 | R80: 0 | S80: 750.11 | T80: 112.5165 | U80: 217.5319 | V80: 1418.8084 | W80: 3750.55 | X80: 0 | Y80: 0 | Z80: 0 | AA80: 0 | AB80: =(N80+O80)-(AE80+AF80) -> 0 | AC80: =(P80+Q80)-(AG80+AH80) -> 0 | AD80: JOSE CARLOS GIMENEZ AQUINO | AE80: 3750.55 | AF80: 0 | AG80: 338.65 | AH80: 0 | AI80: =(E80+F80+H80+I80)-AL80 -> 0 | AJ80: =(J80+K80+L80+M80)-AM80 -> 0.004 | AK80: JOSE CARLOS GIMENEZ AQUINO | AL80: 3750.55 | AM80: 300.04
A81: JOSE JUNIOR VIEIRA DA SILVA | B81: BR - 262/MS - Miranda - Guaicurus MS | C81: A | D81: N | E81: 1555.51 | F81: 0 | H81: 0 | I81: 0 | J81: 124.4408 | K81: 0 | L81: 0 | M81: 0 | N81: 1555.51 | O81: 0 | P81: 116.66 | Q81: 0 | R81: 0 | S81: 311.102 | T81: 46.6653 | U81: 90.21958 | V81: 564.64688 | W81: 1555.51 | X81: 0 | Y81: 0 | Z81: 0 | AA81: 0 | AB81: =(N81+O81)-(AE81+AF81) -> 0 | AC81: =(P81+Q81)-(AG81+AH81) -> 0 | AD81: JOSE JUNIOR VIEIRA DA SILVA | AE81: 1555.51 | AF81: 0 | AG81: 116.66 | AH81: 0 | AI81: =(E81+F81+H81+I81)-AL81 -> 0 | AJ81: =(J81+K81+L81+M81)-AM81 -> 0.0008 | AK81: JOSE JUNIOR VIEIRA DA SILVA | AL81: 1555.51 | AM81: 124.44
A82: JOSE LUIZ CARDOSO | B82: BR-060/MS - Pedra / Nioaque | C82: A | D82: N | E82: 2221.81 | F82: 0 | H82: 0 | I82: 0 | J82: 177.7448 | K82: 0 | L82: 0 | M82: 0 | N82: 2221.81 | O82: 0 | P82: 175.64 | Q82: 0 | R82: 0 | S82: 444.362 | T82: 66.6543 | U82: 128.86498 | V82: 815.52128 | W82: 2221.81 | X82: 0 | Y82: 0 | Z82: 0 | AA82: 0 | AB82: =(N82+O82)-(AE82+AF82) -> 0 | AC82: =(P82+Q82)-(AG82+AH82) -> 0 | AD82: JOSE LUIZ CARDOSO | AE82: 2221.81 | AF82: 0 | AG82: 175.64 | AH82: 0 | AI82: =(E82+F82+H82+I82)-AL82 -> 0 | AJ82: =(J82+K82+L82+M82)-AM82 -> 0.0048 | AK82: JOSE LUIZ CARDOSO | AL82: 2221.81 | AM82: 177.74
A83: JOSE OLIVEIRA DE SOUZA | B83: BR - 267/MS - Nova Alvorada MS - 2º Contrato | C83: A | D83: N | E83: 3386.8 | F83: 0 | H83: 0 | I83: 0 | J83: 270.944 | K83: 0 | L83: 0 | M83: 0 | N83: 3386.8 | O83: 0 | P83: 295 | Q83: 0 | R83: 0 | S83: 677.36 | T83: 101.604 | U83: 196.4344 | V83: 1270.3984 | W83: 3386.8 | X83: 0 | Y83: 0 | Z83: 0 | AA83: 0 | AB83: =(N83+O83)-(AE83+AF83) -> 0 | AC83: =(P83+Q83)-(AG83+AH83) -> 0 | AD83: JOSE OLIVEIRA DE SOUZA | AE83: 3386.8 | AF83: 0 | AG83: 295 | AH83: 0 | AI83: =(E83+F83+H83+I83)-AL83 -> 0 | AJ83: =(J83+K83+L83+M83)-AM83 -> 0.004 | AK83: JOSE OLIVEIRA DE SOUZA | AL83: 3386.8 | AM83: 270.94
A84: JOSE PETRUCIO JACINTO DA SILVA | B84: BR - 267/MS - Nova Alvorada MS - 2º Contrato | C84: D | D84: N | E84: 1439.48 | F84: 282.66 | H84: 0 | I84: 465.64 | J84: 115.1584 | K84: 22.6128 | L84: 0 | M84: 37.2512 | N84: 1439.48 | O84: 465.64 | P84: 107.96 | Q84: 34.92 | R84: 0 | S84: 381.024 | T84: 57.1536 | U84: 110.49696 | V84: 691.55456 | W84: 1439.48 | X84: 0 | Y84: 0 | Z84: 0 | AA84: 0 | AB84: =(N84+O84)-(AE84+AF84) -> 0 | AC84: =(P84+Q84)-(AG84+AH84) -> 0 | AD84: JOSE PETRUCIO JACINTO DA SILVA | AE84: 1439.48 | AF84: 465.64 | AG84: 107.96 | AH84: 34.92 | AI84: =(E84+F84+H84+I84)-AL84 -> 2187.78 | AJ84: =(J84+K84+L84+M84)-AM84 -> 175.0224
A85: JOSE PRUDENCIO PINHEIRO | B85: Oficina | C85: A | D85: N | E85: 3819.08 | F85: 0 | H85: 0 | I85: 0 | J85: 305.5264 | K85: 0 | L85: 0 | M85: 0 | N85: 3819.08 | O85: 0 | P85: 346.87 | Q85: 0 | R85: 0 | S85: 763.816 | T85: 114.5724 | U85: 221.50664 | V85: 1446.765 | W85: 3819.08 | X85: 0 | Y85: 0 | Z85: 0 | AA85: 0 | AB85: =(N85+O85)-(AE85+AF85) -> 0 | AC85: =(P85+Q85)-(AG85+AH85) -> 0 | AD85: JOSE PRUDENCIO PINHEIRO | AE85: 3819.08 | AF85: 0 | AG85: 346.87 | AH85: 0 | AI85: =(E85+F85+H85+I85)-AL85 -> 0 | AJ85: =(J85+K85+L85+M85)-AM85 -> 0.0064 | AK85: JOSE PRUDENCIO PINHEIRO | AL85: 3819.08 | AM85: 305.52
A86: JOSE RENATO DE FIGUEIREDO FILHO | B86: Restaura MS180 - Juti MS | C86: A | D86: N | E86: 504.03 | F86: 0 | H86: 0 | I86: 0 | J86: 40.3224 | K86: 0 | L86: 0 | M86: 0 | N86: 504.03 | O86: 0 | P86: 37.8 | Q86: 0 | R86: 0 | S86: 100.806 | T86: 15.1209 | U86: 29.23374 | V86: 182.96064 | W86: 504.03 | X86: 0 | Y86: 0 | Z86: 0 | AA86: 0 | AB86: =(N86+O86)-(AE86+AF86) -> 0 | AC86: =(P86+Q86)-(AG86+AH86) -> 0 | AD86: JOSE RENATO DE FIGUEIREDO FILHO | AE86: 504.03 | AF86: 0 | AG86: 37.8 | AH86: 0 | AI86: =(E86+F86+H86+I86)-AL86 -> 0 | AJ86: =(J86+K86+L86+M86)-AM86 -> 0.0024 | AK86: JOSE RENATO DE FIGUEIREDO FILHO | AL86: 504.03 | AM86: 40.32
A87: JOSIEL DO NASCIMENTO ROCHA | B87: BR - 359/MS - Coxim MS | C87: A | D87: N | E87: 2144.28 | F87: 0 | H87: 0 | I87: 0 | J87: 171.5424 | K87: 0 | L87: 0 | M87: 0 | N87: 2144.28 | O87: 0 | P87: 168.66 | Q87: 0 | R87: 0 | S87: 428.856 | T87: 64.3284 | U87: 124.36824 | V87: 786.21264 | W87: 2144.28 | X87: 0 | Y87: 0 | Z87: 0 | AA87: 0 | AB87: =(N87+O87)-(AE87+AF87) -> 0 | AC87: =(P87+Q87)-(AG87+AH87) -> 0 | AD87: JOSIEL DO NASCIMENTO ROCHA | AE87: 2144.28 | AF87: 0 | AG87: 168.66 | AH87: 0 | AI87: =(E87+F87+H87+I87)-AL87 -> 0 | AJ87: =(J87+K87+L87+M87)-AM87 -> 0.0024 | AK87: JOSIEL DO NASCIMENTO ROCHA | AL87: 2144.28 | AM87: 171.54
A88: JUAN MARX SIQUEIRA MOREIRA | B88: Financeiro | C88: A | D88: N | E88: 3200 | F88: 0 | H88: 0 | I88: 0 | J88: 256 | K88: 0 | L88: 0 | M88: 0 | N88: 3200 | O88: 0 | P88: 272.58 | Q88: 0 | R88: 0 | S88: 640 | T88: 96 | U88: 185.6 | V88: 1194.18 | W88: 3200 | X88: 0 | Y88: 0 | Z88: 0 | AA88: 0 | AB88: =(N88+O88)-(AE88+AF88) -> 0 | AC88: =(P88+Q88)-(AG88+AH88) -> 0 | AD88: JUAN MARX SIQUEIRA MOREIRA | AE88: 3200 | AF88: 0 | AG88: 272.58 | AH88: 0 | AI88: =(E88+F88+H88+I88)-AL88 -> 0 | AJ88: =(J88+K88+L88+M88)-AM88 -> 0 | AK88: JUAN MARX SIQUEIRA MOREIRA | AL88: 3200 | AM88: 256
A89: JUNIOR CESAR CARDOSO ALEM | B89: BR-419/MS - Anastacio | C89: A | D89: N | E89: 2233.16 | F89: 0 | H89: 0 | I89: 0 | J89: 178.6528 | K89: 0 | L89: 0 | M89: 0 | N89: 2233.16 | O89: 0 | P89: 176.66 | Q89: 0 | R89: 0 | S89: 446.632 | T89: 66.9948 | U89: 129.52328 | V89: 819.81008 | W89: 2233.16 | X89: 0 | Y89: 0 | Z89: 0 | AA89: 0 | AB89: =(N89+O89)-(AE89+AF89) -> 0 | AC89: =(P89+Q89)-(AG89+AH89) -> 0 | AD89: JUNIOR CESAR CARDOSO ALEM | AE89: 2233.16 | AF89: 0 | AG89: 176.66 | AH89: 0 | AI89: =(E89+F89+H89+I89)-AL89 -> 0 | AJ89: =(J89+K89+L89+M89)-AM89 -> 0.0028 | AK89: JUNIOR CESAR CARDOSO ALEM | AL89: 2233.16 | AM89: 178.65
A90: KAUAN MATEUS MENDES DA SILVA | B90: Oficina | C90: A | D90: N | E90: 2700 | F90: 0 | H90: 0 | I90: 0 | J90: 216 | K90: 0 | L90: 0 | M90: 0 | N90: 2700 | O90: 0 | P90: 218.68 | Q90: 0 | R90: 0 | S90: 540 | T90: 81 | U90: 156.6 | V90: 996.28 | W90: 2700 | X90: 0 | Y90: 0 | Z90: 0 | AA90: 0 | AB90: =(N90+O90)-(AE90+AF90) -> 0 | AC90: =(P90+Q90)-(AG90+AH90) -> 0 | AD90: KAUAN MATEUS MENDES DA SILVA | AE90: 2700 | AF90: 0 | AG90: 218.68 | AH90: 0 | AI90: =(E90+F90+H90+I90)-AL90 -> 0 | AJ90: =(J90+K90+L90+M90)-AM90 -> 0 | AK90: KAUAN MATEUS MENDES DA SILVA | AL90: 2700 | AM90: 216
A91: LEANDRO ALVES MACEDO | B91: Restaura MS180 - Juti MS | C91: A | D91: N | E91: 2012.01 | F91: 0 | H91: 0 | I91: 0 | J91: 160.9608 | K91: 0 | L91: 0 | M91: 0 | N91: 2012.01 | O91: 0 | P91: 156.76 | Q91: 0 | R91: 0 | S91: 402.402 | T91: 60.3603 | U91: 116.69658 | V91: 736.21888 | W91: 2012.01 | X91: 0 | Y91: 0 | Z91: 0 | AA91: 0 | AB91: =(N91+O91)-(AE91+AF91) -> 0 | AC91: =(P91+Q91)-(AG91+AH91) -> 0 | AD91: LEANDRO ALVES MACEDO | AE91: 2012.01 | AF91: 0 | AG91: 156.76 | AH91: 0 | AI91: =(E91+F91+H91+I91)-AL91 -> 0 | AJ91: =(J91+K91+L91+M91)-AM91 -> 0.0008 | AK91: LEANDRO ALVES MACEDO | AL91: 2012.01 | AM91: 160.96
A92: LEONARDO VINICIUS DE SOUZA | B92: Financeiro | C92: A | D92: Z | E92: 2090 | F92: 0 | H92: 0 | I92: 0 | J92: =E92*0.02 -> 41.8 | K92: 0 | L92: 0 | M92: 0 | N92: 2090 | O92: 0 | P92: 163.78 | Q92: 0 | R92: 0 | S92: 418 | T92: 62.7 | U92: 121.22 | V92: 765.7 | W92: 2090 | X92: 0 | Y92: 0 | Z92: 0 | AA92: 0 | AB92: =(N92+O92)-(AE92+AF92) -> 0 | AC92: =(P92+Q92)-(AG92+AH92) -> 0 | AD92: LEONARDO VINICIUS DE SOUZA | AE92: 2090 | AF92: 0 | AG92: 163.78 | AH92: 0 | AI92: =(E92+F92+H92+I92)-AL92 -> 0 | AJ92: =(J92+K92+L92+M92)-AM92 -> 0 | AK92: LEONARDO VINICIUS DE SOUZA | AL92: 2090 | AM92: 41.8
A93: LUCAS ALSAMENDIA DE OLIVEIRA | B93: Restaura MS180 - Juti MS | C93: A | D93: N | E93: 622.16 | F93: 0 | H93: 0 | I93: 0 | J93: 49.7728 | K93: 0 | L93: 0 | M93: 0 | N93: 622.16 | O93: 0 | P93: 46.66 | Q93: 0 | R93: 0 | S93: 124.432 | T93: 18.6648 | U93: 36.08528 | V93: 205.58208 | W93: 622.16 | X93: 0 | Y93: 0 | Z93: 0 | AA93: 0 | AB93: =(N93+O93)-(AE93+AF93) -> 0 | AC93: =(P93+Q93)-(AG93+AH93) -> 0 | AD93: LUCAS ALSAMENDIA DE OLIVEIRA | AE93: 622.16 | AF93: 0 | AG93: 46.66 | AH93: 0 | AI93: =(E93+F93+H93+I93)-AL93 -> 0 | AJ93: =(J93+K93+L93+M93)-AM93 -> 0.0028 | AK93: LUCAS ALSAMENDIA DE OLIVEIRA | AL93: 622.16 | AM93: 49.77
A94: LUCAS MOURA DOS SANTOS | B94: Restaura MS180 - Juti MS | C94: A | D94: N | E94: 2345.6 | F94: 0 | H94: 0 | I94: 0 | J94: 187.648 | K94: 0 | L94: 0 | M94: 0 | N94: 2345.6 | O94: 0 | P94: 186.78 | Q94: 0 | R94: 0 | S94: 469.12 | T94: 70.368 | U94: 136.0448 | V94: 862.3128 | W94: 2345.6 | X94: 0 | Y94: 0 | Z94: 0 | AA94: 0 | AB94: =(N94+O94)-(AE94+AF94) -> 0 | AC94: =(P94+Q94)-(AG94+AH94) -> 0 | AD94: LUCAS MOURA DOS SANTOS | AE94: 2345.6 | AF94: 0 | AG94: 186.78 | AH94: 0 | AI94: =(E94+F94+H94+I94)-AL94 -> 0 | AJ94: =(J94+K94+L94+M94)-AM94 -> 0.008 | AK94: LUCAS MOURA DOS SANTOS | AL94: 2345.6 | AM94: 187.64
A95: LUCIANO DE LIMA | B95: Restaura MS180 - Juti MS | C95: A | D95: N | E95: 1071.84 | F95: 0 | H95: 0 | I95: 0 | J95: 85.7472 | K95: 0 | L95: 0 | M95: 0 | N95: 1071.84 | O95: 0 | P95: 80.38 | Q95: 0 | R95: 0 | S95: 214.368 | T95: 32.1552 | U95: 62.16672 | V95: 389.06992 | W95: 1071.84 | X95: 0 | Y95: 0 | Z95: 0 | AA95: 0 | AB95: =(N95+O95)-(AE95+AF95) -> 0 | AC95: =(P95+Q95)-(AG95+AH95) -> 0 | AD95: LUCIANO DE LIMA | AE95: 1071.84 | AF95: 0 | AG95: 80.38 | AH95: 0 | AI95: =(E95+F95+H95+I95)-AL95 -> 0 | AJ95: =(J95+K95+L95+M95)-AM95 -> 0.0072 | AK95: LUCIANO DE LIMA | AL95: 1071.84 | AM95: 85.74
A96: LUCIANO FARIAS RIBEIRO | B96: Oficina | C96: A | D96: N | E96: 4377.4 | F96: 0 | H96: 0 | I96: 0 | J96: 350.192 | K96: 0 | L96: 0 | M96: 0 | N96: 4377.4 | O96: 0 | P96: 414.33 | Q96: 0 | R96: 0 | S96: 875.48 | T96: 131.322 | U96: 253.8892 | V96: 1675.0212 | W96: 4377.4 | X96: 0 | Y96: 0 | Z96: 0 | AA96: 0 | AB96: =(N96+O96)-(AE96+AF96) -> 0 | AC96: =(P96+Q96)-(AG96+AH96) -> 0 | AD96: LUCIANO FARIAS RIBEIRO | AE96: 4377.4 | AF96: 0 | AG96: 414.33 | AH96: 0 | AI96: =(E96+F96+H96+I96)-AL96 -> 0 | AJ96: =(J96+K96+L96+M96)-AM96 -> 0.002 | AK96: LUCIANO FARIAS RIBEIRO | AL96: 4377.4 | AM96: 350.19
A97: LUCIANO LOUVEIRA DA CONCEICAO | B97: BR-060/MS - Pedra / Nioaque | C97: A | D97: N | E97: 2244.8 | F97: 0 | H97: 0 | I97: 0 | J97: 179.584 | K97: 0 | L97: 0 | M97: 0 | N97: 2244.8 | O97: 0 | P97: 177.71 | Q97: 0 | R97: 0 | S97: 448.96 | T97: 67.344 | U97: 130.1984 | V97: 824.2124 | W97: 2244.8 | X97: 0 | Y97: 0 | Z97: 0 | AA97: 0 | AB97: =(N97+O97)-(AE97+AF97) -> 0 | AC97: =(P97+Q97)-(AG97+AH97) -> 0 | AD97: LUCIANO LOUVEIRA DA CONCEICAO | AE97: 2244.8 | AF97: 0 | AG97: 177.71 | AH97: 0 | AI97: =(E97+F97+H97+I97)-AL97 -> 0 | AJ97: =(J97+K97+L97+M97)-AM97 -> 0.004 | AK97: LUCIANO LOUVEIRA DA CONCEICAO | AL97: 2244.8 | AM97: 179.58
A98: LUIZ PEDRO DOS SANTOS | B98: BR-262 e 359/MS - Corumbá - 2º Contrato | C98: A | D98: N | E98: 2493.45 | F98: 0 | H98: 0 | I98: 0 | J98: 199.476 | K98: 0 | L98: 0 | M98: 0 | N98: 2493.45 | O98: 0 | P98: 200.09 | Q98: 0 | R98: 0 | S98: 498.69 | T98: 74.8035 | U98: 144.6201 | V98: 918.2036 | W98: 2493.45 | X98: 0 | Y98: 0 | Z98: 0 | AA98: 0 | AB98: =(N98+O98)-(AE98+AF98) -> 0 | AC98: =(P98+Q98)-(AG98+AH98) -> 0 | AD98: LUIZ PEDRO DOS SANTOS | AE98: 2493.45 | AF98: 0 | AG98: 200.09 | AH98: 0 | AI98: =(E98+F98+H98+I98)-AL98 -> 0 | AJ98: =(J98+K98+L98+M98)-AM98 -> 0.006 | AK98: LUIZ PEDRO DOS SANTOS | AL98: 2493.45 | AM98: 199.47
A99: MARCELO APARECIDO VIEIRA GOMES | B99: BR-419/MS - Anastacio | C99: A | D99: N | E99: 3580.93 | F99: 0 | H99: 0 | I99: 0 | J99: 286.4744 | K99: 0 | L99: 0 | M99: 0 | N99: 3580.93 | O99: 0 | P99: 318.3 | Q99: 0 | R99: 0 | S99: 716.186 | T99: 107.4279 | U99: 207.69394 | V99: 1349.6078 | W99: 3580.93 | X99: 0 | Y99: 0 | Z99: 0 | AA99: 0 | AB99: =(N99+O99)-(AE99+AF99) -> 0 | AC99: =(P99+Q99)-(AG99+AH99) -> 0 | AD99: MARCELO APARECIDO VIEIRA GOMES | AE99: 3580.93 | AF99: 0 | AG99: 318.3 | AH99: 0 | AI99: =(E99+F99+H99+I99)-AL99 -> 0 | AJ99: =(J99+K99+L99+M99)-AM99 -> 0.0044 | AK99: MARCELO APARECIDO VIEIRA GOMES | AL99: 3580.93 | AM99: 286.47
A100: MARCIO DE OLIVEIRA MARTINS | B100: BR-060/MS - Jardim - 2º Contrato | C100: A | D100: N | E100: 6869.69 | F100: 0 | H100: 0 | I100: 0 | J100: 549.5752 | K100: 0 | L100: 0 | M100: 0 | N100: 6869.69 | O100: 0 | P100: 763.25 | Q100: 0 | R100: 0 | S100: 1373.938 | T100: 206.0907 | U100: 398.44202 | V100: 2741.7207 | W100: 6869.69 | X100: 0 | Y100: 706.58 | Z100: 0 | AA100: 0 | AB100: =(N100+O100)-(AE100+AF100) -> 0 | AC100: =(P100+Q100)-(AG100+AH100) -> 0 | AD100: MARCIO DE OLIVEIRA MARTINS | AE100: 6869.69 | AF100: 0 | AG100: 763.25 | AH100: 0 | AI100: =(E100+F100+H100+I100)-AL100 -> 0 | AJ100: =(J100+K100+L100+M100)-AM100 -> 0.0052 | AK100: MARCIO DE OLIVEIRA MARTINS | AL100: 6869.69 | AM100: 549.57
A101: MARCOS ANTONIO DA SILVA MORAES | B101: BR - 262/MS - Miranda - Guaicurus MS | C101: A | D101: N | E101: 1969.89 | F101: 0 | H101: 0 | I101: 0 | J101: 157.5912 | K101: 0 | L101: 0 | M101: 0 | N101: 1969.89 | O101: 0 | P101: 152.97 | Q101: 0 | R101: 0 | S101: 393.978 | T101: 59.0967 | U101: 114.25362 | V101: 720.29832 | W101: 1969.89 | X101: 0 | Y101: 0 | Z101: 0 | AA101: 0 | AB101: =(N101+O101)-(AE101+AF101) -> 0 | AC101: =(P101+Q101)-(AG101+AH101) -> 0 | AD101: MARCOS ANTONIO DA SILVA MORAES | AE101: 1969.89 | AF101: 0 | AG101: 152.97 | AH101: 0 | AI101: =(E101+F101+H101+I101)-AL101 -> 0 | AJ101: =(J101+K101+L101+M101)-AM101 -> 0.0012 | AK101: MARCOS ANTONIO DA SILVA MORAES | AL101: 1969.89 | AM101: 157.59
A102: MARCOS GONCALVES PEREIRA | B102: BR-060/MS - Pedra / Nioaque | C102: A | D102: N | E102: 3842.26 | F102: 0 | H102: 0 | I102: 0 | J102: 307.3808 | K102: 0 | L102: 0 | M102: 0 | N102: 3842.26 | O102: 0 | P102: 349.66 | Q102: 0 | R102: 0 | S102: 768.452 | T102: 115.2678 | U102: 222.85108 | V102: 1456.2309 | W102: 3842.26 | X102: 0 | Y102: 0 | Z102: 0 | AA102: 0 | AB102: =(N102+O102)-(AE102+AF102) -> 0 | AC102: =(P102+Q102)-(AG102+AH102) -> 0 | AD102: MARCOS GONCALVES PEREIRA | AE102: 3842.26 | AF102: 0 | AG102: 349.66 | AH102: 0 | AI102: =(E102+F102+H102+I102)-AL102 -> 0 | AJ102: =(J102+K102+L102+M102)-AM102 -> 0.0008 | AK102: MARCOS GONCALVES PEREIRA | AL102: 3842.26 | AM102: 307.38
A103: MARCOS MARCIEL DA SILVA | B103: BR - 060/MS - Sidrolândia MS | C103: A | D103: N | E103: 3399.66 | F103: 0 | H103: 0 | I103: 0 | J103: 271.9728 | K103: 0 | L103: 0 | M103: 0 | N103: 3399.66 | O103: 0 | P103: 296.54 | Q103: 0 | R103: 0 | S103: 679.932 | T103: 101.9898 | U103: 197.18028 | V103: 1275.6421 | W103: 3399.66 | X103: 0 | Y103: 0 | Z103: 0 | AA103: 0 | AB103: =(N103+O103)-(AE103+AF103) -> 0 | AC103: =(P103+Q103)-(AG103+AH103) -> 0 | AD103: MARCOS MARCIEL DA SILVA | AE103: 3399.66 | AF103: 0 | AG103: 296.54 | AH103: 0 | AI103: =(E103+F103+H103+I103)-AL103 -> 0 | AJ103: =(J103+K103+L103+M103)-AM103 -> 0.0028 | AK103: MARCOS MARCIEL DA SILVA | AL103: 3399.66 | AM103: 271.97
A104: MARCOS OLIVEIRA DE CAMPOS | B104: BR-262 e 359/MS - Corumbá - 2º Contrato | C104: A | D104: N | E104: 2641.43 | F104: 0 | H104: 0 | I104: 0 | J104: 211.3144 | K104: 0 | L104: 0 | M104: 0 | N104: 2641.43 | O104: 0 | P104: 213.4 | Q104: 0 | R104: 0 | S104: 528.286 | T104: 79.2429 | U104: 153.20294 | V104: 974.13184 | W104: 2641.43 | X104: 0 | Y104: 0 | Z104: 0 | AA104: 0 | AB104: =(N104+O104)-(AE104+AF104) -> 0 | AC104: =(P104+Q104)-(AG104+AH104) -> 0 | AD104: MARCOS OLIVEIRA DE CAMPOS | AE104: 2641.43 | AF104: 0 | AG104: 213.4 | AH104: 0 | AI104: =(E104+F104+H104+I104)-AL104 -> 0 | AJ104: =(J104+K104+L104+M104)-AM104 -> 0.0044 | AK104: MARCOS OLIVEIRA DE CAMPOS | AL104: 2641.43 | AM104: 211.31
... A111: MIGUEL ANGELO BASSAN BERRIEL | B111: Oficina | C111: A | D111: N | E111: 5431.62 | F111: 0 | H111: 0 | I111: 0 | J111: 434.5296 | K111: 0 | L111: 0 | M111: 0 | N111: 5431.62 | O111: 0 | P111: 561.92 | Q111: 0 | R111: 0 | S111: 1086.324 | T111: 162.9486 | U111: 315.03396 | V111: 2126.2266 | W111: 5431.62 | X111: 0 | Y111: 122.87 | Z111: 0 | AA111: 0 | AB111: =(N111+O111)-(AE111+AF111) -> 0 | AC111: =(P111+Q111)-(AG111+AH111) -> 0 | AD111: MIGUEL ANGELO BASSAN BERRIEL | AE111: 5431.62 | AF111: 0 | AG111: 561.92 | AH111: 0 | AI111: =(E111+F111+H111+I111)-AL111 -> 0 | AJ111: =(J111+K111+L111+M111)-AM111 -> 0.0096 | AK111: MIGUEL ANGELO BASSAN BERRIEL | AL111: 5431.62 | AM111: 434.52
A112: MIQUELE MENEZES VIEIRA | B112: BR-262 e 359/MS - Corumbá - 2º Contrato | C112: A | D112: N | E112: 3586.33 | F112: 0 | H112: 0 | I112: 0 | J112: 286.9064 | K112: 0 | L112: 0 | M112: 0 | N112: 3586.33 | O112: 0 | P112: 158.83 | Q112: 0 | R112: 160.11 | S112: 717.266 | T112: 107.5899 | U112: 208.00714 | V112: 1351.803 | W112: 1537 | X112: 2049.33 | Y112: 0 | Z112: 0 | AA112: 0 | AB112: =(N112+O112)-(AE112+AF112) -> 0 | AC112: =(P112+Q112)-(AG112+AH112)+R112 -> 0 | AD112: MIQUELE MENEZES VIEIRA | AE112: 3586.33 | AF112: 0 | AG112: 318.94 | AH112: 0 | AI112: =(E112+F112+H112+I112)-AL112 -> 0 | AJ112: =(J112+K112+L112+M112)-AM112 -> 0.0064 | AK112: MIQUELE MENEZES VIEIRA | AL112: 3586.33 | AM112: 286.9
A113: MURILO HENRIQUE MATOS SOARES | B113: Financeiro | C113: A | D113: Z | E113: 610 | F113: 0 | H113: 0 | I113: 0 | J113: =E113*0.02 -> 12.2 | K113: 0 | L113: 0 | M113: 0 | N113: 610 | O113: 0 | P113: 45.75 | Q113: 0 | R113: 0 | S113: 122 | T113: 18.3 | U113: 35.38 | V113: 221.43 | W113: 610 | X113: 0 | Y113: 0 | Z113: 0 | AA113: 0 | AB113: =(N113+O113)-(AE113+AF113) -> 0 | AC113: =(P113+Q113)-(AG113+AH113) -> 0 | AD113: MURILO HENRIQUE MATOS SOARES | AE113: 610 | AF113: 0 | AG113: 45.75 | AH113: 0 | AI113: =(E113+F113+H113+I113)-AL113 -> 0 | AJ113: =(J113+K113+L113+M113)-AM113 -> 0 | AK113: MURILO HENRIQUE MATOS SOARES | AL113: 610 | AM113: 12.2
A114: NILSON BERNAL DA SILVA | B114: Oficina | C114: A | D114: N | E114: 5635.95 | F114: 0 | H114: 0 | I114: 0 | J114: 450.876 | K114: 0 | L114: 0 | M114: 0 | N114: 5635.95 | O114: 0 | P114: 590.53 | Q114: 0 | R114: 0 | S114: 1127.19 | T114: 169.0785 | U114: 326.8851 | V114: 2213.6836 | W114: 5635.95 | X114: 0 | Y114: 245.95 | Z114: 0 | AA114: 0 | AB114: =(N114+O114)-(AE114+AF114) -> 0 | AC114: =(P114+Q114)-(AG114+AH114) -> 0 | AD114: NILSON BERNAL DA SILVA | AE114: 5635.95 | AF114: 0 | AG114: 590.53 | AH114: 0 | AI114: =(E114+F114+H114+I114)-AL114 -> 0 | AJ114: =(J114+K114+L114+M114)-AM114 -> 0.006 | AK114: NILSON BERNAL DA SILVA | AL114: 5635.95 | AM114: 450.87
A115: NILSON DA SILVA | B115: Restaura MS180 - Juti MS | C115: A | D115: N | E115: 504.03 | F115: 0 | H115: 0 | I115: 0 | J115: 40.3224 | K115: 0 | L115: 0 | M115: 0 | N115: 504.03 | O115: 0 | P115: 37.8 | Q115: 0 | R115: 0 | S115: 100.806 | T115: 15.1209 | U115: 29.23374 | V115: 182.96064 | W115: 504.03 | X115: 0 | Y115: 0 | Z115: 0 | AA115: 0 | AB115: =(N115+O115)-(AE115+AF115) -> 0 | AC115: =(P115+Q115)-(AG115+AH115) -> 0 | AD115: NILSON DA SILVA | AE115: 504.03 | AF115: 0 | AG115: 37.8 | AH115: 0 | AI115: =(E115+F115+H115+I115)-AL115 -> 0 | AJ115: =(J115+K115+L115+M115)-AM115 -> 0.0024 | AK115: NILSON DA SILVA | AL115: 504.03 | AM115: 40.32
...

Sheet Emprestimos
L1: 9724.89
L2: 4424.03
L3: 1349.19
L4: 276.16
L5: 143.02
D7: NOME | E7: CODSITUACAO | F7: 5 | L7: =SUM(L1:L6) -> 15917.29
A8: ADNNY DA SILVA PITANGA | B8: 522.6 | C8: =B8-F8 -> 0 | D8: ADNNY DA SILVA PITANGA | E8: D | F8: 522.6
A9: Aloir de Souza Viana | B9: 558.83 | C9: =B9-F9 -> 0 | D9: ALOIR DE SOUZA VIANA | E9: D | F9: 558.83
A10: Arnaldo Salles Guimaraes | B10: 979.3 | C10: =B10-F10 -> 0 | D10: ARNALDO SALLES GUIMARAES | E10: A | F10: 979.3
A11: Daglos Loveira Vaz | B11: 371.63 | C11: =B11-F11 -> 0 | D11: DAGLOS LOVEIRA VAZ | E11: A | F11: 371.63
A12: Daniel Gonzaga Souza | B12: 288.1 | C12: =B12-F12 -> 0 | D12: DANIEL GONZAGA SOUZA | E12: D | F12: 288.1
A13: ELIAQUIM SANTOS MACHADO | B13: 553.93 | C13: =B13-F13 -> 0 | D13: ELIAQUIM SANTOS MACHADO | E13: D | F13: 553.93
A14: Evaldo Benedito Constantino | B14: 650.13 | C14: =B14-F14 -> 0 | D14: EVALDO BENEDITO CONSTANTINO | E14: A | F14: 650.13
A15: Fabio Velasquez Galeano | B15: 485.58 | C15: =B15-F15 -> 0 | D15: FABIO VELASQUEZ GALEANO | E15: A | F15: 485.58
A16: FILIPE DOS SANTOS | B16: 577.04 | C16: =B16-F16 -> 0 | D16: FILIPE DOS SANTOS | E16: D | F16: 577.04
A17: Flavio Carlos de Souza Ortega | B17: 599.43 | C17: =B17-F17 -> 0 | D17: FLAVIO CARLOS DE SOUZA ORTEGA | E17: A | F17: 599.43
A18: FRANCISCO DE ASSIS ANDRADE NETO | B18: 909.99 | C18: =B18-F18 -> 0 | D18: FRANCISCO DE ASSIS ANDRADE NETO | E18: D | F18: 909.99
A19: Geferson Escot Ataide Thomaz | B19: 949.23 | C19: =B19-F19 -> 0 | D19: GEFERSON ESCOT ATAIDE THOMAZ | E19: A | F19: 949.23
... A26: Jose Junior Vieira da Silva | B26: 435.25 | C26: =B26-F26 -> 0 | D26: JOSE JUNIOR VIEIRA DA SILVA | E26: A | F26: 435.25
C27: =B27-F27 -> -114.63 | D27: JOSE PETRUCIO JACINTO DA SILVA | E27: D | F27: 114.63
A28: Luciano Farias Ribeiro | B28: 165.35 | C28: =B28-F28 -> 0 | D28: LUCIANO FARIAS RIBEIRO | E28: A | F28: 165.35
A29: Luiz Pedro dos Santos | B29: 293.2 | C29: =B29-F29 -> 0 | D29: LUIZ PEDRO DOS SANTOS | E29: A | F29: 293.2
A30: Marcos Goncalves Pereira | B30: 217.53 | C30: =B30-F30 -> 0 | D30: MARCOS GONCALVES PEREIRA | E30: A | F30: 217.53
A31: Marcos Marciel da Silva | B31: 559.53 | C31: =B31-F31 -> 0 | D31: MARCOS MARCIEL DA SILVA | E31: A | F31: 559.53
A32: Nilson Bernal da Silva | B32: 856.98 | C32: =B32-F32 -> 0 | D32: NILSON BERNAL DA SILVA | E32: A | F32: 856.98
A33: Reginaldo da Silva Saltiva | B33: 346.18 | C33: =B33-F33 -> 0 | D33: REGINALDO DA SILVA SALTIVA | E33: A | F33: 346.18
A34: Temistocles Candido Rodrigues | B34: 400 | C34: =B34-F34 -> 0 | D34: TEMISTOCLES CANDIDO RODRIGUES | E34: A | F34: 400
A35: Ulisses Luiz Orue | B35: 264.77 | C35: =B35-F35 -> 0 | D35: ULISSES LUIZ ORUE | E35: A | F35: 264.77
A36: Wellington Martins | B36: 245.37 | C36: =B36-F36 -> 0 | D36: WELLINGTON MARTINS | E36: A | F36: 245.37
A37: Willanir da Silva | B37: 1278.77 | C37: =B37-F37 -> 0 | D37: WILLANIR DA SILVA | E37: A | F37: 1278.77
F38: 15917.29
B39: =SUM(B8:B38) -> 15802.66
B40: =B18+B16+B13+B9+B8 -> 3122.39
B42: =B39-B40 -> 12680.27 | C42: =B44-L7 -> 18810.42
B44: =SUM(B8:B40) -> 34727.71

Sheet GRRF
A1: NOME | F1: CHAPA | H1: CODTIPO | I1: FGTS QUITACAO | L1: FGTS MES ANTERIOR | N1: FGTS AVISO PREVIO | O1: FGTS ARTIGO 22 | P1: FGTS 13 SALARIO INDENIZADO | Q1: FGTS 13 Sal rescisao | S1: MÊS
A2: ADNNY DA SILVA PITANGA | F2: 00000667 | H2: N | I2: 117.43 | N2: 49.11 | O2: 1048.8 | Q2: 48.2 | R2: 1263.54 | S2: =I2+N2+P2+Q2 -> 214.74
A3: ADRYAN ANDRADE ESPIRITO SANTO | F3: 00000674 | H3: N | I3: 114.38 | N3: 49.01 | O3: 1039.8 | Q3: 48.13 | R3: 1251.32 | S3: =I3+N3+P3+Q3 -> 211.52
A4: ALOIR DE SOUZA VIANA | F4: 00000615 | H4: N | I4: 79 | N4: 200.91 | O4: 1233.41 | P4: 14.77 | Q4: 44.3 | R4: 1572.39 | S4: =I4+N4+P4+Q4 -> 338.98
A5: EDIVANIO RODRIGUES DA SILVA | F5: 00000778 | H5: N | I5: 216.53 | O5: 185.36 | Q5: 48.81 | R5: 450.7 | S5: =I5+N5+P5+Q5 -> 265.34
A6: ELERRANDRO DUTRA SOUSA | F6: 00000554 | H6: N | I6: 124.1 | N6: 72.69 | O6: 1809.59 | Q6: 48.91 | R6: 2055.29 | S6: =I6+N6+P6+Q6 -> 245.7
A7: ELIAQUIM SANTOS MACHADO | F7: 00000673 | H7: N | I7: 123.15 | N7: 49.47 | O7: 1064.92 | Q7: 48.53 | R7: 1286.07 | S7: =I7+N7+P7+Q7 -> 221.15
A8: FILIPE DOS SANTOS | F8: 00000665 | H8: N | I8: 105.09 | N8: 49.36 | O8: 1041.31 | Q8: 47.86 | R8: 1243.62 | S8: =I8+N8+P8+Q8 -> 202.31
A9: FRANCISCO DE ASSIS ANDRADE NETO | F9: 00000718 | H9: N | I9: 210.7 | N9: 69.35 | O9: 1309.11 | Q9: 74.69 | R9: 1663.85 | S9: =I9+N9+P9+Q9 -> 354.74
A10: JOSE PETRUCIO JACINTO DA SILVA | F10: 00000478 | H10: N | I10: 115.15 | L10: 150.85 | N10: 22.61 | O10: 1615.66 | Q10: 37.25 | R10: 1941.52 | S10: =I10+N10+P10+Q10 -> 175.01
A11: PEDRO HENRIQUE DE SOUSA PINHEIRO | F11: 00000650 | H11: N | I11: 185.04 | N11: 92.73 | O11: 1331.38 | Q11: 67.61 | R11: 1676.76 | S11: =I11+N11+P11+Q11 -> 345.38
A12: SAMUEL DA SILVA SOARES | F12: 00000756 | H12: N | I12: 131.8 | O12: 368.1 | Q12: 61.55 | R12: 561.45 | S12: =I12+N12+P12+Q12 -> 193.35
A13: SAMUEL DE ALMEIDA GOMES | F13: 00000719 | H13: N | I13: 198.78 | N13: 69.19 | O13: 1272.8 | Q13: 75.5 | R13: 1616.27 | S13: =I13+N13+P13+Q13 -> 343.47
I14: 1721.15 | L14: 182.19 | N14: 724.43 | O14: 13320.24 | P14: 14.77 | Q14: 651.34 | R14: 16614.12 | S14: =SUM(S2:S13) -> 3111.69

Sheet eSocial
XEH1: Contribuições Sociais do Contribuinte
XEH2: Filtro de pesquisa
XEH3: Período de Apuração:
XEH4: Número do Recibo do evento de origem:
XEH5: Razão Social
XEH6: Classificação Tributária
XEH7: Informações Complementares
XEH8: Indicativo de Cooperativa
XEH9: Indicativo de Construtora
XEH10: Indicativo de Substituição da Contribuição Previdenciária Patronal
XEH11: Indicador de tributação sobre a folha de pagamento - PIS e PASEP
XEH12: Sim Não
... XEH15: Resumo da Folha de Pagamento
XEH16: Bases de Cálculo | XEI16: Valor
XEH17: 11 - Base de cálculo da contribuição previdenciária | XEI17: 339404.33
XEH18: Contribuições do Segurado | XEI18: Valor Descontado | XEJ18: Valor Calculado
XEH19: Valor total da contribuição | XEI19: 29367.49 | XEJ19: 29367.49
XEH20: Deduções | XEI20: Valor
XEH21: Valor total do salário-família | XEI21: 87.8
XEH22: Estabelecimento 14.042.710/0001-99
XEH23: Informações consolidadas das contribuições sociais
XEH24: Codigo Receita | XEI24: Valor | XEJ24: Valor Suspenso
XEH25: 1082-01 - CP SEGURADOS - EMPREGADOS/AVULSOS | XEI25: 28435.18 | XEJ25: -
XEH26: 1099-01 - CP SEGURADOS - CONTRIBUINTES INDIVIDUAIS - 11% | XEI26: 932.31 | XEJ26: -
XEH27: 1138-01 - CP PATRONAL - EMPREGADOS/AVULSOS | XEI27: 66185.75 | XEJ27: -
XEH28: 1138-04 - CP PATRONAL - CONTRIBUINTES INDIVIDUAIS | XEI28: 1695.11 | XEJ28: -
XEH29: 1170-01 - CP TERCEIROS - SALÁRIO EDUCAÇÃO | XEI29: 8273.21 | XEJ29: - | XEK29: =XEI29+XEI30+XEI31+XEI32+XEI33 -> 19193.84
XEH30: 1176-01 - CP TERCEIROS - INCRA | XEI30: 661.85 | XEJ30: -
XEH31: 1181-01 - CP TERCEIROS - SENAI | XEI31: 3309.28 | XEJ31: -
XEH32: 1184-01 - CP TERCEIROS - SESI | XEI32: 4963.93 | XEJ32: -
XEH33: 1200-01 - CP TERCEIROS - SEBRAE | XEI33: 1985.57 | XEJ33: -
XEH34: 1646-01 - CP PATRONAL - GILRAT AJUSTADO | XEI34: 10237.61 | XEJ34: -

Sheet eCAC
A1: DÉBITOS APURADOS | E1: CRÉDITOS VINCULADOS | F1: SALDO A PAGAR
B2: Tributos/Códigos de Receita | D2: PA Débito | E2: Débito Apurado | G2: Deduções
A3: #VALUE! | G3: Salário-Família
A4: #VALUE! | B4: Total Apurado Empresa 14.042.710/0001-99 | E4: 131312.38 | F4: 87.8 | H4: 131224.58
B5: #VALUE! | C5: Total CONTRIBUIÇÃO PREVIDENCIÁRIA SEGURADOS | E5: 29367.49 | F5: 87.8 | H5: 29279.69
C6: 1082-01 CP SEGURADOS - EMPREGADOS/AVULSO | D6: 46082 | E6: 28435.18 | F6: 87.8 | H6: 28347.38
C7: 1099-01 CP SEGURADOS - CONTRIBUINTES INDIVIDUAIS - 11% | D7: 46082 | E7: 932.31 | F7: - | H7: 932.31
B8: #VALUE! | C8: Total CONTRIBUIÇÃO PREVIDENCIÁRIA PATRONAL | E8: 78118.47 | F8: - | H8: 78118.47
C9: 1138-01 CP PATRONAL - EMPREGADOS/AVULSOS | D9: 46082 | E9: 66185.75 | F9: - | H9: 66185.75
C10: 1138-04 CP PATRONAL - CONTRIBUINTES INDIVIDUAIS | D10: 46082 | E10: 1695.11 | F10: - | H10: 1695.11
C11: 1646-01 CP PATRONAL - GILRAT AJUSTADO | D11: 46082 | E11: 10237.61 | F11: - | H11: 10237.61
B12: #VALUE! | C12: Total CONTRIBUIÇÃO PARA OUTRAS ENTIDADES E FUNDOS | E12: 19193.84 | F12: - | H12: 19193.84
C13: 1170-01 CP TERCEIROS - SALÁRIO EDUCAÇÃO | D13: 46082 | E13: 8273.21 | F13: - | H13: 8273.21
C14: 1176-01 CP TERCEIROS - INCRA | D14: 46082 | E14: 661.85 | F14: - | H14: 661.85
C15: 1181-01 CP TERCEIROS - SENAI | D15: 46082 | E15: 3309.28 | F15: - | H15: 3309.28
C16: 1184-01 CP TERCEIROS - SESI | D16: 46082 | E16: 4963.93 | F16: - | H16: 4963.93
C17: 1200-01 CP TERCEIROS - SEBRAE | D17: 46082 | E17: 1985.57 | F17: - | H17: 1985.57
B18: #VALUE! | C18: Total IRRF | E18: 4632.58 | F18: - | H18: 4632.58
C19: 0561-07 IRRF - RD TRB ASSAL PAÍS/AUS NO EXT A SERV PAÍS | D19: 46082 | E19: 4632.58 | F19: - | H19: 4632.58

Sheet 1210
A1: 62 | B1: EVALDO BENEDITO CONSTANTINO | C1: 29 | D1: =A1-E1 -> 0 | E1: 62 | F1: ID1140427100000002026040616104700001
A2: 347 | B2: JOAO PAULO LUCARELO GOMES | C2: 19 | D2: =A2-E2 -> 0 | E2: 347 | F2: ID1140427100000002026040616104700000
A3: 356 | B3: JOAO IBANHES JUNIOR | C3: 491 | D3: =A3-E3 -> 0 | E3: 356 | F3: ID1140427100000002026040616104800014
A4: 454 | B4: CARLOS DONIZETI BOTARO | C4: 47 | D4: =A4-E4 -> 0 | E4: 454 | F4: ID1140427100000002026040616104700002
A5: 463 | B5: RICARDO LARANJEIRAS DE FARIAS | C5: 53 | D5: =A5-E5 -> 0 | E5: 463 | F5: ID1140427100000002026040616104700003
A6: 609 | B6: MARCOS OLIVEIRA DE CAMPOS | C6: 92 | D6: =A6-E6 -> 0 | E6: 609 | F6: ID1140427100000002026040616104700004
A7: 905 | B7: JOSE CARLOS GIMENEZ AQUINO | C7: 116 | D7: =A7-E7 -> 0 | E7: 905 | F7: ID1140427100000002026040616104700005
A8: 922 | B8: ARNALDO SALLES GUIMARAES | C8: 643 | D8: =A8-E8 -> 0 | E8: 922 | F8: ID1140427100000002026040616104900015
A9: 1111 | B9: MARCIO DE OLIVEIRA MARTINS | C9: 126 | D9: =A9-E9 -> 0 | E9: 1111 | F9: ID1140427100000002026040616104700006
A10: 1153 | B10: PAULO DE ALMEIDA | C10: 419 | D10: =A10-E10 -> 0 | E10: 1153 | F10: ID1140427100000002026040616104800009
A11: 1164 | B11: LUIZ PEDRO DOS SANTOS | C11: 131 | D11: =A11-E11 -> 0 | E11: 1164 | F11: ID1140427100000002026040616104700007
A12: 1221 | B12: CIRO OLICE SALINE VILALBA | C12: 798 | D12: =A12-E12 -> 0 | E12: 1221 | F12: ID1140427100000002026040616105400004
... A137: 2899 | B137: JOSE RENATO DE FIGUEIREDO FILHO | C137: 810 | D137: =A137-E137 -> 0 | E137: 2899 | F137: ID1140427100000002026040616105400016
D138: =A138-E138 -> 0
D139: =A139-E139 -> 0
D140: =A140-E140 -> 0
D141: =A141-E141 -> 0
D142: =A142-E142 -> 0
D143: =A143-E143 -> 0
D144: =A144-E144 -> 0
D145: =A145-E145 -> 0
D146: =A146-E146 -> 0
