Workbook

Sheet BASES
A1: CONCRETA | E1: FGTS
M2: INSS | Q2: VALOR SALARIO FAMILIA | T2: RAT AJUSTADO 3x FAP | V2: VALOR GUIA LANÇAMENTO INSS
E3: BASE FGTS GERAL | F3: =E18+F18+G18+H18+I18 -> 957147.43 | G3: =F3-J5 -> 0 | I3: BASE FGTS SINTETICO | J3: 916114.64 | M3: BASE INSS | O3: BASE GERAL FOLHA | R3: 20% PATRONAL | S3: 5,8% TERCEIROS | U3: FAP | W3: IRRF FOLHA
I4: BASE FGTS 13 SINTETICO | J4: 41032.79 | M4: PROLABORE | N4: =V137 -> 8475.55 | O4: =O6 -> 926484.67 | P4: =eSocial!B3 -> 936260.22 | Q4: 0 | S4: =eSocial!D18 -> 53735.95 | T4: 3 | U4: =IF(A1="CONCRETA",1.2393,1.0312) -> 1.2393 | V4: =U6+R8+S5+O13-Q4 -> 363764.74 | W4: =X18+Y18+Z18 -> 30463.96 | X4: =DCTFWeb!G19 -> 30463.96
F5: BASE | G5: VALOR | J5: =SUM(J3:J4) -> 957147.43 | M5: AUTONOMOS | N5: =Q18 -> 1300 | O5: BASE TOTAL FOLHA | P5: =O4-P4+N6 -> -1.6370905e-10 | S5: =O6*0.058 -> 53736.111 | U5: =T4*U4 -> 3.7179
E6: CLT 8% | F6: =(E18+F18+G18+H18+I18)-F7 -> 953406.99 | G6: =F6*0.08 -> 76272.559 | N6: =SUM(N4:N5) -> 9775.55 | O6: =M8+N8+N9-N4 -> 926484.67 | R6: =N6*0.2 -> 1955.11 | S6: =eSocial!B17 -> 1955.11 | U6: =O6*(U5/100) -> 34445.774 | V6: =eSocial!B23 -> 34445.74 | W6: VALOR GUIA eCAC | X6: =DCTFWeb!G4 -> 394228.49
E7: APRENDIZES 2% | F7: =E51+E78+E144+E145+E178+E215+E227 -> 3740.44 | G7: =F7*0.02 -> 74.8088 | R7: =O6*0.2 -> 185296.93 | S7: =eSocial!B16 -> 185296.92
M8: =O18 -> 893927.43 | N8: =P18 -> 41032.79 | R8: =SUM(R6:R7) -> 187252.04 | X8: =X6-X4 -> 363764.53
E9: GRRF RECOLHIDAS 8% | F9: =G9/8*100 -> 82106.5 | G9: =GRRF!K15 -> 6568.52 | N9: =I18 -> 0 | O9: =U18 -> 0 | V9: =V4-X8 -> 0.20840593
E10: GRRF RECOLHIDAS 2% | F10: =G10/2*100 -> 0 | G10: 0 | N10: INSS | O10: =R18 -> 84246.86 | R10: DIF TERCEIROS | S10: =S4-S5 -> -0.16086
F11: =SUBTOTAL(9,F9:F10) -> 82106.5 | G11: =SUBTOTAL(9,G9:G10) -> 6568.52 | N11: INSS 13 | O11: =S18 -> 3500.33 | R11: DIF PATRONAL | S11: =S7-R7 -> -0.014
N12: INSS FERIAS | O12: =T18 -> 583.62 | R12: DIF RAT | S12: =V6-U6 -> -0.03354593
E13: FGTS DIGITAL 8% | F13: =F6-F9 -> 871300.49 | G13: =F13*0.08 -> 69704.039 | N13: SEGURADOS | O13: =SUM(O9:O12) -> 88330.81 | P13: =eSocial!D14 -> 88330.81 | Q13: =P13-O13 -> 0
E14: FGTS DIGITAL 2% | F14: =F7-F10 -> 3740.44 | G14: =F14*0.02 -> 74.8088 | H14: FGTS DIGITAL
G15: =SUM(G13:G14) -> 69778.848 | H15: 69777.46 | I15: =G15-H15 -> 1.388 | J15: =H15-J199 -> 69597.31
E18: =E279 -> 885451.88 | F18: =F279 -> 30662.76 | G18: =G279 -> 2423.95 | H18: =H279 -> 38608.84 | I18: =I279 -> 0 | J18: =J279 -> 70611.7 | K18: =K279 -> 2453.03 | L18: =L279 -> 193.92 | ... AD18: =AD279 -> 364294.91
A19: NOME | B19: CCUSTO | C19: CODSITUACAO | D19: CODTIPO | E19: BASEFGTS | F19: BASEFGTSAVPREVIO | G19: BASEFGTS13AVPREVIO | H19: BASEFGTS13 | I19: BASEFGTSDIFSAL | J19: FGTS_MES | K19: FGTS_AVISO | L19: FGTS13_AVISO | M19: FGTS13 | N19: FGTSDIF | O19: BASEINSS | P19: BASEINSS13 | Q19: BASE_INSS_AUTONOMO | R19: INSS | S19: INSS13 | T19: INSSFERIAS | U19: INSSDIFSAL | V19: BASEIRRF | W19: BASEIRRFFERIAS | X19: IRRF | Y19: IRRF13 | Z19: IRRFFERIAS | AA19: INSS RAT AJUSTADO | AB19: INSS EMPRESA | AC19: INSS TERCEIROS | AD19: TOTAL GUIA | AE19: COMPARA BASE FGTS | AF19: COMPARA VALOR FGTS | AG19: Nome Trabalhador | AH19: Base Remuneracao Total | AI19: Valor FGTS na Guia | AJ19: COMPARA BASES INSS | AK19: COMPARA VALOR INSS | AL19: Nome | AM19: Governo - Base INSS | AN19: Governo - Valor INSS | AO19: Governo - Base INSS - 13° Salário | AP19: Governo - Valor INSS - 13° Salário
A20: ABNER DAVID MIRANDA CARDOSO | B20: CDHU - Ilha Solteira "D" 100 U.H. | C20: A | D20: N | E20: 2354.01 | F20: 0 | G20: 0 | H20: 0 | I20: 0 | J20: 188.32 | K20: 0 | L20: 0 | M20: 0 | N20: 0 | O20: 2354.01 | P20: 0 | Q20: 0 | R20: 187.54 | S20: 0 | T20: 0 | U20: 0 | V20: 2354.01 | W20: 0 | X20: 0 | Y20: 0 | Z20: 0 | AA20: 87.52 | AB20: 470.8 | AC20: 136.53 | AD20: 882.39 | AE20: =(E20+F20+G20+H20+I20)-AH20 -> 0 | AF20: =(J20+K20+L20+M20+N20)-AI20 -> 0 | AG20: ABNER DAVID MIRANDA CARDOSO | AH20: 2354.01 | AI20: 188.32 | AJ20: =(O20+P20)-(AM20+AO20) -> 0 | AK20: =(R20+S20+T20+U20)-(AN20+AP20) -> 0 | AL20: ABNER DAVID MIRANDA CARDOSO | AM20: 2354.01 | AN20: 187.54 | AO20: 0 | AP20: 0
A21: ADEMAR DE JESUS | B21: Coleta de Lixo Varzea Grande MT | C21: A | D21: N | E21: 3702.68 | F21: 0 | G21: 0 | H21: 0 | I21: 0 | J21: 296.21 | K21: 0 | L21: 0 | M21: 0 | N21: 0 | O21: 3702.68 | P21: 0 | Q21: 0 | R21: 332.91 | S21: 0 | T21: 0 | U21: 0 | V21: 3702.68 | W21: 0 | X21: 0 | Y21: 0 | Z21: 0 | AA21: 137.66 | AB21: 740.54 | AC21: 214.76 | AD21: 1425.86 | AE21: =(E21+F21+G21+H21+I21)-AH21 -> 0 | AF21: =(J21+K21+L21+M21+N21)-AI21 -> 0 | AG21: ADEMAR DE JESUS | AH21: 3702.68 | AI21: 296.21 | AJ21: =(O21+P21)-(AM21+AO21) -> 0 | AK21: =(R21+S21+T21+U21)-(AN21+AP21) -> 0 | AL21: ADEMAR DE JESUS | AM21: 3702.68 | AN21: 332.91 | AO21: 0 | AP21: 0
A22: ADILSON GABRIEL DIAS FERREIRA MIRANDA | B22: Coleta de Lixo Varzea Grande MT | C22: A | D22: N | E22: 3716.01 | F22: 0 | G22: 0 | H22: 0 | I22: 0 | J22: 297.28 | K22: 0 | L22: 0 | M22: 0 | N22: 0 | O22: 3716.01 | P22: 0 | Q22: 0 | R22: 334.51 | S22: 0 | T22: 0 | U22: 0 | V22: 3716.01 | W22: 0 | X22: 0 | Y22: 0 | Z22: 0 | AA22: 138.16 | AB22: 743.2 | AC22: 215.53 | AD22: 1431.4 | AE22: =(E22+F22+G22+H22+I22)-AH22 -> 0 | AF22: =(J22+K22+L22+M22+N22)-AI22 -> 0 | AG22: ADILSON GABRIEL DIAS FERREIRA MIRANDA | AH22: 3716.01 | AI22: 297.28 | AJ22: =(O22+P22)-(AM22+AO22) -> 0 | AK22: =(R22+S22+T22+U22)-(AN22+AP22) -> 0 | AL22: ADILSON GABRIEL DIAS FERREIRA MIRANDA | AM22: 3716.01 | AN22: 334.51 | AO22: 0 | AP22: 0
A23: ADRIANO FERREIRA | B23: CDHU - Piratininga "E1" 56 U.H. | C23: A | D23: N | E23: 1839.59 | F23: 0 | G23: 0 | H23: 0 | I23: 0 | J23: 147.17 | K23: 0 | L23: 0 | M23: 0 | N23: 0 | O23: 1839.59 | P23: 0 | Q23: 0 | R23: 141.24 | S23: 0 | T23: 0 | U23: 0 | V23: 1839.59 | W23: 0 | X23: 0 | Y23: 0 | Z23: 0 | AA23: 68.39 | AB23: 367.92 | AC23: 106.7 | AD23: 684.25 | AE23: =(E23+F23+G23+H23+I23)-AH23 -> 0 | AF23: =(J23+K23+L23+M23+N23)-AI23 -> 0.01 | AG23: ADRIANO FERREIRA | AH23: 1839.59 | AI23: 147.16 | AJ23: =(O23+P23)-(AM23+AO23) -> 0 | AK23: =(R23+S23+T23+U23)-(AN23+AP23) -> 0 | AL23: ADRIANO FERREIRA | AM23: 1839.59 | AN23: 141.24 | AO23: 0 | AP23: 0
A24: AGNALDO GUIMARAES | B24: Coleta de Lixo Varzea Grande MT | C24: A | D24: N | E24: 3869.42 | F24: 0 | G24: 0 | H24: 0 | I24: 0 | J24: 309.55 | K24: 0 | L24: 0 | M24: 0 | N24: 0 | O24: 3869.42 | P24: 0 | Q24: 0 | R24: 352.91 | S24: 0 | T24: 0 | U24: 0 | V24: 3869.42 | W24: 0 | X24: 0 | Y24: 0 | Z24: 0 | AA24: 143.86 | AB24: 773.88 | AC24: 224.43 | AD24: 1495.08 | AE24: =(E24+F24+G24+H24+I24)-AH24 -> 0 | AF24: =(J24+K24+L24+M24+N24)-AI24 -> 0 | AG24: AGNALDO GUIMARAES | AH24: 3869.42 | AI24: 309.55 | AJ24: =(O24+P24)-(AM24+AO24) -> 0 | AK24: =(R24+S24+T24+U24)-(AN24+AP24) -> 0 | AL24: AGNALDO GUIMARAES | AM24: 3869.42 | AN24: 352.91 | AO24: 0 | AP24: 0
A25: AGNALDO NORBERTO DA SILVA | B25: Coleta de Lixo Varzea Grande MT | C25: A | D25: N | E25: 6768.67 | F25: 0 | G25: 0 | H25: 0 | I25: 0 | J25: 541.49 | K25: 0 | L25: 0 | M25: 0 | N25: 0 | O25: 6768.67 | P25: 0 | Q25: 0 | R25: 749.11 | S25: 0 | T25: 0 | U25: 0 | V25: 6768.67 | W25: 0 | X25: 669.24 | Y25: 0 | Z25: 0 | AA25: 251.65 | AB25: 1353.73 | AC25: 392.58 | AD25: 2747.08 | AE25: =(E25+F25+G25+H25+I25)-AH25 -> 0 | AF25: =(J25+K25+L25+M25+N25)-AI25 -> 0 | AG25: AGNALDO NORBETO DA SILVA | AH25: 6768.67 | AI25: 541.49 | AJ25: =(O25+P25)-(AM25+AO25) -> 0 | AK25: =(R25+S25+T25+U25)-(AN25+AP25) -> 0 | AL25: AGNALDO NORBETO DA SILVA | AM25: 6768.67 | AN25: 749.11 | AO25: 0 | AP25: 0
A26: AGRICOLA DIAS DA SILVA JUNIOR | B26: Coleta de Lixo Varzea Grande MT | C26: A | D26: N | E26: 5183.06 | F26: 0 | G26: 0 | H26: 0 | I26: 0 | J26: 414.64 | K26: 0 | L26: 0 | M26: 0 | N26: 0 | O26: 5183.06 | P26: 0 | Q26: 0 | R26: 527.13 | S26: 0 | T26: 0 | U26: 0 | V26: 5183.06 | W26: 0 | X26: 65.55 | Y26: 0 | Z26: 0 | AA26: 192.7 | AB26: 1036.61 | AC26: 300.62 | AD26: 2057.06 | AE26: =(E26+F26+G26+H26+I26)-AH26 -> 0 | AF26: =(J26+K26+L26+M26+N26)-AI26 -> 0 | AG26: AGRICOLA DIAS DA SILVA JUNIOR | AH26: 5183.06 | AI26: 414.64 | AJ26: =(O26+P26)-(AM26+AO26) -> 0 | AK26: =(R26+S26+T26+U26)-(AN26+AP26) -> 0 | AL26: AGRICOLA DIAS DA SILVA JUNIOR | AM26: 5183.06 | AN26: 527.13 | AO26: 0 | AP26: 0
A27: ALESSANDRO PASSOS BARROS | B27: Coleta de Lixo Varzea Grande MT | C27: A | D27: N | E27: 3984.86 | F27: 0 | G27: 0 | H27: 0 | I27: 0 | J27: 318.79 | K27: 0 | L27: 0 | M27: 0 | N27: 0 | O27: 3984.86 | P27: 0 | Q27: 0 | R27: 366.77 | S27: 0 | T27: 0 | U27: 0 | V27: 3984.86 | W27: 0 | X27: 0 | Y27: 0 | Z27: 0 | AA27: 148.15 | AB27: 796.97 | AC27: 231.12 | AD27: 1543.02 | AE27: =(E27+F27+G27+H27+I27)-AH27 -> 0 | AF27: =(J27+K27+L27+M27+N27)-AI27 -> 0.01 | AG27: ALESSANDRO PASSOS BARROS | AH27: 3984.86 | AI27: 318.78 | AJ27: =(O27+P27)-(AM27+AO27) -> 0 | AK27: =(R27+S27+T27+U27)-(AN27+AP27) -> 0 | AL27: ALESSANDRO PASSOS BARROS | AM27: 3984.86 | AN27: 366.77 | AO27: 0 | AP27: 0
A28: ALEX MATHEUS TAVARES CORREA | B28: Coleta de Lixo Varzea Grande MT | C28: A | D28: N | E28: 3045.47 | F28: 0 | G28: 0 | H28: 0 | I28: 0 | J28: 243.64 | K28: 0 | L28: 0 | M28: 0 | N28: 0 | O28: 3045.47 | P28: 0 | Q28: 0 | R28: 254.04 | S28: 0 | T28: 0 | U28: 0 | V28: 3045.47 | W28: 0 | X28: 0 | Y28: 0 | Z28: 0 | AA28: 113.23 | AB28: 609.09 | AC28: 176.64 | AD28: 1153 | AE28: =(E28+F28+G28+H28+I28)-AH28 -> 0 | AF28: =(J28+K28+L28+M28+N28)-AI28 -> 0.01 | AG28: ALEX MATHEUS TAVARES CORREA | AH28: 3045.47 | AI28: 243.63 | AJ28: =(O28+P28)-(AM28+AO28) -> 0 | AK28: =(R28+S28+T28+U28)-(AN28+AP28) -> 0 | AL28: ALEX MATHEUS TAVARES CORREA | AM28: 3045.47 | AN28: 254.04 | AO28: 0 | AP28: 0
A29: ALEXANDRE FERNANDO RAMOS VIANA | B29: Embasa Lote 02 - Municipio de Guanambi BA | C29: A | D29: A | E29: 0 | F29: 0 | G29: 0 | H29: 0 | I29: 0 | J29: 0 | K29: 0 | L29: 0 | M29: 0 | N29: 0 | O29: 0 | P29: 0 | Q29: 1300 | R29: 0 | S29: 0 | T29: 0 | U29: 0 | V29: 1300 | W29: 0 | X29: 0 | Y29: 0 | Z29: 0 | AA29: 0 | AB29: 0 | AC29: 0 | AD29: 0 | AE29: =(E29+F29+G29+H29+I29)-AH29 -> 0 | AF29: =(J29+K29+L29+M29+N29)-AI29 -> 0 | AJ29: =(O29+P29)-(AM29+AO29) -> 0 | AK29: =(R29+S29+T29+U29)-(AN29+AP29) -> 0
A30: ALLAN PETERSON RODRIGUES DE FREITAS | B30: Coleta de Lixo Varzea Grande MT | C30: A | D30: N | E30: 6876.33 | F30: 0 | G30: 0 | H30: 0 | I30: 0 | J30: 550.11 | K30: 0 | L30: 0 | M30: 0 | N30: 0 | O30: 6876.33 | P30: 0 | Q30: 0 | R30: 764.18 | S30: 0 | T30: 0 | U30: 0 | V30: 6876.33 | W30: 0 | X30: 709.04 | Y30: 0 | Z30: 0 | AA30: 255.66 | AB30: 1375.27 | AC30: 398.83 | AD30: 2793.93 | AE30: =(E30+F30+G30+H30+I30)-AH30 -> 0 | AF30: =(J30+K30+L30+M30+N30)-AI30 -> 0.01 | AG30: ALLAN PETERSON RODRIGUES DE FREITAS | AH30: 6876.33 | AI30: 550.1 | AJ30: =(O30+P30)-(AM30+AO30) -> 0 | AK30: =(R30+S30+T30+U30)-(AN30+AP30) -> 0 | AL30: ALLAN PETERSON RODRIGUES DE FREITAS | AM30: 6876.33 | AN30: 764.18 | AO30: 0 | AP30: 0
A31: ALTEVI JUARI PEREIRA | B31: Coleta de Lixo Varzea Grande MT | C31: A | D31: N | E31: 5730.19 | F31: 0 | G31: 0 | H31: 0 | I31: 0 | J31: 458.42 | K31: 0 | L31: 0 | M31: 0 | N31: 0 | O31: 5730.19 | P31: 0 | Q31: 0 | R31: 603.72 | S31: 0 | T31: 0 | U31: 0 | V31: 5730.19 | W31: 0 | X31: 284.41 | Y31: 0 | Z31: 0 | AA31: 213.04 | AB31: 1146.04 | AC31: 332.35 | AD31: 2295.15 | AE31: =(E31+F31+G31+H31+I31)-AH31 -> 0 | AF31: =(J31+K31+L31+M31+N31)-AI31 -> 0.01 | AG31: ALTEVI JUARI PEREIRA | AH31: 5730.19 | AI31: 458.41 | AJ31: =(O31+P31)-(AM31+AO31) -> 0 | AK31: =(R31+S31+T31+U31)-(AN31+AP31) -> 0 | AL31: ALTEVI JUARI PEREIRA | AM31: 5730.19 | AN31: 603.72 | AO31: 0 | AP31: 0
A32: ALVARO RUPPENTHAL | B32: Coleta de Lixo Varzea Grande MT | C32: D | D32: N | E32: 576.08 | F32: 0 | G32: 0 | H32: 1801.08 | I32: 0 | J32: 46.09 | K32: 0 | L32: 0 | M32: 144.09 | N32: 0 | O32: 576.08 | P32: 1801.08 | Q32: 0 | R32: 43.2 | S32: 137.77 | T32: 0 | U32: 0 | V32: 576.08 | W32: 0 | X32: 0 | Y32: 0 | Z32: 0 | AA32: 88.38 | AB32: 475.43 | AC32: 137.88 | AD32: 882.66 | AE32: =(E32+F32+G32+H32+I32)-AH32 -> 2377.16 | AF32: =(J32+K32+L32+M32+N32)-AI32 -> 190.18 | AJ32: =(O32+P32)-(AM32+AO32) -> 0 | AK32: =(R32+S32+T32+U32)-(AN32+AP32) -> 0 | AL32: ALVARO RUPPENTHAL | AM32: 576.08 | AN32: 43.2 | AO32: 1801.08 | AP32: 137.77
A33: ALYSON CAVALCANTE DO CARMO | B33: CDHU - Balbinos "D" 19 U.H. | C33: A | D33: N | E33: 784.67 | F33: 0 | G33: 0 | H33: 0 | I33: 0 | J33: 62.77 | K33: 0 | L33: 0 | M33: 0 | N33: 0 | O33: 784.67 | P33: 0 | Q33: 0 | R33: 58.85 | S33: 0 | T33: 0 | U33: 0 | V33: 784.67 | W33: 0 | X33: 0 | Y33: 0 | Z33: 0 | AA33: 29.17 | AB33: 156.93 | AC33: 45.51 | AD33: 290.47 | AE33: =(E33+F33+G33+H33+I33)-AH33 -> 0 | AF33: =(J33+K33+L33+M33+N33)-AI33 -> 0 | AG33: ALYSON CAVALCANTE DO CARMO | AH33: 784.67 | AI33: 62.77 | AJ33: =(O33+P33)-(AM33+AO33) -> 0 | AK33: =(R33+S33+T33+U33)-(AN33+AP33) -> 0 | AL33: ALYSON CAVALCANTE DO CARMO | AM33: 784.67 | AN33: 58.85 | AO33: 0 | AP33: 0
A34: ANA LAURA SILVA SOARES | B34: CDHU - Ilha Solteira "D" 100 U.H. | C34: A | D34: N | E34: 2839.05 | F34: 0 | G34: 0 | H34: 0 | I34: 0 | J34: 227.12 | K34: 0 | L34: 0 | M34: 0 | N34: 0 | O34: 2839.05 | P34: 0 | Q34: 0 | R34: 231.19 | S34: 0 | T34: 0 | U34: 0 | V34: 2839.05 | W34: 0 | X34: 0 | Y34: 0 | Z34: 0 | AA34: 105.55 | AB34: 567.81 | AC34: 164.66 | AD34: 1069.22 | AE34: =(E34+F34+G34+H34+I34)-AH34 -> 0 | AF34: =(J34+K34+L34+M34+N34)-AI34 -> 0 | AG34: ANA LAURA SILVA SOARES | AH34: 2839.05 | AI34: 227.12 | AJ34: =(O34+P34)-(AM34+AO34) -> 0 | AK34: =(R34+S34+T34+U34)-(AN34+AP34) -> 0 | AL34: ANA LAURA SILVA SOARES | AM34: 2839.05 | AN34: 231.19 | AO34: 0 | AP34: 0
A35: ANDERSON DA CONCEIÇÃO SANTOS | B35: CDHU - Duartina "E1" "E2" 128 U.H. | C35: A | D35: N | E35: 2945.87 | F35: 0 | G35: 0 | H35: 0 | I35: 0 | J35: 235.67 | K35: 0 | L35: 0 | M35: 0 | N35: 0 | O35: 2945.87 | P35: 0 | Q35: 0 | R35: 242.09 | S35: 0 | T35: 0 | U35: 0 | V35: 2945.87 | W35: 0 | X35: 0 | Y35: 0 | Z35: 0 | AA35: 109.52 | AB35: 589.17 | AC35: 170.86 | AD35: 1111.65 | AE35: =(E35+F35+G35+H35+I35)-AH35 -> 0 | AF35: =(J35+K35+L35+M35+N35)-AI35 -> 0.01 | AG35: ANDERSON DA CONCEICAO SANTOS | AH35: 2945.87 | AI35: 235.66 | AJ35: =(O35+P35)-(AM35+AO35) -> 0 | AK35: =(R35+S35+T35+U35)-(AN35+AP35) -> 0 | AL35: ANDERSON DA CONCEICAO SANTOS | AM35: 2945.87 | AN35: 242.09 | AO35: 0 | AP35: 0
A36: ANDERSON JOSE CONOTO LANDER | B36: Coleta de Lixo Varzea Grande MT | C36: A | D36: N | E36: 3571.75 | F36: 0 | G36: 0 | H36: 0 | I36: 0 | J36: 285.74 | K36: 0 | L36: 0 | M36: 0 | N36: 0 | O36: 3571.75 | P36: 0 | Q36: 0 | R36: 317.19 | S36: 0 | T36: 0 | U36: 0 | V36: 3571.75 | W36: 0 | X36: 0 | Y36: 0 | Z36: 0 | AA36: 132.79 | AB36: 714.35 | AC36: 207.16 | AD36: 1371.5 | AE36: =(E36+F36+G36+H36+I36)-AH36 -> 0 | AF36: =(J36+K36+L36+M36+N36)-AI36 -> 0 | AG36: ANDERSON JOSE CONOTO LANDER | AH36: 3571.75 | AI36: 285.74 | AJ36: =(O36+P36)-(AM36+AO36) -> 0 | AK36: =(R36+S36+T36+U36)-(AN36+AP36) -> 0 | AL36: ANDERSON JOSE CONOTO LANDER | AM36: 3571.75 | AN36: 317.19 | AO36: 0 | AP36: 0
A37: ANDERSON NEVES FERREIRA | B37: Coleta de Lixo Varzea Grande MT | C37: A | D37: N | E37: 6411.17 | F37: 0 | G37: 0 | H37: 0 | I37: 0 | J37: 512.89 | K37: 0 | L37: 0 | M37: 0 | N37: 0 | O37: 6411.17 | P37: 0 | Q37: 0 | R37: 699.06 | S37: 0 | T37: 0 | U37: 0 | V37: 6411.17 | W37: 0 | X37: 537.09 | Y37: 0 | Z37: 0 | AA37: 238.36 | AB37: 1282.23 | AC37: 371.85 | AD37: 2591.5 | AE37: =(E37+F37+G37+H37+I37)-AH37 -> 0 | AF37: =(J37+K37+L37+M37+N37)-AI37 -> 0 | AG37: ANDERSON NEVES FERREIRA | AH37: 6411.17 | AI37: 512.89 | AJ37: =(O37+P37)-(AM37+AO37) -> 0 | AK37: =(R37+S37+T37+U37)-(AN37+AP37) -> 0 | AL37: ANDERSON NEVES FERREIRA | AM37: 6411.17 | AN37: 699.06 | AO37: 0 | AP37: 0
A38: ANDRE HENRIQUE SANTOS DE PAULA | B38: Coleta de Lixo Varzea Grande MT | C38: A | D38: N | E38: 3437.75 | F38: 0 | G38: 0 | H38: 0 | I38: 0 | J38: 275.02 | K38: 0 | L38: 0 | M38: 0 | N38: 0 | O38: 3437.75 | P38: 0 | Q38: 0 | R38: 301.11 | S38: 0 | T38: 0 | U38: 0 | V38: 3437.75 | W38: 0 | X38: 0 | Y38: 0 | Z38: 0 | AA38: 127.81 | AB38: 687.55 | AC38: 199.39 | AD38: 1315.86 | AE38: =(E38+F38+G38+H38+I38)-AH38 -> 0 | AF38: =(J38+K38+L38+M38+N38)-AI38 -> 0 | AG38: ANDRE HENRIQUE SANTOS DE PAULA | AH38: 3437.75 | AI38: 275.02 | AJ38: =(O38+P38)-(AM38+AO38) -> 0 | AK38: =(R38+S38+T38+U38)-(AN38+AP38) -> 0 | AL38: ANDRE HENRIQUE SANTOS DE PAULA | AM38: 3437.75 | AN38: 301.11 | AO38: 0 | AP38: 0
A39: ANTONIO MARCOS DE PAULA LINO | B39: Oficina | C39: D | D39: N | E39: 5834.26 | F39: 5161.33 | G39: 367.38 | H39: 1836.9 | I39: 0 | J39: 466.74 | K39: 412.91 | L39: 29.39 | M39: 146.95 | N39: 0 | O39: 5834.26 | P39: 2204.28 | Q39: 0 | R39: 618.29 | S39: 174.06 | T39: 0 | U39: 0 | V39: 5834.26 | W39: 0 | X39: 323.84 | Y39: 0 | Z39: 0 | AA39: 298.86 | AB39: 1607.71 | AC39: 466.24 | AD39: 3165.16 | AE39: =(E39+F39+G39+H39+I39)-AH39 -> 13199.87 | AF39: =(J39+K39+L39+M39+N39)-AI39 -> 1055.99 | AJ39: =(O39+P39)-(AM39+AO39) -> 0 | AK39: =(R39+S39+T39+U39)-(AN39+AP39) -> 0 | AL39: ANTONIO MARCOS DE PAULA LINO | AM39: 5834.26 | AN39: 618.29 | AO39: 2204.28 | AP39: 174.06
A40: ANTONIO MARTINS DA SILVA | B40: Coleta de Lixo Varzea Grande MT | C40: A | D40: N | E40: 3781.66 | F40: 0 | G40: 0 | H40: 0 | I40: 0 | J40: 302.53 | K40: 0 | L40: 0 | M40: 0 | N40: 0 | O40: 3781.66 | P40: 0 | Q40: 0 | R40: 342.38 | S40: 0 | T40: 0 | U40: 0 | V40: 3781.66 | W40: 0 | X40: 0 | Y40: 0 | Z40: 0 | AA40: 140.6 | AB40: 756.33 | AC40: 219.34 | AD40: 1458.65 | AE40: =(E40+F40+G40+H40+I40)-AH40 -> 0 | AF40: =(J40+K40+L40+M40+N40)-AI40 -> 0 | AG40: ANTONIO MARTINS DA SILVA | AH40: 3781.66 | AI40: 302.53 | AJ40: =(O40+P40)-(AM40+AO40) -> 0 | AK40: =(R40+S40+T40+U40)-(AN40+AP40) -> 0 | AL40: ANTONIO MARTINS DA SILVA | AM40: 3781.66 | AN40: 342.38 | AO40: 0 | AP40: 0
A41: ANTONIO MENDES DA LUZ | B41: Coleta de Lixo Varzea Grande MT | C41: A | D41: N | E41: 3396.76 | F41: 0 | G41: 0 | H41: 0 | I41: 0 | J41: 271.74 | K41: 0 | L41: 0 | M41: 0 | N41: 0 | O41: 3396.76 | P41: 0 | Q41: 0 | R41: 296.2 | S41: 0 | T41: 0 | U41: 0 | V41: 3396.76 | W41: 0 | X41: 0 | Y41: 0 | Z41: 0 | AA41: 126.29 | AB41: 679.35 | AC41: 197.01 | AD41: 1298.85 | AE41: =(E41+F41+G41+H41+I41)-AH41 -> 0 | AF41: =(J41+K41+L41+M41+N41)-AI41 -> 0 | AG41: ANTONIO MENDES DA LUZ | AH41: 3396.76 | AI41: 271.74 | AJ41: =(O41+P41)-(AM41+AO41) -> 0 | AK41: =(R41+S41+T41+U41)-(AN41+AP41) -> 0 | AL41: ANTONIO MENDES DA LUZ | AM41: 3396.76 | AN41: 296.2 | AO41: 0 | AP41: 0
A42: ANTONIO ROBERTO DE SOUZA | B42: CDHU - Bocaina "H1" "H2" 96 U.H. | C42: A | D42: N | E42: 3169.1 | F42: 0 | G42: 0 | H42: 0 | I42: 0 | J42: 253.53 | K42: 0 | L42: 0 | M42: 0 | N42: 0 | O42: 3169.1 | P42: 0 | Q42: 0 | R42: 268.88 | S42: 0 | T42: 0 | U42: 0 | V42: 3169.1 | W42: 0 | X42: 0 | Y42: 0 | Z42: 0 | AA42: 117.82 | AB42: 633.82 | AC42: 183.81 | AD42: 1204.33 | AE42: =(E42+F42+G42+H42+I42)-AH42 -> 0 | AF42: =(J42+K42+L42+M42+N42)-AI42 -> 0.01 | AG42: ANTONIO ROBERTO DE SOUZA | AH42: 3169.1 | AI42: 253.52 | AJ42: =(O42+P42)-(AM42+AO42) -> 0 | AK42: =(R42+S42+T42+U42)-(AN42+AP42) -> 0 | AL42: ANTONIO ROBERTO DE SOUZA | AM42: 3169.1 | AN42: 268.88 | AO42: 0 | AP42: 0
A43: APARECIDO LUIZ BENITTE CANHADA | B43: CDHU - Mirandopolis "D" 259 U.H. | C43: P | D43: N | E43: 0 | F43: 0 | G43: 0 | H43: 0 | I43: 0 | J43: 0 | K43: 0 | L43: 0 | M43: 0 | N43: 0 | O43: 0 | P43: 0 | Q43: 0 | R43: 0 | S43: 0 | T43: 0 | U43: 0 | V43: 0 | W43: 0 | X43: 0 | Y43: 0 | Z43: 0 | AA43: 0 | AB43: 0 | AC43: 0 | AD43: 0 | AE43: =(E43+F43+G43+H43+I43)-AH43 -> 0 | AF43: =(J43+K43+L43+M43+N43)-AI43 -> 0 | AJ43: =(O43+P43)-(AM43+AO43) -> 0 | AK43: =(R43+S43+T43+U43)-(AN43+AP43) -> 0
A44: ARIANO JOSE CONCEICAO DE SOUZA | B44: Coleta de Lixo Varzea Grande MT | C44: A | D44: N | E44: 3283.12 | F44: 0 | G44: 0 | H44: 0 | I44: 0 | J44: 262.65 | K44: 0 | L44: 0 | M44: 0 | N44: 0 | O44: 3283.12 | P44: 0 | Q44: 0 | R44: 282.56 | S44: 0 | T44: 0 | U44: 0 | V44: 3283.12 | W44: 0 | X44: 0 | Y44: 0 | Z44: 0 | AA44: 122.06 | AB44: 656.62 | AC44: 190.42 | AD44: 1251.67 | AE44: =(E44+F44+G44+H44+I44)-AH44 -> 0 | AF44: =(J44+K44+L44+M44+N44)-AI44 -> 0.01 | AG44: ARIANO JOSE CONCEICAO DE SOUZA | AH44: 3283.12 | AI44: 262.64 | AJ44: =(O44+P44)-(AM44+AO44) -> 0 | AK44: =(R44+S44+T44+U44)-(AN44+AP44) -> 0 | AL44: ARIANO JOSE CONCEICAO DE SOUZA | AM44: 3283.12 | AN44: 282.56 | AO44: 0 | AP44: 0
A45: ARLINE MORAES DA SILVA | B45: Coleta de Lixo Varzea Grande MT | C45: A | D45: N | E45: 2234.65 | F45: 0 | G45: 0 | H45: 0 | I45: 0 | J45: 178.77 | K45: 0 | L45: 0 | M45: 0 | N45: 0 | O45: 2234.65 | P45: 0 | Q45: 0 | R45: 176.79 | S45: 0 | T45: 0 | U45: 0 | V45: 2234.65 | W45: 0 | X45: 0 | Y45: 0 | Z45: 0 | AA45: 83.08 | AB45: 446.93 | AC45: 129.61 | AD45: 836.41 | AE45: =(E45+F45+G45+H45+I45)-AH45 -> 0 | AF45: =(J45+K45+L45+M45+N45)-AI45 -> 0 | AG45: ARLINE MORAES DA SILVA | AH45: 2234.65 | AI45: 178.77 | AJ45: =(O45+P45)-(AM45+AO45) -> 0 | AK45: =(R45+S45+T45+U45)-(AN45+AP45) -> 0 | AL45: ARLINE MORAES DA SILVA | AM45: 2234.65 | AN45: 176.79 | AO45: 0 | AP45: 0
A46: ARNALDO FERREIRA DE MELO | B46: Coleta de Lixo Varzea Grande MT | C46: D | D46: N | E46: 196.83 | F46: 0 | G46: 0 | H46: 0 | I46: 0 | J46: 15.75 | K46: 0 | L46: 0 | M46: 0 | N46: 0 | O46: 196.83 | P46: 0 | Q46: 0 | R46: 14.76 | S46: 0 | T46: 0 | U46: 0 | V46: 196.83 | W46: 0 | X46: 0 | Y46: 0 | Z46: 0 | AA46: 7.32 | AB46: 39.37 | AC46: 11.42 | AD46: 72.86 | AE46: =(E46+F46+G46+H46+I46)-AH46 -> 0 | AF46: =(J46+K46+L46+M46+N46)-AI46 -> 0.01 | AG46: ARNALDO FERREIRA DE MELO | AH46: 196.83 | AI46: 15.74 | AJ46: =(O46+P46)-(AM46+AO46) -> 0 | AK46: =(R46+S46+T46+U46)-(AN46+AP46) -> 0 | AL46: ARNALDO FERREIRA DE MELO | AM46: 196.83 | AN46: 14.76 | AO46: 0 | AP46: 0
A47: BENEDITO PALOCO | B47: CDHU - Piratininga "E1" 56 U.H. | C47: A | D47: N | E47: 2724.57 | F47: 0 | G47: 0 | H47: 0 | I47: 0 | J47: 217.97 | K47: 0 | L47: 0 | M47: 0 | N47: 0 | O47: 2724.57 | P47: 0 | Q47: 0 | R47: 220.89 | S47: 0 | T47: 0 | U47: 0 | V47: 2724.57 | W47: 0 | X47: 0 | Y47: 0 | Z47: 0 | AA47: 101.3 | AB47: 544.91 | AC47: 158.03 | AD47: 1025.13 | AE47: =(E47+F47+G47+H47+I47)-AH47 -> 0 | AF47: =(J47+K47+L47+M47+N47)-AI47 -> 0.01 | AG47: BENEDITO PALOCO | AH47: 2724.57 | AI47: 217.96 | AJ47: =(O47+P47)-(AM47+AO47) -> 0 | AK47: =(R47+S47+T47+U47)-(AN47+AP47) -> 0 | AL47: BENEDITO PALOCO | AM47: 2724.57 | AN47: 220.89 | AO47: 0 | AP47: 0
A48: BENTO PEREIRA AMADO | B48: CDHU - Mirandopolis "D" 259 U.H. | C48: D | D48: N | E48: 2396.23 | F48: 293.32 | G48: 0 | H48: 2214.34 | I48: 0 | J48: 191.7 | K48: 23.47 | L48: 0 | M48: 177.15 | N48: 0 | O48: 2396.23 | P48: 2214.34 | Q48: 0 | R48: 191.34 | S48: 174.97 | T48: 0 | U48: 0 | V48: 2396.23 | W48: 0 | X48: 0 | Y48: 0 | Z48: 0 | AA48: 171.42 | AB48: 922.11 | AC48: 267.41 | AD48: 1727.25 | AE48: =(E48+F48+G48+H48+I48)-AH48 -> 4903.89 | AF48: =(J48+K48+L48+M48+N48)-AI48 -> 392.32 | AJ48: =(O48+P48)-(AM48+AO48) -> 0 | AK48: =(R48+S48+T48+U48)-(AN48+AP48) -> 0 | AL48: BENTO PEREIRA AMADO | AM48: 2396.23 | AN48: 191.34 | AO48: 2214.34 | AP48: 174.97
A49: BIBIANO ANASTACIO DE PAULA | B49: Coleta de Lixo Varzea Grande MT | C49: A | D49: N | E49: 3805.54 | F49: 0 | G49: 0 | H49: 0 | I49: 0 | J49: 304.44 | K49: 0 | L49: 0 | M49: 0 | N49: 0 | O49: 3805.54 | P49: 0 | Q49: 0 | R49: 345.25 | S49: 0 | T49: 0 | U49: 0 | V49: 3805.54 | W49: 0 | X49: 0 | Y49: 0 | Z49: 0 | AA49: 141.49 | AB49: 761.11 | AC49: 220.72 | AD49: 1468.57 | AE49: =(E49+F49+G49+H49+I49)-AH49 -> 0 | AF49: =(J49+K49+L49+M49+N49)-AI49 -> 0 | AG49: BIBIANO ANASTACIO DE PAULA | AH49: 3805.54 | AI49: 304.44 | AJ49: =(O49+P49)-(AM49+AO49) -> 0 | AK49: =(R49+S49+T49+U49)-(AN49+AP49) -> 0 | AL49: BIBIANO ANASTACIO DE PAULA | AM49: 3805.54 | AN49: 345.25 | AO49: 0 | AP49: 0
A50: BRENO ROSA DE ALMEIDA | B50: Coleta de Lixo Varzea Grande MT | C50: A | D50: N | E50: 3158.92 | F50: 0 | G50: 0 | H50: 0 | I50: 0 | J50: 252.71 | K50: 0 | L50: 0 | M50: 0 | N50: 0 | O50: 3158.92 | P50: 0 | Q50: 0 | R50: 267.65 | S50: 0 | T50: 0 | U50: 0 | V50: 3158.92 | W50: 0 | X50: 0 | Y50: 0 | Z50: 0 | AA50: 117.45 | AB50: 631.78 | AC50: 183.22 | AD50: 1200.1 | AE50: =(E50+F50+G50+H50+I50)-AH50 -> 0 | AF50: =(J50+K50+L50+M50+N50)-AI50 -> 0 | AG50: BRENO ROSA DE ALMEIDA | AH50: 3158.92 | AI50: 252.71 | AJ50: =(O50+P50)-(AM50+AO50) -> 0 | AK50: =(R50+S50+T50+U50)-(AN50+AP50) -> 0 | AL50: BRENO ROSA DE ALMEIDA | AM50: 3158.92 | AN50: 267.65 | AO50: 0 | AP50: 0
A51: CAIO FERNANDES CALIXTO | B51: Financeiro | C51: A | D51: Z | E51: 641.42 | F51: 0 | G51: 0 | H51: 0 | I51: 0 | J51: 12.83 | K51: 0 | L51: 0 | M51: 0 | N51: 0 | O51: 641.42 | P51: 0 | Q51: 0 | R51: 48.1 | S51: 0 | T51: 0 | U51: 0 | V51: 641.42 | W51: 0 | X51: 0 | Y51: 0 | Z51: 0 | AA51: 23.85 | AB51: 128.28 | AC51: 37.2 | AD51: 237.43 | AE51: =(E51+F51+G51+H51+I51)-AH51 -> 0 | AF51: =(J51+K51+L51+M51+N51)-AI51 -> 0.01 | AG51: CAIO FERNANDES CALIXTO | AH51: 641.42 | AI51: 12.82 | AJ51: =(O51+P51)-(AM51+AO51) -> 0 | AK51: =(R51+S51+T51+U51)-(AN51+AP51) -> 0 | AL51: CAIO FERNANDES CALIXTO | AM51: 641.42 | AN51: 48.1 | AO51: 0 | AP51: 0
A52: CALIXTO CONCEICAO DE ARRUDA | B52: Coleta de Lixo Varzea Grande MT | C52: A | D52: N | E52: 3624.63 | F52: 0 | G52: 0 | H52: 0 | I52: 0 | J52: 289.97 | K52: 0 | L52: 0 | M52: 0 | N52: 0 | O52: 3624.63 | P52: 0 | Q52: 0 | R52: 323.54 | S52: 0 | T52: 0 | U52: 0 | V52: 3624.63 | W52: 0 | X52: 0 | Y52: 0 | Z52: 0 | AA52: 134.76 | AB52: 724.93 | AC52: 210.23 | AD52: 1393.45 | AE52: =(E52+F52+G52+H52+I52)-AH52 -> 0 | AF52: =(J52+K52+L52+M52+N52)-AI52 -> 0 | AG52: CALIXTO CONCEICAO DE ARRUDA | AH52: 3624.63 | AI52: 289.97 | AJ52: =(O52+P52)-(AM52+AO52) -> 0 | AK52: =(R52+S52+T52+U52)-(AN52+AP52) -> 0 | AL52: CALIXTO CONCEICAO DE ARRUDA | AM52: 3624.63 | AN52: 323.54 | AO52: 0 | AP52: 0
A53: CARLITO PAULA DOS SANTOS | B53: CDHU - Piratininga "E1" 56 U.H. | C53: A | D53: N | E53: 3200.88 | F53: 0 | G53: 0 | H53: 0 | I53: 0 | J53: 256.07 | K53: 0 | L53: 0 | M53: 0 | N53: 0 | O53: 3200.88 | P53: 0 | Q53: 0 | R53: 272.69 | S53: 0 | T53: 0 | U53: 0 | V53: 3200.88 | W53: 0 | X53: 0 | Y53: 0 | Z53: 0 | AA53: 119.01 | AB53: 640.18 | AC53: 185.65 | AD53: 1217.52 | AE53: =(E53+F53+G53+H53+I53)-AH53 -> 0 | AF53: =(J53+K53+L53+M53+N53)-AI53 -> 0 | AG53: CARLITO PAULA DOS SANTOS | AH53: 3200.88 | AI53: 256.07 | AJ53: =(O53+P53)-(AM53+AO53) -> 0 | AK53: =(R53+S53+T53+U53)-(AN53+AP53) -> 0 | AL53: CARLITO PAULA DOS SANTOS | AM53: 3200.88 | AN53: 272.69 | AO53: 0 | AP53: 0
A54: CARLOS ANDRE OLIVEIRA DA SILVA | B54: CDHU - Birigui "D" 143 U.H. | C54: A | D54: N | E54: 3112.09 | F54: 0 | G54: 0 | H54: 0 | I54: 0 | J54: 248.97 | K54: 0 | L54: 0 | M54: 0 | N54: 0 | O54: 3112.09 | P54: 0 | Q54: 0 | R54: 262.04 | S54: 0 | T54: 0 | U54: 0 | V54: 3112.09 | W54: 0 | X54: 0 | Y54: 0 | Z54: 0 | AA54: 115.7 | AB54: 622.42 | AC54: 180.5 | AD54: 1180.66 | AE54: =(E54+F54+G54+H54+I54)-AH54 -> 0 | AF54: =(J54+K54+L54+M54+N54)-AI54 -> 0.01 | AG54: CARLOS ANDRE OLIVEIRA DA SILVA | AH54: 3112.09 | AI54: 248.96 | AJ54: =(O54+P54)-(AM54+AO54) -> 0 | AK54: =(R54+S54+T54+U54)-(AN54+AP54) -> 0 | AL54: CARLOS ANDRE OLIVEIRA DA SILVA | AM54: 3112.09 | AN54: 262.04 | AO54: 0 | AP54: 0
A55: CARLOS EDUARDO OLIVEIRA DE LIMA | B55: Coleta de Lixo Varzea Grande MT | C55: D | D55: N | E55: 799.32 | F55: 0 | G55: 0 | H55: 2104.08 | I55: 0 | J55: 63.95 | K55: 0 | L55: 0 | M55: 168.33 | N55: 0 | O55: 799.32 | P55: 2104.08 | Q55: 0 | R55: 59.94 | S55: 165.04 | T55: 0 | U55: 0 | V55: 799.32 | W55: 0 | X55: 0 | Y55: 0 | Z55: 0 | AA55: 107.95 | AB55: 580.68 | AC55: 168.4 | AD55: 1082 | AE55: =(E55+F55+G55+H55+I55)-AH55 -> 0 | AF55: =(J55+K55+L55+M55+N55)-AI55 -> 0.02 | AG55: CARLOS EDUARDO OLIVEIRA DE LIMA | AH55: 2903.4 | AI55: 232.26 | AJ55: =(O55+P55)-(AM55+AO55) -> 0 | AK55: =(R55+S55+T55+U55)-(AN55+AP55) -> 0 | AL55: CARLOS EDUARDO OLIVEIRA DE LIMA | AM55: 799.32 | AN55: 59.94 | AO55: 2104.08 | AP55: 165.04
A56: CARLOS EDUARDO SILVEIRA COSTA | B56: Coleta de Lixo Varzea Grande MT | C56: A | D56: N | E56: 6175.9 | F56: 0 | G56: 0 | H56: 0 | I56: 0 | J56: 494.07 | K56: 0 | L56: 0 | M56: 0 | N56: 0 | O56: 6175.9 | P56: 0 | Q56: 0 | R56: 666.12 | S56: 0 | T56: 0 | U56: 0 | V56: 6175.9 | W56: 0 | X56: 397.99 | Y56: 0 | Z56: 0 | AA56: 229.61 | AB56: 1235.18 | AC56: 358.2 | AD56: 2489.12 | AE56: =(E56+F56+G56+H56+I56)-AH56 -> 0 | AF56: =(J56+K56+L56+M56+N56)-AI56 -> 0 | AG56: CARLOS EDUARDO SILVEIRA COSTA | AH56: 6175.9 | AI56: 494.07 | AJ56: =(O56+P56)-(AM56+AO56) -> 0 | AK56: =(R56+S56+T56+U56)-(AN56+AP56) -> 0 | AL56: CARLOS EDUARDO SILVEIRA COSTA | AM56: 6175.9 | AN56: 666.12 | AO56: 0 | AP56: 0
A57: CARLOS LUIZ DOS SANTOS | B57: CDHU - Birigui "D" 143 U.H. | C57: A | D57: N | E57: 3710.73 | F57: 0 | G57: 0 | H57: 0 | I57: 0 | J57: 296.86 | K57: 0 | L57: 0 | M57: 0 | N57: 0 | O57: 3710.73 | P57: 0 | Q57: 0 | R57: 333.87 | S57: 0 | T57: 0 | U57: 0 | V57: 3710.73 | W57: 0 | X57: 0 | Y57: 0 | Z57: 0 | AA57: 137.96 | AB57: 742.15 | AC57: 215.22 | AD57: 1429.2 | AE57: =(E57+F57+G57+H57+I57)-AH57 -> 0 | AF57: =(J57+K57+L57+M57+N57)-AI57 -> 0.01 | AG57: CARLOS LUIZ DOS SANTOS | AH57: 3710.73 | AI57: 296.85 | AJ57: =(O57+P57)-(AM57+AO57) -> 0 | AK57: =(R57+S57+T57+U57)-(AN57+AP57) -> 0 | AL57: CARLOS LUIZ DOS SANTOS | AM57: 3710.73 | AN57: 333.87 | AO57: 0 | AP57: 0
A58: CARLOS VINICIUS DE LIMA CAMPOS | B58: Coleta de Lixo Varzea Grande MT | C58: A | D58: N | E58: 3633.07 | F58: 0 | G58: 0 | H58: 0 | I58: 0 | J58: 290.65 | K58: 0 | L58: 0 | M58: 0 | N58: 0 | O58: 3633.07 | P58: 0 | Q58: 0 | R58: 324.55 | S58: 0 | T58: 0 | U58: 0 | V58: 3633.07 | W58: 0 | X58: 0 | Y58: 0 | Z58: 0 | AA58: 135.07 | AB58: 726.61 | AC58: 210.72 | AD58: 1396.96 | AE58: =(E58+F58+G58+H58+I58)-AH58 -> 0 | AF58: =(J58+K58+L58+M58+N58)-AI58 -> 0.01 | AG58: CARLOS VINICIUS DE LIMA CAMPOS | AH58: 3633.07 | AI58: 290.64 | AJ58: =(O58+P58)-(AM58+AO58) -> 0 | AK58: =(R58+S58+T58+U58)-(AN58+AP58) -> 0 | AL58: CARLOS VINICIUS DE LIMA CAMPOS | AM58: 3633.07 | AN58: 324.55 | AO58: 0 | AP58: 0
A59: CARLOS WILLIAM PAULA DE SOUZA | B59: Coleta de Lixo Varzea Grande MT | C59: A | D59: N | E59: 3288.34 | F59: 0 | G59: 0 | H59: 0 | I59: 0 | J59: 263.07 | K59: 0 | L59: 0 | M59: 0 | N59: 0 | O59: 3288.34 | P59: 0 | Q59: 0 | R59: 283.19 | S59: 0 | T59: 0 | U59: 0 | V59: 3288.34 | W59: 0 | X59: 0 | Y59: 0 | Z59: 0 | AA59: 122.26 | AB59: 657.67 | AC59: 190.72 | AD59: 1253.84 | AE59: =(E59+F59+G59+H59+I59)-AH59 -> 0 | AF59: =(J59+K59+L59+M59+N59)-AI59 -> 0.01 | AG59: CARLOS WILLIAM PAULA DE SOUZA | AH59: 3288.34 | AI59: 263.06 | AJ59: =(O59+P59)-(AM59+AO59) -> 0 | AK59: =(R59+S59+T59+U59)-(AN59+AP59) -> 0 | AL59: CARLOS WILLIAM PAULA DE SOUZA | AM59: 3288.34 | AN59: 283.19 | AO59: 0 | AP59: 0
A60: CAUA RODRIGUES NORBERTO DA SILVA | B60: Coleta de Lixo Varzea Grande MT | C60: A | D60: N | E60: 3861.07 | F60: 0 | G60: 0 | H60: 0 | I60: 0 | J60: 308.89 | K60: 0 | L60: 0 | M60: 0 | N60: 0 | O60: 3861.07 | P60: 0 | Q60: 0 | R60: 351.91 | S60: 0 | T60: 0 | U60: 0 | V60: 3861.07 | W60: 0 | X60: 0 | Y60: 0 | Z60: 0 | AA60: 143.55 | AB60: 772.21 | AC60: 223.94 | AD60: 1491.62 | AE60: =(E60+F60+G60+H60+I60)-AH60 -> 0 | AF60: =(J60+K60+L60+M60+N60)-AI60 -> 0.01 | AG60: CAUA RODRIGUES NORBERTO DA SILVA | AH60: 3861.07 | AI60: 308.88 | AJ60: =(O60+P60)-(AM60+AO60) -> 0 | AK60: =(R60+S60+T60+U60)-(AN60+AP60) -> 0 | AL60: CAUA RODRIGUES NORBERTO DA SILVA | AM60: 3861.07 | AN60: 351.91 | AO60: 0 | AP60: 0
... A64: CLAUDINEI FERREIRA DA SILVA | B64: BR-488 e 459 - Lorena/Piquete/Aparecida | C64: A | D64: N | E64: 2998.36 | F64: 0 | G64: 0 | H64: 0 | I64: 0 | J64: 239.87 | K64: 0 | L64: 0 | M64: 0 | N64: 0 | O64: 2998.36 | P64: 0 | Q64: 0 | R64: 248.39 | S64: 0 | T64: 0 | U64: 0 | V64: 2998.36 | W64: 0 | X64: 0 | Y64: 0 | Z64: 0 | AA64: 111.48 | AB64: 599.67 | AC64: 173.9 | AD64: 1133.44 | AE64: =(E64+F64+G64+H64+I64)-AH64 -> 0 | AF64: =(J64+K64+L64+M64+N64)-AI64 -> 0.01 | AG64: CLAUDINEI FERREIRA DA SILVA | AH64: 2998.36 | AI64: 239.86 | AJ64: =(O64+P64)-(AM64+AO64) -> 0 | AK64: =(R64+S64+T64+U64)-(AN64+AP64) -> 0 | AL64: CLAUDINEI FERREIRA DA SILVA | AM64: 2998.36 | AN64: 248.39 | AO64: 0 | AP64: 0
A65: CLAUDIO MODESTO | B65: CDHU - Mirandopolis "D" 259 U.H. | C65: D | D65: N | E65: 487.12 | F65: 471.09 | G65: 0 | H65: 1570.36 | I65: 0 | J65: 38.97 | K65: 37.69 | L65: 0 | M65: 125.63 | N65: 0 | O65: 487.12 | P65: 1570.36 | Q65: 0 | R65: 36.53 | S65: 117.77 | T65: 0 | U65: 0 | V65: 487.12 | W65: 0 | X65: 0 | Y65: 0 | Z65: 0 | AA65: 76.5 | AB65: 411.5 | AC65: 119.33 | AD65: 761.62 | AE65: =(E65+F65+G65+H65+I65)-AH65 -> 2528.57 | AF65: =(J65+K65+L65+M65+N65)-AI65 -> 202.29 | AJ65: =(O65+P65)-(AM65+AO65) -> 0 | AK65: =(R65+S65+T65+U65)-(AN65+AP65) -> 0 | AL65: CLAUDIO MODESTO | AM65: 487.12 | AN65: 36.53 | AO65: 1570.36 | AP65: 117.77
A66: CLAUDIONOR RODRIGUES VILHENA JUNIOR | B66: Oficina | C66: A | D66: N | E66: 4736.27 | F66: 0 | G66: 0 | H66: 0 | I66: 0 | J66: 378.9 | K66: 0 | L66: 0 | M66: 0 | N66: 0 | O66: 4736.27 | P66: 0 | Q66: 0 | R66: 464.58 | S66: 0 | T66: 0 | U66: 0 | V66: 4736.27 | W66: 0 | X66: 0 | Y66: 0 | Z66: 0 | AA66: 176.09 | AB66: 947.25 | AC66: 274.7 | AD66: 1862.63 | AE66: =(E66+F66+G66+H66+I66)-AH66 -> 0 | AF66: =(J66+K66+L66+M66+N66)-AI66 -> 0 | AG66: CLAUDIONOR RODRIGUES VILHENA JUNIOR | AH66: 4736.27 | AI66: 378.9 | AJ66: =(O66+P66)-(AM66+AO66) -> 0 | AK66: =(R66+S66+T66+U66)-(AN66+AP66) -> 0 | AL66: CLAUDIONOR RODRIGUES VILHENA JUNIOR | AM66: 4736.27 | AN66: 464.58 | AO66: 0 | AP66: 0
A67: CLEBER SCHNEIDERS MARTINS | B67: Coleta de Lixo Varzea Grande MT | C67: A | D67: N | E67: 3589.6 | F67: 0 | G67: 0 | H67: 0 | I67: 0 | J67: 287.17 | K67: 0 | L67: 0 | M67: 0 | N67: 0 | O67: 3589.6 | P67: 0 | Q67: 0 | R67: 319.34 | S67: 0 | T67: 0 | U67: 0 | V67: 3589.6 | W67: 0 | X67: 0 | Y67: 0 | Z67: 0 | AA67: 133.46 | AB67: 717.92 | AC67: 208.2 | AD67: 1378.91 | AE67: =(E67+F67+G67+H67+I67)-AH67 -> 0 | AF67: =(J67+K67+L67+M67+N67)-AI67 -> 0.01 | AG67: CLEBER SCHNEIDERS MARTINS | AH67: 3589.6 | AI67: 287.16 | AJ67: =(O67+P67)-(AM67+AO67) -> 0 | AK67: =(R67+S67+T67+U67)-(AN67+AP67) -> 0 | AL67: CLEBER SCHNEIDERS MARTINS | AM67: 3589.6 | AN67: 319.34 | AO67: 0 | AP67: 0
A68: CLEIVISON APARECIDO DA SILVA | B68: Coleta de Lixo Varzea Grande MT | C68: A | D68: N | E68: 3864.39 | F68: 0 | G68: 0 | H68: 0 | I68: 0 | J68: 309.15 | K68: 0 | L68: 0 | M68: 0 | N68: 0 | O68: 3864.39 | P68: 0 | Q68: 0 | R68: 352.31 | S68: 0 | T68: 0 | U68: 0 | V68: 3864.39 | W68: 0 | X68: 0 | Y68: 0 | Z68: 0 | AA68: 143.67 | AB68: 772.88 | AC68: 224.13 | AD68: 1493 | AE68: =(E68+F68+G68+H68+I68)-AH68 -> 0 | AF68: =(J68+K68+L68+M68+N68)-AI68 -> 0 | AG68: CLEIVISON APARECIDO DA SILVA | AH68: 3864.39 | AI68: 309.15 | AJ68: =(O68+P68)-(AM68+AO68) -> 0 | AK68: =(R68+S68+T68+U68)-(AN68+AP68) -> 0 | AL68: CLEIVISON APARECIDO DA SILVA | AM68: 3864.39 | AN68: 352.31 | AO68: 0 | AP68: 0
A69: CLEOMAR MOREIRA DOS SANTOS | B69: Coleta de Lixo Varzea Grande MT | C69: A | D69: N | E69: 6305.06 | F69: 0 | G69: 0 | H69: 0 | I69: 0 | J69: 504.4 | K69: 0 | L69: 0 | M69: 0 | N69: 0 | O69: 6305.06 | P69: 0 | Q69: 0 | R69: 684.21 | S69: 0 | T69: 0 | U69: 0 | V69: 6305.06 | W69: 0 | X69: 497.87 | Y69: 0 | Z69: 0 | AA69: 234.42 | AB69: 1261.01 | AC69: 365.69 | AD69: 2545.33 | AE69: =(E69+F69+G69+H69+I69)-AH69 -> 0 | AF69: =(J69+K69+L69+M69+N69)-AI69 -> 0 | AG69: CLEOMAR MOREIRA DOS SANTOS | AH69: 6305.06 | AI69: 504.4 | AJ69: =(O69+P69)-(AM69+AO69) -> 0 | AK69: =(R69+S69+T69+U69)-(AN69+AP69) -> 0 | AL69: CLEOMAR MOREIRA DOS SANTOS | AM69: 6305.06 | AN69: 684.21 | AO69: 0 | AP69: 0
A70: CLOVIS SERGIO RONDON | B70: Coleta de Lixo Varzea Grande MT | C70: A | D70: N | E70: 3780.92 | F70: 0 | G70: 0 | H70: 0 | I70: 0 | J70: 302.47 | K70: 0 | L70: 0 | M70: 0 | N70: 0 | O70: 3780.92 | P70: 0 | Q70: 0 | R70: 342.29 | S70: 0 | T70: 0 | U70: 0 | V70: 3780.92 | W70: 0 | X70: 0 | Y70: 0 | Z70: 0 | AA70: 140.57 | AB70: 756.18 | AC70: 219.29 | AD70: 1458.34 | AE70: =(E70+F70+G70+H70+I70)-AH70 -> 0 | AF70: =(J70+K70+L70+M70+N70)-AI70 -> 0 | AG70: CLOVIS SERGIO RONDON | AH70: 3780.92 | AI70: 302.47 | AJ70: =(O70+P70)-(AM70+AO70) -> 0 | AK70: =(R70+S70+T70+U70)-(AN70+AP70) -> 0 | AL70: CLOVIS SERGIO RONDON | AM70: 3780.92 | AN70: 342.29 | AO70: 0 | AP70: 0
A71: DANIEL DA SILVA FERREIRA | B71: Coleta de Lixo Varzea Grande MT | C71: D | D71: N | E71: 2666.62 | F71: 3376.78 | G71: 288.63 | H71: 2597.63 | I71: 0 | J71: 213.33 | K71: 270.14 | L71: 23.09 | M71: 207.81 | N71: 0 | O71: 2666.62 | P71: 2886.26 | Q71: 0 | R71: 215.67 | S71: 235.44 | T71: 0 | U71: 0 | V71: 2666.62 | W71: 0 | X71: 0 | Y71: 0 | Z71: 0 | AA71: 206.45 | AB71: 1110.58 | AC71: 322.07 | AD71: 2090.2 | AE71: =(E71+F71+G71+H71+I71)-AH71 -> 8929.66 | AF71: =(J71+K71+L71+M71+N71)-AI71 -> 714.37 | AJ71: =(O71+P71)-(AM71+AO71) -> 0 | AK71: =(R71+S71+T71+U71)-(AN71+AP71) -> 0 | AL71: DANIEL DA SILVA FERREIRA | AM71: 2666.62 | AN71: 215.67 | AO71: 2886.26 | AP71: 235.44
A72: DANIEL DOS SANTOS SOUZA | B72: Coleta de Lixo Varzea Grande MT | C72: A | D72: N | E72: 3345.93 | F72: 0 | G72: 0 | H72: 0 | I72: 0 | J72: 267.67 | K72: 0 | L72: 0 | M72: 0 | N72: 0 | O72: 3345.93 | P72: 0 | Q72: 0 | R72: 290.1 | S72: 0 | T72: 0 | U72: 0 | V72: 3345.93 | W72: 0 | X72: 0 | Y72: 0 | Z72: 0 | AA72: 124.4 | AB72: 669.19 | AC72: 194.06 | AD72: 1277.75 | AE72: =(E72+F72+G72+H72+I72)-AH72 -> 0 | AF72: =(J72+K72+L72+M72+N72)-AI72 -> 0 | AG72: DANIEL DOS SANTOS SOUZA | AH72: 3345.93 | AI72: 267.67 | AJ72: =(O72+P72)-(AM72+AO72) -> 0 | AK72: =(R72+S72+T72+U72)-(AN72+AP72) -> 0 | AL72: DANIEL DOS SANTOS SOUZA | AM72: 3345.93 | AN72: 290.1 | AO72: 0 | AP72: 0
A73: DANIEL FELIPE DA SILVA AMANCIO | B73: CDHU - Sabino "E1" "E2" 190 U.H. | C73: D | D73: N | E73: 1482.31 | F73: 0 | G73: 0 | H73: 2051.25 | I73: 0 | J73: 118.58 | K73: 0 | L73: 0 | M73: 164.1 | N73: 0 | O73: 1482.31 | P73: 2051.25 | Q73: 0 | R73: 111.17 | S73: 160.29 | T73: 0 | U73: 0 | V73: 1482.31 | W73: 0 | X73: 0 | Y73: 0 | Z73: 0 | AA73: 131.37 | AB73: 706.71 | AC73: 204.95 | AD73: 1314.49 | AE73: =(E73+F73+G73+H73+I73)-AH73 -> 0 | AF73: =(J73+K73+L73+M73+N73)-AI73 -> 0 | AG73: DANIEL FELIPE DA SILVA AMANCIO | AH73: 3533.56 | AI73: 282.68 | AJ73: =(O73+P73)-(AM73+AO73) -> 0 | AK73: =(R73+S73+T73+U73)-(AN73+AP73) -> 0 | AL73: DANIEL FELIPE DA SILVA AMANCIO | AM73: 1482.31 | AN73: 111.17 | AO73: 2051.25 | AP73: 160.29
A74: DANIEL RAIMUNDO | B74: BR-488 e 459 - Lorena/Piquete/Aparecida | C74: A | D74: N | E74: 3016.88 | F74: 0 | G74: 0 | H74: 0 | I74: 0 | J74: 241.35 | K74: 0 | L74: 0 | M74: 0 | N74: 0 | O74: 3016.88 | P74: 0 | Q74: 0 | R74: 250.61 | S74: 0 | T74: 0 | U74: 0 | V74: 3016.88 | W74: 0 | X74: 0 | Y74: 0 | Z74: 0 | AA74: 112.16 | AB74: 603.38 | AC74: 174.98 | AD74: 1141.13 | AE74: =(E74+F74+G74+H74+I74)-AH74 -> 0 | AF74: =(J74+K74+L74+M74+N74)-AI74 -> 0 | AG74: DANIEL RAIMUNDO | AH74: 3016.88 | AI74: 241.35 | AJ74: =(O74+P74)-(AM74+AO74) -> 0 | AK74: =(R74+S74+T74+U74)-(AN74+AP74) -> 0 | AL74: DANIEL RAIMUNDO | AM74: 3016.88 | AN74: 250.61 | AO74: 0 | AP74: 0
A75: DANIEL SOARES DA SILVA | B75: Coleta de Lixo Varzea Grande MT | C75: A | D75: N | E75: 3281.61 | F75: 0 | G75: 0 | H75: 0 | I75: 0 | J75: 262.53 | K75: 0 | L75: 0 | M75: 0 | N75: 0 | O75: 3281.61 | P75: 0 | Q75: 0 | R75: 282.38 | S75: 0 | T75: 0 | U75: 0 | V75: 3281.61 | W75: 0 | X75: 0 | Y75: 0 | Z75: 0 | AA75: 122.01 | AB75: 656.32 | AC75: 190.33 | AD75: 1251.04 | AE75: =(E75+F75+G75+H75+I75)-AH75 -> 0 | AF75: =(J75+K75+L75+M75+N75)-AI75 -> 0.01 | AG75: DANIEL SOARES DA SILVA | AH75: 3281.61 | AI75: 262.52 | AJ75: =(O75+P75)-(AM75+AO75) -> 0 | AK75: =(R75+S75+T75+U75)-(AN75+AP75) -> 0 | AL75: DANIEL SOARES DA SILVA | AM75: 3281.61 | AN75: 282.38 | AO75: 0 | AP75: 0
A76: DANIELI HAISSA CHIRE DE QUISPE SILVA | B76: Financeiro | C76: A | D76: N | E76: 2911.87 | F76: 0 | G76: 0 | H76: 0 | I76: 0 | J76: 232.95 | K76: 0 | L76: 0 | M76: 0 | N76: 0 | O76: 2911.87 | P76: 0 | Q76: 0 | R76: 238.01 | S76: 0 | T76: 0 | U76: 0 | V76: 2911.87 | W76: 0 | X76: 0 | Y76: 0 | Z76: 0 | AA76: 108.26 | AB76: 582.37 | AC76: 168.89 | AD76: 1097.53 | AE76: =(E76+F76+G76+H76+I76)-AH76 -> 0 | AF76: =(J76+K76+L76+M76+N76)-AI76 -> 0.01 | AG76: DANIELI HAISSA CHIRE DE QUISPE SILVA | AH76: 2911.87 | AI76: 232.94 | AJ76: =(O76+P76)-(AM76+AO76) -> 0 | AK76: =(R76+S76+T76+U76)-(AN76+AP76) -> 0 | AL76: DANIELI HAISSA CHIRE DE QUISPE | AM76: 2911.87 | AN76: 238.01 | AO76: 0 | AP76: 0
A77: DAVI GERALDO COELHO | B77: CDHU - Piratininga "E1" 56 U.H. | C77: A | D77: N | E77: 2354.01 | F77: 0 | G77: 0 | H77: 0 | I77: 0 | J77: 188.32 | K77: 0 | L77: 0 | M77: 0 | N77: 0 | O77: 2354.01 | P77: 0 | Q77: 0 | R77: 187.54 | S77: 0 | T77: 0 | U77: 0 | V77: 2354.01 | W77: 0 | X77: 0 | Y77: 0 | Z77: 0 | AA77: 87.52 | AB77: 470.8 | AC77: 136.53 | AD77: 882.39 | AE77: =(E77+F77+G77+H77+I77)-AH77 -> 0 | AF77: =(J77+K77+L77+M77+N77)-AI77 -> 0 | AG77: DAVI GERALDO COELHO | AH77: 2354.01 | AI77: 188.32 | AJ77: =(O77+P77)-(AM77+AO77) -> 0 | AK77: =(R77+S77+T77+U77)-(AN77+AP77) -> 0 | AL77: DAVI GERALDO COELHO | AM77: 2354.01 | AN77: 187.54 | AO77: 0 | AP77: 0
A78: DAVI NASCIMENTO DE OLIVEIRA | B78: Financeiro | C78: A | D78: Z | E78: 641.42 | F78: 0 | G78: 0 | H78: 0 | I78: 0 | J78: 12.83 | K78: 0 | L78: 0 | M78: 0 | N78: 0 | O78: 641.42 | P78: 0 | Q78: 0 | R78: 48.1 | S78: 0 | T78: 0 | U78: 0 | V78: 641.42 | W78: 0 | X78: 0 | Y78: 0 | Z78: 0 | AA78: 23.85 | AB78: 128.28 | AC78: 37.2 | AD78: 237.43 | AE78: =(E78+F78+G78+H78+I78)-AH78 -> 0 | AF78: =(J78+K78+L78+M78+N78)-AI78 -> 0.01 | AG78: DAVI NASCIMENTO DE OLIVEIRA | AH78: 641.42 | AI78: 12.82 | AJ78: =(O78+P78)-(AM78+AO78) -> 0 | AK78: =(R78+S78+T78+U78)-(AN78+AP78) -> 0 | AL78: DAVI NASCIMENTO DE OLIVEIRA | AM78: 641.42 | AN78: 48.1 | AO78: 0 | AP78: 0
A79: DAVID MANDELLI DE CASTRO | B79: CDHU - Sabino "E1" "E2" 190 U.H. | C79: A | D79: N | E79: 470.8 | F79: 0 | G79: 0 | H79: 0 | I79: 0 | J79: 37.66 | K79: 0 | L79: 0 | M79: 0 | N79: 0 | O79: 470.8 | P79: 0 | Q79: 0 | R79: 35.31 | S79: 0 | T79: 0 | U79: 0 | V79: 470.8 | W79: 0 | X79: 0 | Y79: 0 | Z79: 0 | AA79: 17.5 | AB79: 94.16 | AC79: 27.31 | AD79: 174.28 | AE79: =(E79+F79+G79+H79+I79)-AH79 -> 0 | AF79: =(J79+K79+L79+M79+N79)-AI79 -> 0 | AG79: DAVID MANDELLI DE CASTRO | AH79: 470.8 | AI79: 37.66 | AJ79: =(O79+P79)-(AM79+AO79) -> 0 | AK79: =(R79+S79+T79+U79)-(AN79+AP79) -> 0 | AL79: DAVID MANDELLI DE CASTRO | AM79: 470.8 | AN79: 35.31 | AO79: 0 | AP79: 0
A80: DAVID RONDON BRANDAO | B80: Coleta de Lixo Varzea Grande MT | C80: A | D80: N | E80: 3666.9 | F80: 0 | G80: 0 | H80: 0 | I80: 0 | J80: 293.35 | K80: 0 | L80: 0 | M80: 0 | N80: 0 | O80: 3666.9 | P80: 0 | Q80: 0 | R80: 328.61 | S80: 0 | T80: 0 | U80: 0 | V80: 3666.9 | W80: 0 | X80: 0 | Y80: 0 | Z80: 0 | AA80: 136.33 | AB80: 733.38 | AC80: 212.68 | AD80: 1411 | AE80: =(E80+F80+G80+H80+I80)-AH80 -> 0 | AF80: =(J80+K80+L80+M80+N80)-AI80 -> 0 | AG80: DAVID RONDON BRANDAO | AH80: 3666.9 | AI80: 293.35 | AJ80: =(O80+P80)-(AM80+AO80) -> 0 | AK80: =(R80+S80+T80+U80)-(AN80+AP80) -> 0 | AL80: DAVID RONDON BRANDAO | AM80: 3666.9 | AN80: 328.61 | AO80: 0 | AP80: 0
A81: DEJAIR BORGES DE ALMEIDA | B81: Coleta de Lixo Varzea Grande MT | C81: A | D81: N | E81: 3436.56 | F81: 0 | G81: 0 | H81: 0 | I81: 0 | J81: 274.92 | K81: 0 | L81: 0 | M81: 0 | N81: 0 | O81: 3436.56 | P81: 0 | Q81: 0 | R81: 300.97 | S81: 0 | T81: 0 | U81: 0 | V81: 3436.56 | W81: 0 | X81: 0 | Y81: 0 | Z81: 0 | AA81: 127.77 | AB81: 687.31 | AC81: 199.32 | AD81: 1315.37 | AE81: =(E81+F81+G81+H81+I81)-AH81 -> 0 | AF81: =(J81+K81+L81+M81+N81)-AI81 -> 0 | AG81: DEJAIR BORGES DE ALMEIDA | AH81: 3436.56 | AI81: 274.92 | AJ81: =(O81+P81)-(AM81+AO81) -> 0 | AK81: =(R81+S81+T81+U81)-(AN81+AP81) -> 0 | AL81: DEJAIR BORGES DE ALMEIDA | AM81: 3436.56 | AN81: 300.97 | AO81: 0 | AP81: 0
A82: DENIS JOSE FERNANDES DA SILVA | B82: Coleta de Lixo Varzea Grande MT | C82: A | D82: N | E82: 799.32 | F82: 0 | G82: 0 | H82: 0 | I82: 0 | J82: 63.95 | K82: 0 | L82: 0 | M82: 0 | N82: 0 | O82: 799.32 | P82: 0 | Q82: 0 | R82: 59.94 | S82: 0 | T82: 0 | U82: 0 | V82: 799.32 | W82: 0 | X82: 0 | Y82: 0 | Z82: 0 | AA82: 29.72 | AB82: 159.86 | AC82: 46.36 | AD82: 295.88 | AE82: =(E82+F82+G82+H82+I82)-AH82 -> 0 | AF82: =(J82+K82+L82+M82+N82)-AI82 -> 0.01 | AG82: DENIS JOSE FERNANDES DA SILVA | AH82: 799.32 | AI82: 63.94 | AJ82: =(O82+P82)-(AM82+AO82) -> 0 | AK82: =(R82+S82+T82+U82)-(AN82+AP82) -> 0 | AL82: DENIS JOSE FERNANDES DA SILVA | AM82: 799.32 | AN82: 59.94 | AO82: 0 | AP82: 0
A83: DERIK HENRIQUE DOS SANTOS ANUNCIACAO | B83: Coleta de Lixo Varzea Grande MT | C83: A | D83: N | E83: 3760.14 | F83: 0 | G83: 0 | H83: 0 | I83: 0 | J83: 300.81 | K83: 0 | L83: 0 | M83: 0 | N83: 0 | O83: 3760.14 | P83: 0 | Q83: 0 | R83: 339.8 | S83: 0 | T83: 0 | U83: 0 | V83: 3760.14 | W83: 0 | X83: 0 | Y83: 0 | Z83: 0 | AA83: 139.8 | AB83: 752.03 | AC83: 218.09 | AD83: 1449.71 | AE83: =(E83+F83+G83+H83+I83)-AH83 -> 0 | AF83: =(J83+K83+L83+M83+N83)-AI83 -> 0 | AG83: DERIK HENRIQUE DOS SANTOS ANUNCIACAO | AH83: 3760.14 | AI83: 300.81 | AJ83: =(O83+P83)-(AM83+AO83) -> 0 | AK83: =(R83+S83+T83+U83)-(AN83+AP83) -> 0 | AL83: DERIK HENRIQUE DOS SANTOS ANUNCIACAO | AM83: 3760.14 | AN83: 339.8 | AO83: 0 | AP83: 0
A84: DIEGO RODRIGO DA CUNHA PARDINHO | B84: CDHU - Ilha Solteira "D" 100 U.H. | C84: D | D84: N | E84: 1716.96 | F84: 0 | G84: 0 | H84: 430.83 | I84: 0 | J84: 137.36 | K84: 0 | L84: 0 | M84: 34.47 | N84: 0 | O84: 1716.96 | P84: 430.83 | Q84: 0 | R84: 130.2 | S84: 32.31 | T84: 0 | U84: 0 | V84: 1716.96 | W84: 0 | X84: 0 | Y84: 0 | Z84: 0 | AA84: 79.85 | AB84: 429.56 | AC84: 124.57 | AD84: 796.49 | AE84: =(E84+F84+G84+H84+I84)-AH84 -> 2147.79 | AF84: =(J84+K84+L84+M84+N84)-AI84 -> 171.83 | AJ84: =(O84+P84)-(AM84+AO84) -> 0 | AK84: =(R84+S84+T84+U84)-(AN84+AP84) -> 0 | AL84: DIEGO RODRIGO DA CUNHA PARDINHO | AM84: 1716.96 | AN84: 130.2 | AO84: 430.83 | AP84: 32.31
A85: DIOMAR MAGALHAES DE SOUZA | B85: Coleta de Lixo Varzea Grande MT | C85: A | D85: N | E85: 3671.1 | F85: 0 | G85: 0 | H85: 0 | I85: 0 | J85: 293.69 | K85: 0 | L85: 0 | M85: 0 | N85: 0 | O85: 3671.1 | P85: 0 | Q85: 0 | R85: 329.12 | S85: 0 | T85: 0 | U85: 0 | V85: 3671.1 | W85: 0 | X85: 0 | Y85: 0 | Z85: 0 | AA85: 136.49 | AB85: 734.22 | AC85: 212.92 | AD85: 1412.75 | AE85: =(E85+F85+G85+H85+I85)-AH85 -> 0 | AF85: =(J85+K85+L85+M85+N85)-AI85 -> 0.01 | AG85: DIOMAR MAGALHAES DE SOUZA | AH85: 3671.1 | AI85: 293.68 | AJ85: =(O85+P85)-(AM85+AO85) -> 0 | AK85: =(R85+S85+T85+U85)-(AN85+AP85) -> 0 | AL85: DIOMAR MAGALHAES DE SOUZA | AM85: 3671.1 | AN85: 329.12 | AO85: 0 | AP85: 0
A86: DIONES DA CONCEICAO ALVARENGA | B86: Coleta de Lixo Varzea Grande MT | C86: A | D86: N | E86: 6698.45 | F86: 0 | G86: 0 | H86: 0 | I86: 0 | J86: 535.88 | K86: 0 | L86: 0 | M86: 0 | N86: 0 | O86: 6698.45 | P86: 0 | Q86: 0 | R86: 739.28 | S86: 0 | T86: 0 | U86: 0 | V86: 6698.45 | W86: 0 | X86: 643.28 | Y86: 0 | Z86: 0 | AA86: 249.04 | AB86: 1339.69 | AC86: 388.51 | AD86: 2716.52 | AE86: =(E86+F86+G86+H86+I86)-AH86 -> 0 | AF86: =(J86+K86+L86+M86+N86)-AI86 -> 0.01 | AG86: DIONES DA CONCEICAO ALVARENGA | AH86: 6698.45 | AI86: 535.87 | AJ86: =(O86+P86)-(AM86+AO86) -> 0 | AK86: =(R86+S86+T86+U86)-(AN86+AP86) -> 0 | AL86: DIONES DA CONCEICAO ALVARENGA | AM86: 6698.45 | AN86: 739.28 | AO86: 0 | AP86: 0
A87: DIRCEU JOSE MERLINO NUNES | B87: Coleta de Lixo Varzea Grande MT | C87: A | D87: N | E87: 3925.28 | F87: 0 | G87: 0 | H87: 0 | I87: 0 | J87: 314.02 | K87: 0 | L87: 0 | M87: 0 | N87: 0 | O87: 3925.28 | P87: 0 | Q87: 0 | R87: 359.62 | S87: 0 | T87: 0 | U87: 0 | V87: 3925.28 | W87: 0 | X87: 0 | Y87: 0 | Z87: 0 | AA87: 145.94 | AB87: 785.06 | AC87: 227.67 | AD87: 1518.28 | AE87: =(E87+F87+G87+H87+I87)-AH87 -> 0 | AF87: =(J87+K87+L87+M87+N87)-AI87 -> 0 | AG87: DIRCEU JOSE MERLINO NUNES | AH87: 3925.28 | AI87: 314.02 | AJ87: =(O87+P87)-(AM87+AO87) -> 0 | AK87: =(R87+S87+T87+U87)-(AN87+AP87) -> 0 | AL87: DIRCEU JOSE MERLINO NUNES | AM87: 3925.28 | AN87: 359.62 | AO87: 0 | AP87: 0
A88: DIVINO SANTOS REIS | B88: Coleta de Lixo Varzea Grande MT | C88: A | D88: N | E88: 6363.82 | F88: 0 | G88: 0 | H88: 0 | I88: 0 | J88: 509.11 | K88: 0 | L88: 0 | M88: 0 | N88: 0 | O88: 6363.82 | P88: 0 | Q88: 0 | R88: 692.43 | S88: 0 | T88: 0 | U88: 0 | V88: 6363.82 | W88: 0 | X88: 519.59 | Y88: 0 | Z88: 0 | AA88: 236.6 | AB88: 1272.76 | AC88: 369.1 | AD88: 2570.9 | AE88: =(E88+F88+G88+H88+I88)-AH88 -> 0 | AF88: =(J88+K88+L88+M88+N88)-AI88 -> 0.01 | AG88: DIVINO SANTOS REIS | AH88: 6363.82 | AI88: 509.1 | AJ88: =(O88+P88)-(AM88+AO88) -> 0 | AK88: =(R88+S88+T88+U88)-(AN88+AP88) -> 0 | AL88: DIVINO SANTOS REIS | AM88: 6363.82 | AN88: 692.43 | AO88: 0 | AP88: 0
A89: DOUGLAS ORTIS DE OLIVEIRA | B89: Coleta de Lixo Varzea Grande MT | C89: A | D89: N | E89: 1948.53 | F89: 0 | G89: 0 | H89: 0 | I89: 0 | J89: 155.88 | K89: 0 | L89: 0 | M89: 0 | N89: 0 | O89: 1948.53 | P89: 0 | Q89: 0 | R89: 151.04 | S89: 0 | T89: 0 | U89: 0 | V89: 1948.53 | W89: 0 | X89: 0 | Y89: 0 | Z89: 0 | AA89: 72.44 | AB89: 389.71 | AC89: 113.01 | AD89: 726.21 | AE89: =(E89+F89+G89+H89+I89)-AH89 -> 0 | AF89: =(J89+K89+L89+M89+N89)-AI89 -> 0 | AG89: DOUGLAS ORTIS DE OLIVEIRA | AH89: 1948.53 | AI89: 155.88 | AJ89: =(O89+P89)-(AM89+AO89) -> 0 | AK89: =(R89+S89+T89+U89)-(AN89+AP89) -> 0 | AL89: DOUGLAS ORTIS DE OLIVEIRA | AM89: 1948.53 | AN89: 151.04 | AO89: 0 | AP89: 0
A90: EDINEI SILVA BATISTA | B90: Embasa Lote 02 - Municipio de Paramirim BA | C90: A | D90: N | E90: 2973.88 | F90: 0 | G90: 0 | H90: 0 | I90: 0 | J90: 237.91 | K90: 0 | L90: 0 | M90: 0 | N90: 0 | O90: 2973.88 | P90: 0 | Q90: 0 | R90: 245.45 | S90: 0 | T90: 0 | U90: 0 | V90: 2973.88 | W90: 0 | X90: 0 | Y90: 0 | Z90: 0 | AA90: 110.57 | AB90: 594.78 | AC90: 172.49 | AD90: 1123.28 | AE90: =(E90+F90+G90+H90+I90)-AH90 -> 0 | AF90: =(J90+K90+L90+M90+N90)-AI90 -> 0 | AG90: EDINEI SILVA BATISTA | AH90: 2973.88 | AI90: 237.91 | AJ90: =(O90+P90)-(AM90+AO90) -> 0 | AK90: =(R90+S90+T90+U90)-(AN90+AP90) -> 0 | AL90: EDINEI SILVA BATISTA | AM90: 2973.88 | AN90: 245.45 | AO90: 0 | AP90: 0
A91: EDMILSON JOAQUIM DA SILVA | B91: Coleta de Lixo Varzea Grande MT | C91: A | D91: N | E91: 3958.11 | F91: 0 | G91: 0 | H91: 0 | I91: 0 | J91: 316.65 | K91: 0 | L91: 0 | M91: 0 | N91: 0 | O91: 3958.11 | P91: 0 | Q91: 0 | R91: 363.56 | S91: 0 | T91: 0 | U91: 0 | V91: 3958.11 | W91: 0 | X91: 0 | Y91: 0 | Z91: 0 | AA91: 147.16 | AB91: 791.62 | AC91: 229.57 | AD91: 1531.91 | AE91: =(E91+F91+G91+H91+I91)-AH91 -> 0 | AF91: =(J91+K91+L91+M91+N91)-AI91 -> 0.01 | AG91: EDMILSON JOAQUIM DA SILVA | AH91: 3958.11 | AI91: 316.64 | AJ91: =(O91+P91)-(AM91+AO91) -> 0 | AK91: =(R91+S91+T91+U91)-(AN91+AP91) -> 0 | AL91: EDMILSON JOAQUIM DA SILVA | AM91: 3958.11 | AN91: 363.56 | AO91: 0 | AP91: 0
A92: EDMILTON PEREIRA DE ARRUDA | B92: Coleta de Lixo Varzea Grande MT | C92: A | D92: N | E92: 3128.6 | F92: 0 | G92: 0 | H92: 0 | I92: 0 | J92: 250.29 | K92: 0 | L92: 0 | M92: 0 | N92: 0 | O92: 3128.6 | P92: 0 | Q92: 0 | R92: 264.02 | S92: 0 | T92: 0 | U92: 0 | V92: 3128.6 | W92: 0 | X92: 0 | Y92: 0 | Z92: 0 | AA92: 116.32 | AB92: 625.72 | AC92: 181.46 | AD92: 1187.52 | AE92: =(E92+F92+G92+H92+I92)-AH92 -> 0 | AF92: =(J92+K92+L92+M92+N92)-AI92 -> 0.01 | AG92: EDMILTON PEREIRA DE ARRUDA | AH92: 3128.6 | AI92: 250.28 | AJ92: =(O92+P92)-(AM92+AO92) -> 0 | AK92: =(R92+S92+T92+U92)-(AN92+AP92) -> 0 | AL92: EDMILTON PEREIRA DE ARRUDA | AM92: 3128.6 | AN92: 264.02 | AO92: 0 | AP92: 0
A93: EDSON ANSELMO GUANDALIN | B93: CDHU - Balbinos "D" 19 U.H. | C93: A | D93: N | E93: 4500 | F93: 0 | G93: 0 | H93: 0 | I93: 0 | J93: 360 | K93: 0 | L93: 0 | M93: 0 | N93: 0 | O93: 4500 | P93: 0 | Q93: 0 | R93: 431.5 | S93: 0 | T93: 0 | U93: 0 | V93: 4500 | W93: 0 | X93: 0 | Y93: 0 | Z93: 0 | AA93: 167.31 | AB93: 900 | AC93: 261 | AD93: 1759.81 | AE93: =(E93+F93+G93+H93+I93)-AH93 -> 0 | AF93: =(J93+K93+L93+M93+N93)-AI93 -> 0 | AG93: EDSON ANSELMO GUANDALIN | AH93: 4500 | AI93: 360 | AJ93: =(O93+P93)-(AM93+AO93) -> 0 | AK93: =(R93+S93+T93+U93)-(AN93+AP93) -> 0 | AL93: EDSON ANSELMO GUANDALIN | AM93: 4500 | AN93: 431.5 | AO93: 0 | AP93: 0
A94: EDUARDO AMARO LINS DOS SANTOS | B94: Coleta de Lixo Varzea Grande MT | C94: A | D94: N | E94: 3022.5 | F94: 0 | G94: 0 | H94: 0 | I94: 0 | J94: 241.8 | K94: 0 | L94: 0 | M94: 0 | N94: 0 | O94: 3022.5 | P94: 0 | Q94: 0 | R94: 251.28 | S94: 0 | T94: 0 | U94: 0 | V94: 3022.5 | W94: 0 | X94: 0 | Y94: 0 | Z94: 0 | AA94: 112.37 | AB94: 604.5 | AC94: 175.31 | AD94: 1143.46 | AE94: =(E94+F94+G94+H94+I94)-AH94 -> 0 | AF94: =(J94+K94+L94+M94+N94)-AI94 -> 0 | AG94: EDUARDO AMARO LINS DOS SANTOS | AH94: 3022.5 | AI94: 241.8 | AJ94: =(O94+P94)-(AM94+AO94) -> 0 | AK94: =(R94+S94+T94+U94)-(AN94+AP94) -> 0 | AL94: EDUARDO AMARO LINS DOS SANTOS | AM94: 3022.5 | AN94: 251.28 | AO94: 0 | AP94: 0
A95: EDUARDO HENRIQUE LOPES LOURENCO | B95: Coleta de Lixo Varzea Grande MT | C95: P | D95: N | E95: 2140.67 | F95: 0 | G95: 0 | H95: 0 | I95: 0 | J95: 171.25 | K95: 0 | L95: 0 | M95: 0 | N95: 0 | O95: 2140.67 | P95: 0 | Q95: 0 | R95: 168.34 | S95: 0 | T95: 0 | U95: 0 | V95: 2140.67 | W95: 0 | X95: 0 | Y95: 0 | Z95: 0 | AA95: 79.59 | AB95: 428.13 | AC95: 124.16 | AD95: 800.22 | AE95: =(E95+F95+G95+H95+I95)-AH95 -> 0 | AF95: =(J95+K95+L95+M95+N95)-AI95 -> 0 | AG95: EDUARDO HENRIQUE LOPES LOURENCO | AH95: 2140.67 | AI95: 171.25 | AJ95: =(O95+P95)-(AM95+AO95) -> 0 | AK95: =(R95+S95+T95+U95)-(AN95+AP95) -> 0 | AL95: EDUARDO HENRIQUE LOPES LOURENCO | AM95: 2140.67 | AN95: 168.34 | AO95: 0 | AP95: 0
A96: ELIANA APARECIDA DOMINGUES EMILIO | B96: CDHU - Duartina "E1" "E2" 128 U.H. | C96: D | D96: N | E96: 83.61 | F96: 2533.49 | G96: 210.47 | H96: 1683.77 | I96: 0 | J96: 6.69 | K96: 202.68 | L96: 16.84 | M96: 134.7 | N96: 0 | O96: 83.61 | P96: 1894.24 | Q96: 0 | R96: 6.27 | S96: 146.16 | T96: 0 | U96: 0 | V96: 83.61 | W96: 0 | X96: 0 | Y96: 0 | Z96: 0 | AA96: 73.53 | AB96: 395.57 | AC96: 114.72 | AD96: 736.25 | AE96: =(E96+F96+G96+H96+I96)-AH96 -> 4511.34 | AF96: =(J96+K96+L96+M96+N96)-AI96 -> 360.91 | AJ96: =(O96+P96)-(AM96+AO96) -> 0 | AK96: =(R96+S96+T96+U96)-(AN96+AP96) -> 0 | AL96: ELIANA APARECIDA DOMINGUES EMILIO | AM96: 83.61 | AN96: 6.27 | AO96: 1894.24 | AP96: 146.16
A97: ELITON RICARDO RIBEIRO | B97: BR-488 e 459 - Lorena/Piquete/Aparecida | C97: A | D97: N | E97: 5565.56 | F97: 0 | G97: 0 | H97: 0 | I97: 0 | J97: 445.24 | K97: 0 | L97: 0 | M97: 0 | N97: 0 | O97: 5565.56 | P97: 0 | Q97: 0 | R97: 580.68 | S97: 0 | T97: 0 | U97: 0 | V97: 5565.56 | W97: 0 | X97: 217.22 | Y97: 0 | Z97: 0 | AA97: 206.92 | AB97: 1113.11 | AC97: 322.8 | AD97: 2223.52 | AE97: =(E97+F97+G97+H97+I97)-AH97 -> 0 | AF97: =(J97+K97+L97+M97+N97)-AI97 -> 0 | AG97: ELITON RICARDO RIBEIRO | AH97: 5565.56 | AI97: 445.24 | AJ97: =(O97+P97)-(AM97+AO97) -> 0 | AK97: =(R97+S97+T97+U97)-(AN97+AP97) -> 0 | AL97: ELITON RICARDO RIBEIRO | AM97: 5565.56 | AN97: 580.68 | AO97: 0 | AP97: 0
A98: ELIVELTON DE OLIVEIRA PASSOS | B98: Coleta de Lixo Varzea Grande MT | C98: A | D98: N | E98: 3671.99 | F98: 0 | G98: 0 | H98: 0 | I98: 0 | J98: 293.76 | K98: 0 | L98: 0 | M98: 0 | N98: 0 | O98: 3671.99 | P98: 0 | Q98: 0 | R98: 329.22 | S98: 0 | T98: 0 | U98: 0 | V98: 3671.99 | W98: 0 | X98: 0 | Y98: 0 | Z98: 0 | AA98: 136.52 | AB98: 734.4 | AC98: 212.98 | AD98: 1413.11 | AE98: =(E98+F98+G98+H98+I98)-AH98 -> 0 | AF98: =(J98+K98+L98+M98+N98)-AI98 -> 0.01 | AG98: ELIVELTON DE OLIVEIRA PASSOS | AH98: 3671.99 | AI98: 293.75 | AJ98: =(O98+P98)-(AM98+AO98) -> 0 | AK98: =(R98+S98+T98+U98)-(AN98+AP98) -> 0 | AL98: ELIVELTON DE OLIVEIRA PASSOS | AM98: 3671.99 | AN98: 329.22 | AO98: 0 | AP98: 0
A99: ELY CAMPOS DE ABREU | B99: Embasa Lote 02 - Municipio de Paramirim BA | C99: A | D99: N | E99: 6816.14 | F99: 0 | G99: 0 | H99: 0 | I99: 0 | J99: 545.29 | K99: 0 | L99: 0 | M99: 0 | N99: 0 | O99: 6816.14 | P99: 0 | Q99: 0 | R99: 755.76 | S99: 0 | T99: 0 | U99: 0 | V99: 6816.14 | W99: 0 | X99: 634.65 | Y99: 0 | Z99: 0 | AA99: 253.42 | AB99: 1363.23 | AC99: 395.34 | AD99: 2767.74 | AE99: =(E99+F99+G99+H99+I99)-AH99 -> 0 | AF99: =(J99+K99+L99+M99+N99)-AI99 -> 0 | AG99: ELY CAMPOS DE ABREU | AH99: 6816.14 | AI99: 545.29 | AJ99: =(O99+P99)-(AM99+AO99) -> 0 | AK99: =(R99+S99+T99+U99)-(AN99+AP99) -> 0 | AL99: ELY CAMPOS DE ABREU | AM99: 6816.14 | AN99: 755.76 | AO99: 0 | AP99: 0
A100: ERICK ANTONNY DE JESUS SANTOS | B100: CDHU - Duartina "E1" "E2" 128 U.H. | C100: A | D100: N | E100: 1426.39 | F100: 0 | G100: 0 | H100: 0 | I100: 0 | J100: 114.11 | K100: 0 | L100: 0 | M100: 0 | N100: 0 | O100: 1426.39 | P100: 0 | Q100: 0 | R100: 106.97 | S100: 0 | T100: 0 | U100: 0 | V100: 1426.39 | W100: 0 | X100: 0 | Y100: 0 | Z100: 0 | AA100: 53.03 | AB100: 285.28 | AC100: 82.73 | AD100: 528.01 | AE100: =(E100+F100+G100+H100+I100)-AH100 -> 0 | AF100: =(J100+K100+L100+M100+N100)-AI100 -> 0 | AG100: ERICK ANTONNY DE JESUS SANTOS | AH100: 1426.39 | AI100: 114.11 | AJ100: =(O100+P100)-(AM100+AO100) -> 0 | AK100: =(R100+S100+T100+U100)-(AN100+AP100) -> 0 | AL100: ERICK ANTONNY DE JESUS SANTOS | AM100: 1426.39 | AN100: 106.97 | AO100: 0 | AP100: 0
A101: Erinaldo Ferreira Guterres | B101: Financeiro | C101: P | D101: N | E101: 0 | F101: 0 | G101: 0 | H101: 0 | I101: 0 | J101: 0 | K101: 0 | L101: 0 | M101: 0 | N101: 0 | O101: 0 | P101: 0 | Q101: 0 | R101: 0 | S101: 0 | T101: 0 | U101: 0 | V101: 0 | W101: 0 | X101: 0 | Y101: 0 | Z101: 0 | AA101: 0 | AB101: 0 | AC101: 0 | AD101: 0 | AE101: =(E101+F101+G101+H101+I101)-AH101 -> 0 | AF101: =(J101+K101+L101+M101+N101)-AI101 -> 0 | AJ101: =(O101+P101)-(AM101+AO101) -> 0 | AK101: =(R101+S101+T101+U101)-(AN101+AP101) -> 0
A102: FABIANO DA CONCEICAO | B102: Coleta de Lixo Varzea Grande MT | C102: A | D102: N | E102: 6075.86 | F102: 0 | G102: 0 | H102: 0 | I102: 0 | J102: 486.07 | K102: 0 | L102: 0 | M102: 0 | N102: 0 | O102: 6075.86 | P102: 0 | Q102: 0 | R102: 652.12 | S102: 0 | T102: 0 | U102: 0 | V102: 6075.86 | W102: 0 | X102: 413.14 | Y102: 0 | Z102: 0 | AA102: 225.89 | AB102: 1215.17 | AC102: 352.4 | AD102: 2445.59 | AE102: =(E102+F102+G102+H102+I102)-AH102 -> 0 | AF102: =(J102+K102+L102+M102+N102)-AI102 -> 0.01 | AG102: FABIANO DA CONCEICAO | AH102: 6075.86 | AI102: 486.06 | AJ102: =(O102+P102)-(AM102+AO102) -> 0 | AK102: =(R102+S102+T102+U102)-(AN102+AP102) -> 0 | AL102: FABIANO DA CONCEICAO | AM102: 6075.86 | AN102: 652.12 | AO102: 0 | AP102: 0
A103: Fabiano Dacie | B103: Financeiro | C103: A | D103: N | E103: 3988.92 | F103: 0 | G103: 0 | H103: 0 | I103: 0 | J103: 319.11 | K103: 0 | L103: 0 | M103: 0 | N103: 0 | O103: 3988.92 | P103: 0 | Q103: 0 | R103: 367.25 | S103: 0 | T103: 0 | U103: 0 | V103: 3988.92 | W103: 0 | X103: 0 | Y103: 0 | Z103: 0 | AA103: 148.3 | AB103: 797.78 | AC103: 231.36 | AD103: 1544.7 | AE103: =(E103+F103+G103+H103+I103)-AH103 -> 0 | AF103: =(J103+K103+L103+M103+N103)-AI103 -> 0 | AG103: FABIANO DACIE | AH103: 3988.92 | AI103: 319.11 | AJ103: =(O103+P103)-(AM103+AO103) -> 0 | AK103: =(R103+S103+T103+U103)-(AN103+AP103) -> 0 | AL103: FABIANO DACIE | AM103: 3988.92 | AN103: 367.25 | AO103: 0 | AP103: 0
A104: FABRICIO DE JESUS | B104: Embasa Lote 02 - Municipio de Paramirim BA | C104: A | D104: N | E104: 2323.8 | F104: 0 | G104: 0 | H104: 0 | I104: 0 | J104: 185.9 | K104: 0 | L104: 0 | M104: 0 | N104: 0 | O104: 2323.8 | P104: 0 | Q104: 0 | R104: 184.82 | S104: 0 | T104: 0 | U104: 0 | V104: 2323.8 | W104: 0 | X104: 0 | Y104: 0 | Z104: 0 | AA104: 86.4 | AB104: 464.76 | AC104: 134.78 | AD104: 870.76 | AE104: =(E104+F104+G104+H104+I104)-AH104 -> 0 | AF104: =(J104+K104+L104+M104+N104)-AI104 -> 0 | AG104: FABRICIO DE JESUS | AH104: 2323.8 | AI104: 185.9 | AJ104: =(O104+P104)-(AM104+AO104) -> 0 | AK104: =(R104+S104+T104+U104)-(AN104+AP104) -> 0 | AL104: FABRICIO DE JESUS | AM104: 2323.8 | AN104: 184.82 | AO104: 0 | AP104: 0
A105: FERNANDA MONISE DIAS QUEIROZ | B105: CDHU - Birigui "D" 143 U.H. | C105: A | D105: N | E105: 1070.01 | F105: 0 | G105: 0 | H105: 0 | I105: 0 | J105: 85.6 | K105: 0 | L105: 0 | M105: 0 | N105: 0 | O105: 1070.01 | P105: 0 | Q105: 0 | R105: 80.25 | S105: 0 | T105: 0 | U105: 0 | V105: 1070.01 | W105: 0 | X105: 0 | Y105: 0 | Z105: 0 | AA105: 39.78 | AB105: 214 | AC105: 62.06 | AD105: 396.09 | AE105: =(E105+F105+G105+H105+I105)-AH105 -> 0 | AF105: =(J105+K105+L105+M105+N105)-AI105 -> 0 | AG105: FERNANDA MONISE DIAS QUEIROZ | AH105: 1070.01 | AI105: 85.6 | AJ105: =(O105+P105)-(AM105+AO105) -> 0 | AK105: =(R105+S105+T105+U105)-(AN105+AP105) -> 0 | AL105: FERNANDA MONISE DIAS QUEIROZ | AM105: 1070.01 | AN105: 80.25 | AO105: 0 | AP105: 0
...

Sheet RATEIOS
A3: Rótulos de Linha | B3: Soma de Valor FGTS na Guia | C3: Soma de IRRF | E3: Soma de Valor FGTS na Guia | F3: Soma de IRRF
A4: BR-060/GO - Goiania GO | C4: 0 | E4: 0 | F4: 0
A5: BR-488 e 459 - Lorena/Piquete/Aparecida | B5: 1988.74 | C5: 217.22 | E5: 1988.74 | F5: 217.22
A6: CDHU - Balbinos "D" 19 U.H. | B6: 802.57 | C6: 0 | E6: 802.57 | F6: 0
A7: CDHU - Birigui "D" 143 U.H. | B7: 2594.84 | C7: 1752.3 | E7: 2594.84 | F7: 1752.3
A8: CDHU - Bocaina "H1" "H2" 96 U.H. | B8: 1812.89 | C8: 0 | E8: 1812.89 | F8: 0
A9: CDHU - Duartina "E1" "E2" 128 U.H. | B9: 3437.65 | C9: 1453.82 | E9: 3437.65 | F9: 1453.82
A10: CDHU - Ilha Solteira "D" 100 U.H. | B10: 1817.25 | C10: 0 | E10: 1817.25 | F10: 0
A11: CDHU - Mirandopolis "D" 259 U.H. | B11: 234.32 | C11: 0 | E11: 234.32 | F11: 0
A12: CDHU - Piratininga "E1" 56 U.H. | B12: 1674.4 | C12: 674.97 | E12: 1674.4 | F12: 674.97
A13: CDHU - Sabino "E1" "E2" 190 U.H. | B13: 2402.25 | C13: 92.21 | E13: 2402.25 | F13: 92.21
A14: Coleta de Lixo Varzea Grande MT | B14: 44578.71 | C14: 21405.27 | E14: 44578.71 | F14: 21405.27
A15: DER - Ipaussu | C15: 0 | E15: 0 | F15: 0
A16: Embasa Lote 02 - Municipio de Guanambi BA | C16: 0 | E16: 0 | F16: 0
A17: Embasa Lote 02 - Municipio de Paramirim BA | B17: 2515.51 | C17: 634.65 | E17: 2515.51 | F17: 634.65
A18: Financeiro | B18: 2791.84 | C18: 2711.65 | E18: 2791.84 | F18: 2711.65
A19: Oficina | B19: 3126.49 | C19: 1422.52 | E19: 3126.49 | F19: 1422.52
A20: Total Geral | B20: 69777.46 | C20: 30364.61

Sheet eSocial
A1: Resumo da Folha de Pagamento
A2: Bases de Cálculo | B2: Valor
A3: 11 - Base de cálculo da contribuição previdenciária | B3: 936260.22
A4: Contribuições do Segurado | B4: Valor Descontado | C4: Valor Calculado
A5: Valor total da contribuição | B5: 88330.81 | C5: 88330.81 | D5: =C5-B5 -> 0
A6: Estabelecimento 04.327.690/0001-49
A7: Estabelecimento 00.900.255/9107-74
A8: Estabelecimento 00.900.255/9018-79
A9: Estabelecimento 00.900.255/9076-75
A10: Estabelecimento 00.900.296/3171-79
A11: Estabelecimento 00.900.255/9056-72
A12: Informações consolidadas das contribuições sociais
A13: Codigo Receita | B13: Valor | C13: Valor Suspenso
A14: 1082-01 - CP SEGURADOS - EMPREGADOS/AVULSOS | B14: 87398.5 | C14: - | D14: =B14+B15 -> 88330.81
A15: 1099-01 - CP SEGURADOS - CONTRIBUINTES INDIVIDUAIS - 11% | B15: 932.31 | C15: -
A16: 1138-01 - CP PATRONAL - EMPREGADOS/AVULSOS | B16: 185296.92 | C16: -
A17: 1138-04 - CP PATRONAL - CONTRIBUINTES INDIVIDUAIS | B17: 1955.11 | C17: -
A18: 1170-01 - CP TERCEIROS - SALÁRIO EDUCAÇÃO | B18: 23162.08 | C18: - | D18: =B18+B19+B20+B21+B22 -> 53735.95
A19: 1176-01 - CP TERCEIROS - INCRA | B19: 1852.94 | C19: -
A20: 1181-01 - CP TERCEIROS - SENAI | B20: 9264.81 | C20: -
A21: 1184-01 - CP TERCEIROS - SESI | B21: 13897.25 | C21: -
A22: 1200-01 - CP TERCEIROS - SEBRAE | B22: 5558.87 | C22: -
A23: 1646-01 - CP PATRONAL - GILRAT AJUSTADO | B23: 34445.74 | C23: -

Sheet DCTFWeb
A1: DÉBITOS APURADOS | E1: SALDO A PAGAR
B2: Tributos/Códigos de Receita | D2: PA Débito | F2: Débito Apurado
A3: #VALUE!
A4: #VALUE! | B4: Total Apurado Empresa 04.327.690/0001-49 | E4: 394228.49 | G4: 394228.49
B5: #VALUE! | C5: Total CONTRIBUIÇÃO PREVIDENCIÁRIA SEGURADOS | E5: 88330.81 | G5: 88330.81
C6: 1082-01 CP SEGURADOS - EMPREGADOS/AVULSO | D6: 46266 | E6: 87398.5 | G6: 87398.5
C7: 1099-01 CP SEGURADOS - CONTRIBUINTES INDIVIDUAIS - 11% | D7: 46266 | E7: 932.31 | G7: 932.31
B8: #VALUE! | C8: Total CONTRIBUIÇÃO PREVIDENCIÁRIA PATRONAL | E8: 139727.82 | G8: 139727.82
C9: 1138-01 CP PATRONAL - EMPREGADOS/AVULSOS | D9: 46266 | E9: 116176.15 | G9: 116176.15
C10: 1138-04 CP PATRONAL - CONTRIBUINTES INDIVIDUAIS | D10: 46266 | E10: 1955.11 | G10: 1955.11
C11: 1646-01 CP PATRONAL - GILRAT AJUSTADO | D11: 46266 | E11: 21596.56 | G11: 21596.56
B12: #VALUE! | C12: Total CONTRIBUIÇÃO PARA OUTRAS ENTIDADES E FUNDOS | E12: 33691.06 | G12: 33691.06
C13: 1170-01 CP TERCEIROS - SALÁRIO EDUCAÇÃO | D13: 46266 | E13: 14522.01 | G13: 14522.01
C14: 1176-01 CP TERCEIROS - INCRA | D14: 46266 | E14: 1161.76 | G14: 1161.76
C15: 1181-01 CP TERCEIROS - SENAI | D15: 46266 | E15: 5808.8 | G15: 5808.8
C16: 1184-01 CP TERCEIROS - SESI | D16: 46266 | E16: 8713.21 | G16: 8713.21
C17: 1200-01 CP TERCEIROS - SEBRAE | D17: 46266 | E17: 3485.28 | G17: 3485.28
B18: #VALUE! | C18: Total IRRF | E18: 30463.96 | G18: 30463.96
C19: 0561-07 IRRF - RD TRB ASSAL PAÍS/AUS NO EXT A SERV PAÍS | D19: 46266 | E19: 30463.96 | G19: 30463.96
B20: #VALUE! | C20: Total Apurado - CNO 90.025.59018/79 | E20: 16759.21 | G20: 16759.21
B21: #VALUE! | C21: Total Apurado - CNO 90.025.59056/72 | E21: 26385.26 | G21: 26385.26
B22: #VALUE! | C22: Total Apurado - CNO 90.025.59076/75 | E22: 6599.49 | G22: 6599.49
B23: #VALUE! | C23: Total Apurado - CNO 90.025.59107/74 | E23: 39981.23 | G23: 39981.23
B24: #VALUE! | C24: Total Apurado - CNO 90.029.63171/79 | E24: 12289.65 | G24: 12289.65

Sheet GRRF
A1: NOME | B1: CHAPA | C1: CODTIPO | D1: FGTS QUITACAO | E1: FGTS MES ANTERIOR | F1: FGTS AVISO PREVIO | G1: FGTS ARTIGO 22 | H1: FGTS 13 SALARIO INDENIZADO | I1: FGTS 13 Sal rescisao | J1: TOTAL | K1: JÁ RECOLHIDO
A2: ALVARO RUPPENTHAL | B2: 00001831 | C2: N | D2: 46.08 | E2: 268.36 | G2: 861.15 | I2: 144.08 | J2: 1319.67 | K2: =D2+F2+H2+I2 -> 190.16
A3: ANTONIO MARCOS DE PAULA LINO | B3: 00001459 | C3: N | D3: 466.74 | F3: 412.9 | G3: 5454.03 | H3: 29.39 | I3: 146.95 | J3: 6510.01 | K3: =D3+F3+H3+I3 -> 1055.98
A4: BENTO PEREIRA AMADO | B4: 00001644 | C4: N | D4: 191.69 | F4: 23.46 | G4: 1648.61 | I4: 177.14 | J4: 2040.9 | K4: =D4+F4+H4+I4 -> 392.29
A5: CLAUDIO MODESTO | B5: 00001586 | C5: N | D5: 38.96 | E5: 176.17 | F5: 37.68 | G5: 1999.14 | I5: 125.62 | J5: 2377.57 | K5: =D5+F5+H5+I5 -> 202.26
A6: DANIEL DA SILVA FERREIRA | B6: 00001758 | C6: N | D6: 213.32 | F6: 270.14 | G6: 1092.36 | H6: 23.09 | I6: 207.81 | J6: 1806.72 | K6: =D6+F6+H6+I6 -> 714.36
A7: DIEGO RODRIGO DA CUNHA PARDINHO | B7: 00001968 | C7: N | D7: 137.35 | I7: 34.46 | J7: 171.81 | K7: =D7+F7+H7+I7 -> 171.81
A8: ELIANA APARECIDA DOMINGUES EMILIO | B8: 00001695 | C8: N | D8: 6.68 | E8: 188.65 | F8: 202.67 | G8: 748.66 | H8: 16.83 | I8: 134.7 | J8: 1298.19 | K8: =D8+F8+H8+I8 -> 360.88
A9: JORGE LUIS IBARRA GOMEZ | B9: 00001794 | C9: N | D9: 225.28 | F9: 269.35 | G9: 1083.88 | H9: 23.11 | I9: 208.03 | J9: 1809.65 | K9: =D9+F9+H9+I9 -> 725.77
A10: JOSE DOS SANTOS | B10: 00001701 | C10: N | D10: 417.76 | F10: 344.1 | G10: 1639.9 | H10: 29.62 | I10: 266.57 | J10: 2697.95 | K10: =D10+F10+H10+I10 -> 1058.05
A11: JOSE SEBASTIAO DOS SANTOS | B11: 00001650 | C11: N | D11: 231.34 | F11: 330.11 | G11: 2012.11 | H11: 24.33 | I11: 218.97 | J11: 2816.86 | K11: =D11+F11+H11+I11 -> 804.75
A12: REGINALDO CARVALHO SANTOS | B12: 00001971 | C12: N | E12: 128.72 | G12: 56.51 | I12: 12.56 | J12: 197.79 | K12: =D12+F12+H12+I12 -> 12.56
A13: ROMUALDO ADRIANO MARTINEZ PERES | B13: 00001930 | C13: N | D13: 5.61 | E13: 245.99 | F13: 325.72 | G13: 546.61 | H13: 27.14 | I13: 81.43 | J13: 1232.5 | K13: =D13+F13+H13+I13 -> 439.9
A14: VITOR CARLOS TAVARES | B14: 00001859 | C14: N | D14: 39.83 | E14: 283.13 | F14: 236.84 | G14: 983.62 | H14: 20.38 | I14: 142.7 | J14: 1706.5 | K14: =D14+F14+H14+I14 -> 439.75
D15: =SUM(D2:D14) -> 2020.64 | E15: =SUM(E2:E14) -> 1291.02 | F15: =SUM(F2:F14) -> 2452.97 | G15: =SUM(G2:G14) -> 18126.58 | H15: =SUM(H2:H14) -> 193.89 | I15: =SUM(I2:I14) -> 1901.02 | J15: =SUM(J2:J14) -> 25986.12 | K15: =SUM(K2:K14) -> 6568.52

Sheet EMPRESTIMOS
A1: CODCOLIGADA | B1: NOME | C1: CODSITUACAO | D1: VALOR | F1: Rótulos de Linha | G1: Soma de Valor
A2: 1 | B2: ADILSON GABRIEL DIAS FERREIRA MIRANDA | C2: A | D2: 629.12 | E2: =D2-G2 -> 0 | F2: ADILSON GABRIEL DIAS FERREIRA MIRANDA | G2: 629.12 | I2: =G2-J2 -> 0 | J2: 629.12 | K2: Emprestimo Consignado - Competência: set/2026 Períodos: 5 - ADILSON GABRIEL DIAS FERREIRA MIRANDA- 11075354170- 104- 3090- 159032250
A3: 1 | B3: ADRIANO FERREIRA | C3: A | D3: 483 | E3: =D3-G3 -> 0 | F3: ADRIANO FERREIRA | G3: 483 | I3: =G3-J3 -> 0 | J3: 483 | K3: Emprestimo Consignado - Competência: set/2026 Períodos: 5 - ADRIANO FERREIRA- 38433029878- 104- 3090- 082193433
A4: 1 | B4: ALEX MATHEUS TAVARES CORREA | C4: A | D4: 120.57 | E4: =D4-G4 -> 0 | F4: ALEX MATHEUS TAVARES CORREA | G4: 120.57 | I4: =G4-J4 -> 0 | J4: 120.57 | K4: Emprestimo Consignado - Competência: set/2026 Períodos: 5 - ALEX MATHEUS TAVARES CORREA- 05985413144- 104- 3090- 159035942
A5: 1 | B5: ALLAN PETERSON RODRIGUES DE FREITAS | C5: A | D5: 1397.69 | E5: =D5-G5 -> 0 | F5: ALLAN PETERSON RODRIGUES DE FREITAS | G5: 1397.69 | I5: =G5-J5 -> 0 | J5: 1397.69 | K5: Emprestimo Consignado - Competência: set/2026 Períodos: 5 - ALLAN PETERSON RODRIGUES DE FREITAS- 06837574159- 104- 3090- 157265789
A6: 1 | B6: ALTEVI JUARI PEREIRA | C6: A | D6: 707.74 | E6: =D6-G6 -> 0 | F6: ALTEVI JUARI PEREIRA | G6: 707.74 | I6: =G6-J6 -> 0 | J6: 707.74 | K6: Emprestimo Consignado - Competência: set/2026 Períodos: 5 - ALTEVI JUARI PEREIRA- 89202171149- 104- 3090- 157266254
A7: 1 | B7: ANDERSON DA CONCEIÇÃO SANTOS | C7: A | D7: 536.57 | E7: =D7-G7 -> 0 | F7: ANDERSON DA CONCEICAO SANTOS | G7: 536.57 | I7: =G7-J7 -> 0 | J7: 536.57 | K7: Emprestimo Consignado - Competência: set/2026 Períodos: 5 - ANDERSON DA CONCEIÇÃO SANTOS- 11463603550- 104- 3090- 154086867
A8: 1 | B8: ANDERSON NEVES FERREIRA | C8: A | D8: 498.81 | E8: =D8-G8 -> 0 | F8: ANDERSON NEVES FERREIRA | G8: 498.81 | I8: =G8-J8 -> 0 | J8: 498.81 | K8: Emprestimo Consignado - Competência: set/2026 Períodos: 5 - ANDERSON NEVES FERREIRA- 98933833153- 104- 3090- 159029535
A9: 1 | B9: ANDRE HENRIQUE SANTOS DE PAULA | C9: A | D9: 533.41 | E9: =D9-G9 -> 0 | F9: ANDRE HENRIQUE SANTOS DE PAULA | G9: 533.41 | I9: =G9-J9 -> 0 | J9: 533.41 | K9: Emprestimo Consignado - Competência: set/2026 Períodos: 5 - ANDRE HENRIQUE SANTOS DE PAULA- 06694872100- 104- 3090- 142857170
A10: 1 | B10: ANTONIO MARTINS DA SILVA | C10: A | D10: 623.63 | E10: =D10-G10 -> 0 | F10: ANTONIO MARTINS DA SILVA | G10: 623.63 | I10: =G10-J10 -> 0 | J10: 623.63 | K10: Emprestimo Consignado - Competência: set/2026 Períodos: 5 - ANTONIO MARTINS DA SILVA- 06189796117- 104- 3090- 157265428
A11: 1 | B11: ARNALDO FERREIRA DE MELO | C11: D | D11: 53.09 | E11: =D11-G11 -> 0 | F11: ARNALDO FERREIRA DE MELO | G11: 53.09 | I11: =G11-J11 -> 0 | J11: 53.09 | K11: Emprestimo Consignado - Competência: set/2026 Períodos: 5 - ARNALDO FERREIRA DE MELO- 08678807407- 104- 3090- 157264855
A12: 1 | B12: CARLITO PAULA DOS SANTOS | C12: A | D12: 1024.87 | E12: =D12-G12 -> 0 | F12: CARLITO PAULA DOS SANTOS | G12: 1024.87 | I12: =G12-J12 -> 0 | J12: 1024.87 | K12: Emprestimo Consignado - Competência: set/2026 Períodos: 5 - CARLITO PAULA DOS SANTOS- 36271056806- 104- 3090- 178323257
A13: 1 | B13: CARLOS ANDRE OLIVEIRA DA SILVA | C13: A | D13: 574.63 | E13: =D13-G13 -> 0 | F13: CARLOS ANDRE OLIVEIRA DA SILVA | G13: 574.63 | I13: =G13-J13 -> 0 | J13: 574.63 | K13: Emprestimo Consignado - Competência: set/2026 Períodos: 5 - CARLOS ANDRE OLIVEIRA DA SILVA- 52477668811- 104- 3090- 159174616
... A18: 1 | B18: CLEIVISON APARECIDO DA SILVA | C18: A | D18: 387.11 | E18: =D18-G18 -> 0 | F18: CLEIVISON APARECIDO DA SILVA | G18: 387.11 | I18: =G18-J18 -> 0 | J18: 387.11 | K18: Emprestimo Consignado - Competência: set/2026 Períodos: 5 - CLEIVISON APARECIDO DA SILVA- 92633285287- 104- 3090- 157266564
A19: 1 | B19: DANIEL DA SILVA FERREIRA | C19: D | D19: 1438.76 | E19: =D19-G19 -> 1438.76 | I19: =G19-J19 -> -1438.76 | J19: 1438.76 | K19: Emprestimo Consignado - Competência: set/2026 Períodos: 5 - DANIEL DA SILVA FERREIRA- 61458088375- 104- 3090- 159036124
A20: 1 | B20: DANIEL DOS SANTOS SOUZA | C20: A | D20: 146.05 | E20: =D20-G20 -> 0 | F20: DANIEL DOS SANTOS SOUZA | G20: 146.05 | I20: =G20-J20 -> 0 | J20: 146.05 | K20: Emprestimo Consignado - Competência: set/2026 Períodos: 5 - DANIEL DOS SANTOS SOUZA- 04056719110- 104- 3090- 157265738
A21: 1 | B21: DEJAIR BORGES DE ALMEIDA | C21: A | D21: 410.26 | E21: =D21-G21 -> 0 | F21: DEJAIR BORGES DE ALMEIDA | G21: 410.26 | I21: =G21-J21 -> 0 | J21: 410.26 | K21: Emprestimo Consignado - Competência: set/2026 Períodos: 5 - DEJAIR BORGES DE ALMEIDA- 05526813185- 104- 3090- 159032137
A22: 1 | B22: DERIK HENRIQUE DOS SANTOS ANUNCIACAO | C22: A | D22: 691.34 | E22: =D22-G22 -> 0 | F22: DERIK HENRIQUE DOS SANTOS ANUNCIACAO | G22: 691.34 | I22: =G22-J22 -> 0 | J22: 691.34 | K22: Emprestimo Consignado - Competência: set/2026 Períodos: 5 - DERIK HENRIQUE DOS SANTOS ANUNCIACAO- 07132055127- 104- 3090- 157265347
A23: 1 | B23: DOUGLAS ORTIS DE OLIVEIRA | C23: A | D23: 428.35 | E23: =D23-G23 -> 0 | F23: DOUGLAS ORTIS DE OLIVEIRA | G23: 428.35 | I23: =G23-J23 -> 0 | J23: 428.35 | K23: Emprestimo Consignado - Competência: set/2026 Períodos: 5 - DOUGLAS ORTIS DE OLIVEIRA- 06591997180- 104- 3090- 159032218
A24: 1 | B24: EDMILTON PEREIRA DE ARRUDA | C24: A | D24: 537.99 | E24: =D24-G24 -> 0 | F24: EDMILTON PEREIRA DE ARRUDA | G24: 537.99 | I24: =G24-J24 -> 0 | J24: 537.99 | K24: Emprestimo Consignado - Competência: set/2026 Períodos: 5 - EDMILTON PEREIRA DE ARRUDA- 04634736128- 104- 3090- 157263840
A25: 1 | B25: EDUARDO HENRIQUE LOPES LOURENCO | C25: P | D25: 690.32 | E25: =D25-G25 -> 0 | F25: EDUARDO HENRIQUE LOPES LOURENCO | G25: 690.32 | I25: =G25-J25 -> 0 | J25: 690.32 | K25: Emprestimo Consignado - Competência: set/2026 Períodos: 5 - EDUARDO HENRIQUE LOPES LOURENCO- 71158215185- 104- 3090- 157265126
A26: 1 | B26: ELIANA APARECIDA DOMINGUES EMILIO | C26: D | D26: 2610.49 | E26: =D26-G26 -> 2610.49 | I26: =G26-J26 -> -2610.49 | J26: 2610.49 | K26: Emprestimo Consignado - Competência: set/2026 Períodos: 5 - ELIANA APARECIDA DOMINGUES EMILIO- 33713192880- 104- 3090- 188455210
A27: 1 | B27: FERNANDA MONISE DIAS QUEIROZ | C27: A | D27: 64.68 | E27: =D27-G27 -> 0 | F27: FERNANDA MONISE DIAS QUEIROZ | G27: 64.68 | I27: =G27-J27 -> 0 | J27: 64.68 | K27: Emprestimo Consignado - Competência: set/2026 Períodos: 5 - FERNANDA MONISE DIAS QUEIROZ- 16028364428- 104- 3090- 163709375
A28: 1 | B28: FERNANDO URBANO | C28: A | D28: 325.92 | E28: =D28-G28 -> 0 | F28: FERNANDO URBANO | G28: 325.92 | I28: =G28-J28 -> 0 | J28: 325.92 | K28: Emprestimo Consignado - Competência: set/2026 Períodos: 5 - FERNANDO URBANO- 10101689837- 104- 2785- 866587750
A29: 1 | B29: GUILHERME DOS SANTOS CAVALCANTE | C29: A | D29: 649.52 | E29: =D29-G29 -> 0 | F29: GUILHERME DOS SANTOS CAVALCANTE | G29: 649.52 | I29: =G29-J29 -> 0 | J29: 649.52 | K29: Emprestimo Consignado - Competência: set/2026 Períodos: 5 - GUILHERME DOS SANTOS CAVALCANTE- 08987248216- 104- 3090- 159035276
A30: 1 | B30: GUILHERME GABRIEL PARRA | C30: A | D30: 458.7 | E30: =D30-G30 -> 0 | F30: GUILHERME GABRIEL PARRA | G30: 458.7 | I30: =G30-J30 -> 0 | J30: 458.7 | K30: Emprestimo Consignado - Competência: set/2026 Períodos: 5 - GUILHERME GABRIEL PARRA- 46546999889- 104- 3090- 932525862
A31: 1 | B31: ISMAEL CESAR DE SOUZA ESPIRITO SANTO | C31: A | D31: 592.08 | E31: =D31-G31 -> 0 | F31: ISMAEL CESAR DE SOUZA ESPIRITO SANTO | G31: 592.08 | I31: =G31-J31 -> 0 | J31: 592.08 | K31: Emprestimo Consignado - Competência: set/2026 Períodos: 5 - ISMAEL CESAR DE SOUZA ESPIRITO SANTO- 70173394108- 104- 3090- 159029462
A32: 1 | B32: ISRAEL BORGES DA SILVA | C32: A | D32: 390.48 | E32: =D32-G32 -> 0 | F32: ISRAEL BORGES DA SILVA | G32: 390.48 | I32: =G32-J32 -> 0 | J32: 390.48 | K32: Emprestimo Consignado - Competência: set/2026 Períodos: 5 - ISRAEL BORGES DA SILVA- 60981225390- 104- 3090- 159029845
A33: 1 | B33: IVANILDO RODRIGUES DE SOUZA | C33: A | D33: 642.24 | E33: =D33-G33 -> 0 | F33: IVANILDO RODRIGUES DE SOUZA | G33: 642.24 | I33: =G33-J33 -> 0 | J33: 642.24 | K33: Emprestimo Consignado - Competência: set/2026 Períodos: 5 - IVANILDO RODRIGUES DE SOUZA- 90061268100- 104- 3090- 157263875
A34: 1 | B34: JAMES CARVALHO ALMEIDA | C34: A | D34: 641.66 | E34: =D34-G34 -> 0 | F34: JAMES CARVALHO ALMEIDA | G34: 641.66 | I34: =G34-J34 -> 0 | J34: 641.66 | K34: Emprestimo Consignado - Competência: set/2026 Períodos: 5 - JAMES CARVALHO ALMEIDA- 99036614368- 104- 3090- 142251825
A35: 1 | B35: JEFF ALCIUS | C35: A | D35: 462.39 | E35: =D35-G35 -> 0 | F35: JEFF ALCIUS | G35: 462.39 | I35: =G35-J35 -> 0 | J35: 462.39 | K35: Emprestimo Consignado - Competência: set/2026 Períodos: 5 - JEFF ALCIUS- 70469807210- 104- 3090- 158968236
A36: 1 | B36: JEREMIAS VIEIRA DE LIMA | C36: A | D36: 232 | E36: =D36-G36 -> 0 | F36: JEREMIAS VIEIRA DE LIMA | G36: 232 | I36: =G36-J36 -> 0 | J36: 232 | K36: Emprestimo Consignado - Competência: set/2026 Períodos: 5 - JEREMIAS VIEIRA DE LIMA- 10282135308- 104- 3090- 142807440
A37: 1 | B37: JOADIR MENDES DA SILVA | C37: A | D37: 1076.3 | E37: =D37-G37 -> 0 | F37: JOADIR MENDES DA SILVA | G37: 1076.3 | I37: =G37-J37 -> 0 | J37: 1076.3 | K37: Emprestimo Consignado - Competência: set/2026 Períodos: 5 - JOADIR MENDES DA SILVA- 05402462127- 104- 3090- 157266939
A38: 1 | B38: JOAO CARLOS DE OLIVEIRA | C38: A | D38: 417.29 | E38: =D38-G38 -> 0 | F38: JOAO CARLOS DE OLIVEIRA | G38: 417.29 | I38: =G38-J38 -> 0 | J38: 417.29 | K38: Emprestimo Consignado - Competência: set/2026 Períodos: 5 - JOAO CARLOS DE OLIVEIRA- 33615374878- 104- 0319- 927463242
... A40: 1 | B40: JOCELINO FERNANDO DA SILVA | C40: A | D40: 514.28 | E40: =D40-G40 -> 0 | F40: JOCELINO FERNANDO DA SILVA | G40: 514.28 | I40: =G40-J40 -> 0 | J40: 514.28 | K40: Emprestimo Consignado - Competência: set/2026 Períodos: 5 - JOCELINO FERNANDO DA SILVA- 70364852135- 104- 3090- 142857227
A41: 1 | B41: JOSE SEBASTIAO DOS SANTOS | C41: D | D41: 3994.47 | E41: =D41-G41 -> 3994.47 | I41: =G41-J41 -> -3994.47 | J41: 3994.47 | K41: Emprestimo Consignado - Competência: set/2026 Períodos: 5 - JOSE SEBASTIAO DOS SANTOS- 81485026415- 104- 3090- 166910497
A42: 1 | B42: JOSE SERGIO DA SILVA | C42: D | D42: 1880.19 | E42: =D42-G42 -> 0 | F42: JOSE SERGIO DA SILVA | G42: 1880.19 | I42: =G42-J42 -> 0 | J42: 1880.19 | K42: Emprestimo Consignado - Competência: set/2026 Períodos: 5 - JOSE SERGIO DA SILVA- 03664054113- 104- 3090- 199843284
A43: 1 | B43: JOSE VALENTIM LEITE | C43: A | D43: 281.18 | E43: =D43-G43 -> 0 | F43: JOSE VALENTIM LEITE | G43: 281.18 | I43: =G43-J43 -> 0 | J43: 281.18 | K43: Emprestimo Consignado - Competência: set/2026 Períodos: 5 - JOSE VALENTIM LEITE- 10026082870- 104- 3090- 154086875
A44: 1 | B44: JOSENILSON ARMANDO DA SILVA | C44: A | D44: 645.66 | E44: =D44-G44 -> 0 | F44: JOSENILSON ARMANDO DA SILVA | G44: 645.66 | I44: =G44-J44 -> 0 | J44: 645.66 | K44: Emprestimo Consignado - Competência: set/2026 Períodos: 5 - JOSENILSON ARMANDO DA SILVA- 06034023130- 104- 3090- 159029616
A45: 1 | B45: JOSIMAR RODRIGUES NOBRES | C45: A | D45: 482 | E45: =D45-G45 -> 0 | F45: JOSIMAR RODRIGUES NOBRES | G45: 482 | I45: =G45-J45 -> 0 | J45: 482 | K45: Emprestimo Consignado - Competência: set/2026 Períodos: 5 - JOSIMAR RODRIGUES NOBRES- 00981190103- 104- 3090- 159029713
A46: 1 | B46: JOSUE CAVALCANTE DOS SANTOS | C46: A | D46: 1051.34 | E46: =D46-G46 -> 0 | F46: JOSUE CAVALCANTE DOS SANTOS | G46: 1051.34 | I46: =G46-J46 -> 0 | J46: 1051.34 | K46: Emprestimo Consignado - Competência: set/2026 Períodos: 5 - JOSUE CAVALCANTE DOS SANTOS- 02200388993- 104- 3090- 187980664
A47: 1 | B47: LEANDRO ALVES VIANA | C47: A | D47: 650.18 | E47: =D47-G47 -> 0 | F47: LEANDRO ALVES VIANA | G47: 650.18 | I47: =G47-J47 -> 0 | J47: 650.18 | K47: Emprestimo Consignado - Competência: set/2026 Períodos: 5 - LEANDRO ALVES VIANA- 03740431164- 104- 3090- 157265533
A48: 1 | B48: LEANDRO ORIVALDO DE ARRUDA | C48: A | D48: 620.44 | E48: =D48-G48 -> 0 | F48: LEANDRO ORIVALDO DE ARRUDA | G48: 620.44 | I48: =G48-J48 -> 0 | J48: 620.44 | K48: Emprestimo Consignado - Competência: set/2026 Períodos: 5 - LEANDRO ORIVALDO DE ARRUDA- 03881521178- 104- 3090- 157265355
A49: 1 | B49: LEANDRO VIEIRA DA SILVA | C49: A | D49: 1210.15 | E49: =D49-G49 -> 0 | F49: LEANDRO VIEIRA DA SILVA | G49: 1210.15 | I49: =G49-J49 -> 0 | J49: 1210.15 | K49: Emprestimo Consignado - Competência: set/2026 Períodos: 5 - LEANDRO VIEIRA DA SILVA- 07428513464- 104- 3090- 159004818
A50: 1 | B50: LINDOVAL FERREIRA DE OLIVEIRA | C50: A | D50: 374.3 | E50: =D50-G50 -> 0 | F50: LINDOVAL FERREIRA DE OLIVEIRA | G50: 374.3 | I50: =G50-J50 -> 0 | J50: 374.3 | K50: Emprestimo Consignado - Competência: set/2026 Períodos: 5 - LINDOVAL FERREIRA DE OLIVEIRA- 72123451991- 104- 3090- 091082070
A51: 1 | B51: LUCAS DE MOURA QUEIROZ | C51: A | D51: 687.69 | E51: =D51-G51 -> 0 | F51: LUCAS DE MOURA QUEIROZ | G51: 687.69 | I51: =G51-J51 -> 0 | J51: 687.69 | K51: Emprestimo Consignado - Competência: set/2026 Períodos: 5 - LUCAS DE MOURA QUEIROZ- 70327954124- 104- 3090- 091081979
A52: 1 | B52: LUCIANO DO CARMO ARAUJO | C52: A | D52: 968.74 | E52: =D52-G52 -> 0 | F52: LUCIANO DO CARMO ARAUJO | G52: 968.74 | I52: =G52-J52 -> 0 | J52: 968.74 | K52: Emprestimo Consignado - Competência: set/2026 Períodos: 5 - LUCIANO DO CARMO ARAUJO- 90417844115- 104- 3090- 159004850
A53: 1 | B53: LUIS FERNANDO DOS SANTOS | C53: D | D53: 2827.21 | E53: =D53-G53 -> 0 | F53: LUIS FERNANDO DOS SANTOS | G53: 2827.21 | I53: =G53-J53 -> 0 | J53: 2827.21 | K53: Emprestimo Consignado - Competência: set/2026 Períodos: 5 - LUIS FERNANDO DOS SANTOS- 23196224899- 104- 3090- 406294221
... A66: 1 | B66: RODRIGO DA SILVA BRANDAO | C66: A | D66: 776.6 | E66: =D66-G66 -> 0 | F66: RODRIGO DA SILVA BRANDAO | G66: 776.6 | I66: =G66-J66 -> 0 | J66: 776.6 | K66: Emprestimo Consignado - Competência: set/2026 Períodos: 5 - RODRIGO DA SILVA BRANDAO- 43967089800- 104- 1153- 631118389
A67: 1 | B67: ROMUALDO ADRIANO MARTINEZ PERES | C67: D | D67: 604.16 | E67: =D67-G67 -> 604.16 | I67: =G67-J67 -> -604.16 | J67: 604.16 | K67: Emprestimo Consignado - Competência: set/2026 Períodos: 5 - ROMUALDO ADRIANO MARTINEZ PERES- 02187158110- 104- 3090- 088057191
A68: 1 | B68: ROSEMAR SILVA DE OLIVEIRA | C68: A | D68: 367.54 | E68: =D68-G68 -> 0 | F68: ROSEMAR SILVA DE OLIVEIRA | G68: 367.54 | I68: =G68-J68 -> 0 | J68: 367.54 | K68: Emprestimo Consignado - Competência: set/2026 Períodos: 5 - ROSEMAR SILVA DE OLIVEIRA- 12077094761- 104- 3090- 158967973
A69: 1 | B69: SAMUEL MACHADO COSTA | C69: A | D69: 617.43 | E69: =D69-G69 -> 0 | F69: SAMUEL MACHADO COSTA | G69: 617.43 | I69: =G69-J69 -> 0 | J69: 617.43 | K69: Emprestimo Consignado - Competência: set/2026 Períodos: 5 - SAMUEL MACHADO COSTA- 03460885181- 104- 3090- 192847837
A70: 1 | B70: SANDRA LOPES | C70: A | D70: 565.75 | E70: =D70-G70 -> 0 | F70: SANDRA LOPES | G70: 565.75 | I70: =G70-J70 -> 0 | J70: 565.75 | K70: Emprestimo Consignado - Competência: set/2026 Períodos: 5 - SANDRA LOPES- 32805696808- 104- 3090- 189368567
A71: 1 | B71: SEVERINO JOSE DA SILVA | C71: A | D71: 220.22 | E71: =D71-G71 -> 0 | F71: SEVERINO JOSE DA SILVA | G71: 220.22 | I71: =G71-J71 -> 0 | J71: 220.22 | K71: Emprestimo Consignado - Competência: set/2026 Períodos: 5 - SEVERINO JOSE DA SILVA- 11680303406- 104- 3090- 088057221
A72: 1 | B72: TAMER DE SOUZA JUSTI | C72: A | D72: 336.35 | E72: =D72-G72 -> 0 | F72: TAMER DE SOUZA JUSTI | G72: 336.35 | I72: =G72-J72 -> 0 | J72: 336.35 | K72: Emprestimo Consignado - Competência: set/2026 Períodos: 5 - TAMER DE SOUZA JUSTI- 44094220810- 104- 3090- 940112229
A73: 1 | B73: VICTOR HUGO CAMPOS MONGE | C73: A | D73: 692.57 | E73: =D73-G73 -> 0 | F73: VICTOR HUGO CAMPOS MONGE | G73: 692.57 | I73: =G73-J73 -> 0 | J73: 692.57 | K73: Emprestimo Consignado - Competência: set/2026 Períodos: 5 - VICTOR HUGO CAMPOS MONGE- 06421241166- 104- 3090- 159034555
A74: 1 | B74: VICTOR HUGO SOUZA SALES | C74: A | D74: 325.45 | E74: =D74-G74 -> 0 | F74: VICTOR HUGO SOUZA SALES | G74: 325.45 | I74: =G74-J74 -> 0 | J74: 325.45 | K74: Emprestimo Consignado - Competência: set/2026 Períodos: 5 - VICTOR HUGO SOUZA SALES- 46086416893- 104- 3090- 080240590
A75: 1 | B75: WALLAF BRUNO LIMA DA SILVA | C75: A | D75: 474.8 | E75: =D75-G75 -> 0 | F75: WALLAF BRUNO LIMA DA SILVA | G75: 474.8 | I75: =G75-J75 -> 0 | J75: 474.8 | K75: Emprestimo Consignado - Competência: set/2026 Períodos: 5 - WALLAF BRUNO LIMA DA SILVA- 06416051109- 104- 3090- 159034644
A76: 1 | B76: WEDRIQUI DA SILVA | C76: A | D76: 654.72 | E76: =D76-G76 -> 0 | F76: WEDRIQUI DA SILVA | G76: 654.72 | I76: =G76-J76 -> 0 | J76: 654.72 | K76: Emprestimo Consignado - Competência: set/2026 Períodos: 5 - WEDRIQUI DA SILVA- 71724771116- 104- 3090- 093852140
A77: 1 | B77: WILLIAM CAMPOS DE MORAES | C77: A | D77: 610.36 | E77: =D77-G77 -> 0 | F77: WILLIAM CAMPOS DE MORAES | G77: 610.36 | I77: =G77-J77 -> 0 | J77: 610.36 | K77: Emprestimo Consignado - Competência: set/2026 Períodos: 5 - WILLIAM CAMPOS DE MORAES- 71886127140- 104- 3090- 159032145
A78: 1 | B78: WILLIAN SILVA DE OLIVEIRA | C78: A | D78: 626.65 | E78: =D78-G78 -> 0 | F78: WILLIAN SILVA DE OLIVEIRA | G78: 626.65 | I78: =G78-J78 -> 0 | J78: 626.65 | K78: Emprestimo Consignado - Competência: set/2026 Períodos: 5 - WILLIAN SILVA DE OLIVEIRA- 03235864148- 104- 3090- 155115534
A79: 1 | B79: WILSON MARCELINO DO NASCIMENTO | C79: A | D79: 665.87 | E79: =D79-G79 -> 0 | F79: WILSON MARCELINO DO NASCIMENTO | G79: 665.87 | I79: =G79-J79 -> 0 | J79: 665.87 | K79: Emprestimo Consignado - Competência: set/2026 Períodos: 5 - WILSON MARCELINO DO NASCIMENTO- 55171303134- 104- 3090- 157264936
A80: 1 Total | D80: =SUBTOTAL(9,D2:D79) -> 55417.49 | E80: =D80-G80 -> 8647.88 | F80: Total Geral | G80: 46769.61 | J80: =SUM(J2:J79) -> 55417.49
E82: =D80-E80 -> 46769.61

Sheet EMPRESAS
A1: EMPRESAS
A2: CONCRETA
A3: JPL
A4: JC GOMES
